Workbook

Sheet NYP General Assessment
L6: HDR | M6: True
B7: Type: NYP General Assessment | L7: HDR | M7: True
L8: HDR | M8: True
L9: HDR | M9: True
B10: Name | D10: Enter the name | F10: =GENERAL!D4 -> PeriWatch Vigilance - 9181 - NYP General Assessment | L10: HDR | M10: True
L11: HDR | M11: True
B12: Short Name | D12: Question / Description | F12: Answer / Value
B14: Name | D14: Enter the name | L14: ATTR
B16: Short Name | D16: Question / Description | F16: Answer / Value | H16: Comment
H17: =IF(F18=B32003,C32003,"") -> Enter Response | M17: =IF(F18=B32003,E32003,"") -> 2
B18: Information Question 01 | D18: APPLICATION/PRODUCT/SERVICE NAME: | F18: Select here to enter response | G18: * | H18: =GENERAL!D12 -> PeriWatch Vigilance | L18: CTRL | N18: 201633
H19: =IF(F20=B32004,C32004,"") -> Enter Response | M19: =IF(F20=B32004,E32004,"") -> 2
B20: NYP: Information Question 01.5 | D20: IT SYSTEM REQUEST NUMBER: | F20: Select here to enter a response | G20: * | H20: =GENERAL!D14 -> 9181 | L20: CTRL | N20: 207848
H21: =IF(F22=B32005,C32005,"") -> Enter Response | M21: =IF(F22=B32005,E32005,"") -> 2
B22: Information Question 02 | D22: Name: | F22: Select here to enter response | G22: * | H22: =GENERAL!D16 -> Michael Kennedy | L22: CTRL | N22: 201635
H23: =IF(F24=B32006,C32006,"") -> Enter Response | M23: =IF(F24=B32006,E32006,"") -> 2
B24: Information Question 03 | D24: Email: | F24: Select here to enter response | G24: * | H24: =GENERAL!D18 -> Perigen Fetal Surveillance | L24: CTRL | N24: 201637
H25: =IF(F26=B32007,C32007,"") -> Enter Response | M25: =IF(F26=B32007,E32007,"") -> 2
B26: Information Question 04 | D26: Phone number: | F26: Select here to enter response | G26: * | H26: =GENERAL!D20 -> 0 | L26: CTRL | N26: 201639
H27: =IF(F28=B32008,C32008,"") -> Enter Response | M27: =IF(F28=B32008,E32008,"") -> 2
B28: Information Question 05 | D28: DATE SUBMITTED (mm/dd/yy): | F28: Select here to enter response | G28: * | H28: =GENERAL!D22 -> 44531 | L28: CTRL | N28: 201641
H29: =IF(F30=B32009,C32009,"") -> Enter Response | M29: =IF(F30=B32009,E32009,"") -> 2
B30: Information Question 06 | D30: EXPECTED GO-LIVE DATE (mm/dd/yy): | F30: Select here to enter response | G30: * | H30: =GENERAL!D24 -> 0 | L30: CTRL | N30: 201643
B32: Information Question 07 | D32: Will this application or system be HOSTED by NYP or the Vendor? | F32: =GENERAL!D26 -> NYP | G32: * | L32: CTRL | N32: 201645
B34: Information Question 08 | D34: Will this application or system be SUPPORTED by NYP or the Vendor? | F34: =GENERAL!D28 -> Vendor | G34: * | L34: CTRL | N34: 201648
H35: =IF(F36=B32014,C32014,"") -> Enter Response | M35: =IF(F36=B32014,E32014,"") -> 2
B36: Information Question 09 | D36: Description of product features, functionality and/or services: | F36: Select here to enter response | G36: * | H36: =GENERAL!D30 -> OB Fetal Surveillance, archiving, alerts and early warning functions | L36: CTRL | N36: 201651
B38: System Architecture Diagram | D38: Please insert a graphic image containing a diagram of the recommended system architecture | F38: =GENERAL!D34 -> Select here to add attachment | G38: * | H38: =GENERAL!E34 -> * | J38: =IF(F38=B32015,D32015,"") -> Please attach system architecture diagram | L38: CTRL | N38: 201653
H39: =IF(F40=B32017,C32017,"") -> Please confirm DESIGN Tab review: | M39: =IF(F40=B32017,E32017,"") -> 2
B40: NYP: Information IT Resources | D40: Will this PMO request require technical resources from IT such as Server and Database resources? OR Does this PMO request introduce a new network-connected device (such as a biomedical, audio/visual, or building management) or changes to an existing device or service, that will require ongoing connectivity and support? | F40: =GENERAL!D36 -> Yes | G40: * | H40: =GENERAL!F36 -> This PMO requires IT involvement to create the required environmnets (servers, DBs) for PeriWatch Vigilance. | L40: CTRL | N40: 211983
B42: Information Question 10 | D42: Does your application include a technology that can be utilized to provide a highly available system architecture, which meets the Tiering requirements of the system? NOTE: If answering NO, disregard the remaining BCDR questions!! | F42: =BCDR!D5 -> No | G42: * | L42: CTRL | N42: 201656
B44: Will the server / workstation be built and managed by NYP? ( | D44: Does this request include a Medical Device/ BioMed Component? NOTE: If answering NO, disregard the remaining Medical Device questions!! | F44: =GENERAL!D38 -> No | G44: * | L44: CTRL | N44: 201680
B46: Information Question 19 | D46: Doest this request include a cloud-based or externally-hosted component? NOTE: If answering NO, disregard the remaining Vendor Hosted questions!! | F46: =GENERAL!D40 -> No | G46: * | L46: CTRL | N46: 201683
H47: =IF(F48=B32025,C32025,"") -> Enter Response | M47: =IF(F48=B32025,E32025,"") -> 2
B48: BCDR RTO & RPO Tiering Level | D48: Please describe what technologies, native to your application, that can be utilized to provide a highly available system architecture that meets the "RTO and "RPO" of the appropriate Tiering level. | F48: Select here to enter response | G48: * | H48: =BCDR!D7 -> There are no native technologies. PeriWatch Vigilance relies on SQL clustering for DB HA and Vmware HA capabilities. Typically, PeriWatch Vigilance is not considered tier 1 application like fetal surveillance. | L48: CTRL | N48: 201686
H49: =IF(F50=B32027,C32027,"") -> Enter Response | M49: =IF(F50=B32027,E32027,"") -> 2
B50: BCDR Interoperability & Support | D50: Please let us know below, if your application provides interoperability and support for these technologies, or encounters general issues with using these technologies to provide high availability. | F50: Select here to enter response | G50: * | H50: =BCDR!D9 -> Same as above. | L50: CTRL | N50: 201689
H51: =IF(F52=B32029,C32029,"") -> Enter Response | M51: =IF(F52=B32029,E32029,"") -> 2
B52: Vendor Information | D52: Vendor Name: | F52: Select here to enter response | G52: * | H52: =SECURITY!D6 -> PeriGen Inc. | L52: CTRL | N52: 201725
H53: =IF(F54=B32030,C32030,"") -> Enter Response | M53: =IF(F54=B32030,E32030,"") -> 2
B54: Solution Information | D54: Application/Solution/Service Name: | F54: Select here to enter response | G54: * | H54: =SECURITY!D7 -> PeriWatch Vigilance | L54: CTRL | N54: 201727
H55: =IF(F56=B32031,C32031,"") -> Enter Response | M55: =IF(F56=B32031,E32031,"") -> 2
B56: Software Information | D56: Software Version: | F56: Select here to enter response | G56: * | H56: =SECURITY!D8 -> 2021.1 | L56: CTRL | N56: 201729
H57: =IF(F58=B32032,C32032,"") -> Enter Response | M57: =IF(F58=B32032,E32032,"") -> 2
B58: Application or Service Information | D58: Short Description of Application/Solution or Service being provided: | F58: Select here to enter response | G58: * | H58: =SECURITY!D9 -> Obstetrical Early Warning system | L58: CTRL | N58: 201731
H59: =IF(F60=B32035,C32035,"") | M59: =IF(F60=B32035,E32035,"")
B60: Application / System Data /Type of Data Created / Received / Processed / Maintained / Stored / Accessed (PHI) | D60: Is Protected Health Information (PHI) data created, processed, stored, or received by the system or application (or accessed by the vendor/contractor in case of professional services projects)? | F60: =SECURITY!D14 -> Yes | G60: * | L60: CTRL | N60: 201733
H61: =IF(F62=B32038,C32038,"") | M61: =IF(F62=B32038,E32038,"")
B62: Application / System Data /Type of Data Created / Received / Processed / Maintained / Stored / Accessed (PII) | D62: Is Personally Identifiable Information (PII) data created, processed, stored, or received by the system or application (or accessed by the vendor/contractor in case of professional services projects)? | F62: =SECURITY!D15 -> No | G62: * | L62: CTRL | N62: 201737
H63: =IF(F64=B32041,C32041,"") | M63: =IF(F64=B32041,E32041,"")
B64: Application / System Data /Type of Data Created / Received / Processed / Maintained / Stored / Accessed (PCI) | D64: Is Payment Card Industry (PCI) data created, processed, stored, or received by the system or application (or accessed by the vendor/contractor in case of professional services projects)? | F64: =SECURITY!D16 -> No | G64: * | L64: CTRL | N64: 201741
H65: =IF(F66=B32044,C32044,"") | M65: =IF(F66=B32044,E32044,"")
B66: Application / System Data /Type of Data Created / Received / Processed / Maintained / Stored / Accessed (Payroll Data) | D66: Is Payroll Data created, processed, stored, or received by the system or application (or accessed by the vendor/contractor in case of professional services projects)? | F66: =SECURITY!D17 -> No | G66: * | L66: CTRL | N66: 201745
H67: =IF(F68=B32047,C32047,"") | M67: =IF(F68=B32047,E32047,"")
B68: Application / System Data /Type of Data Created / Received / Processed / Maintained / Stored / Accessed (Financial Records) | D68: Is Financial Records data (e.g. revenue) created, processed, stored, or received by the system or application (or accessed by the vendor/contractor in case of professional services projects)? | F68: =SECURITY!D18 -> No | G68: * | L68: CTRL | N68: 201749
H69: =IF(F70=B32048,C32048,"") | M69: =IF(F70=B32048,E32048,"")
B70: Application / System Data /Type of Data Created / Received / Processed / Maintained / Stored / Accessed (Other) | D70: Is there any OTHER data not previously mentioned that is created, processed, stored, or received by the system or application (or accessed by the vendor/contractor in case of professional services projects)? If so, please specify. | F70: =SECURITY!D20 -> No | G70: * | H70: =SECURITY!G20 -> 0 | L70: CTRL | N70: 201753
H71: =IF(F72=B32053,C32053,"") | M71: =IF(F72=B32053,E32053,"")
B72: Application / System Data /Data / Application Hosting | D72: Is the application/data Hosted in NYP Data Center? | F72: =SECURITY!D24 -> Yes | G72: * | L72: CTRL | N72: 201757
H73: =IF(F74=B32056,C32056,"") | M73: =IF(F74=B32056,E32056,"")
B74: Application / System Data /Data / Application Hosting/Vendor Hosting | D74: Is the application/data Hosted By Vendor? | F74: =SECURITY!D25 -> No | G74: * | L74: CTRL | N74: 201761
H75: =IF(F76=B32057,C32057,"") | M75: =IF(F76=B32057,E32057,"")
B76: Application / System Data /Data / Application Hosting/Third Party Hosting | D76: Is the application/data Hosted by other 3rd Party? If so, provide name | F76: =SECURITY!D27 -> No | G76: * | H76: =SECURITY!G27 -> 0 | L76: CTRL | N76: 201765
H77: =IF(F78=B32062,C32062,"") | M77: =IF(F78=B32062,E32062,"")
B78: Application / System Data /Data / Application Hosting/Vendor Owned Hosting | D78: Is the application/data NYP data stored on a Vendor owned system? | F78: =SECURITY!D28 -> No | G78: * | L78: CTRL | N78: 201769
H79: =IF(F80=B32065,C32065,"") | M79: =IF(F80=B32065,E32065,"")
B80: Application / System Data /Data / Application Hosting/Standalone | D80: Is the application/data N/A - (e.g. Standalone, desktop, embedded device)? | F80: =SECURITY!D30 -> No | G80: * | H80: =SECURITY!G30 -> 0 | L80: CTRL | N80: 201773
H81: =IF(F82=B32068,C32068,"") | M81: =IF(F82=B32068,E32068,"")
B82: Data Transfers/LAN | D82: Is NYP data transmitted over a local NYP local network? | F82: =SECURITY!D34 -> Yes | G82: * | L82: CTRL | N82: 201777
H83: =IF(F84=B32071,C32071,"") | M83: =IF(F84=B32071,E32071,"")
B84: Data Transfers/WAN | D84: Is NYP data transmitted over a WAN? | F84: =SECURITY!D35 -> No | G84: * | L84: CTRL | N84: 201781
H85: =IF(F86=B32074,C32074,"") | M85: =IF(F86=B32074,E32074,"")
B86: Data Transfers/VPN | D86: Is NYP data transmitted over a NYP Virtual Private Network (VPN)? | F86: =SECURITY!D36 -> No | G86: * | L86: CTRL | N86: 201785
H87: =IF(F88=B32077,C32077,"") | M87: =IF(F88=B32077,E32077,"")
B88: Data Transfers/Internet | D88: Is NYP data transmitted over the Internet? | F88: =SECURITY!D37 -> No | G88: * | L88: CTRL | N88: 201789
H89: =IF(F90=B32080,C32080,"") | M89: =IF(F90=B32080,E32080,"")
B90: Data Transfers/Wireless/Security (WiFi) | D90: Is NYP data transmitted over a WiFi connection? | F90: =SECURITY!D38 -> Yes | G90: * | L90: CTRL | N90: 201793
H91: =IF(F92=B32083,C32083,"") | M91: =IF(F92=B32083,E32083,"")
B92: Data Transfers/Wireless/Security (Blue Tooth) | D92: Is NYP data transmitted over a BlueTooth connection? | F92: =SECURITY!D39 -> No | G92: * | L92: CTRL | N92: 201797
H93: =IF(F94=B32086,C32086,"") | M93: =IF(F94=B32086,E32086,"")
B94: Data Transfers/Wireless/Security (Mobile) | D94: Is NYP data transmitted over a Mobile connection? | F94: =SECURITY!D40 -> Yes | G94: * | L94: CTRL | N94: 201801
H95: =IF(F96=B32089,C32089,"") | M95: =IF(F96=B32089,E32089,"")
B96: Application / System Data /Data Transfers/(PHI) | D96: Does this system/application transfer any Protected Health Information (PHI)? | F96: =SECURITY!D44 -> Yes | G96: * | L96: CTRL | N96: 201805
H97: =IF(F98=B32092,C32092,"") | M97: =IF(F98=B32092,E32092,"")
B98: Application / System Data /Data Transfers/(PII) | D98: Does this system/application transfer any Personally Identifiable Information (PII)? | F98: =SECURITY!D45 -> No | G98: * | L98: CTRL | N98: 201809
H99: =IF(F100=B32095,C32095,"") | M99: =IF(F100=B32095,E32095,"")
B100: Application / System Data /Data Transfers/(PCI) | D100: Does this system/application transfer any Payment Card Industry (PCI) data? | F100: =SECURITY!D46 -> No | G100: * | L100: CTRL | N100: 201813
H101: =IF(F102=B32098,C32098,"") | M101: =IF(F102=B32098,E32098,"")
B102: Application / System Data /Data Transfers/(Payroll) | D102: Does this system/application transfer any Payroll data? | F102: =SECURITY!D47 -> No | G102: * | L102: CTRL | N102: 201817
H103: =IF(F104=B32101,C32101,"") | M103: =IF(F104=B32101,E32101,"")
B104: Application / System Data /Data Transfers/(Financial) | D104: Does this system/application transfer any Financial records (e.g. revenue)? | F104: =SECURITY!D48 -> No | G104: * | L104: CTRL | N104: 201821
H105: =IF(F106=B32103,C32103,"") -> Please Specify | M105: =IF(F106=B32103,E32103,"") -> 2
B106: Application / System Data /Data Transfers/(Other) | D106: Does this system/application transfer any Other – Please describe? | F106: =SECURITY!D50 -> Yes | G106: * | H106: =SECURITY!G50 -> Fetal tracings, vitals, cervical exams, GA/EDD etc. <30 fields received via HL7 from the EMR. | L106: CTRL | N106: 201825
H107: =IF(F108=B32104,C32104,"") | M107: =IF(F108=B32104,E32104,"")
B108: Application / System Data /Application / System Security | D108: Will the server / workstation be built and managed by NYP? (If vendor built/managed, describe OS patching process and frequency, and anti-malware used in the comments section) | F108: =SECURITY!D54 -> NYP | G108: * | H108: =SECURITY!G54 -> 0 | L108: CTRL | N108: 201828
H109: =IF(F110=B32106,C32106,"") -> Enter Response | M109: =IF(F110=B32106,E32106,"") -> 2
B110: OS | D110: OS Name and Version | F110: Select here to enter response | G110: * | H110: =SECURITY!D55 -> Windows 2016/2019 and Windows 10 | L110: CTRL | N110: 201831
H111: =IF(F112=B32108,C32108,"") -> Enter Response | M111: =IF(F112=B32108,E32108,"") -> 2
B112: OS Support | D112: OS vendor end-of-life support date (skip if it is an NYP-built and managed server/workstation) | F112: Select here to enter response | G112: * | H112: =SECURITY!D56 -> 0 | L112: CTRL | N112: 201834
H113: =IF(F114=B32110,C32110,"")&IF(F114=B32111,C32111,"") | M113: =IF(F114=B32110,E32110,"")&IF(F114=B32111,E32111,"")
...

Sheet GENERAL
B1: GENERAL
B2: Complete ALL Orange highlighted cells
B4: Enter the name | D4: =D12&" - "&D14&" - NYP General Assessment" -> PeriWatch Vigilance - 9181 - NYP General Assessment
B6: Question / Description
B8: Enter the name
B10: Question / Description | D10: Answer / Value
B12: APPLICATION/PRODUCT/SERVICE NAME: | D12: PeriWatch Vigilance | E12: *
B14: IT SYSTEM REQUEST NUMBER: | D14: 9181 | E14: *
B16: Name: | D16: Michael Kennedy | E16: *
B18: Email: | D18: Perigen Fetal Surveillance | E18: *
B20: Phone number: | E20: *
B22: DATE SUBMITTED (mm/dd/yy): | D22: 44531 | E22: *
B24: EXPECTED GO-LIVE DATE (mm/dd/yy): | E24: *
B26: Will this application or system be HOSTED by NYP or the Vendor? | D26: NYP | E26: *
B28: Will this application or system be SUPPORTED by NYP or the Vendor? | D28: Vendor | E28: *
B30: Description of product features, functionality and/or services: | D30: OB Fetal Surveillance, archiving, alerts and early warning functions | E30: *
B32: Web URLs | D32: www.perigen.com
B34: Please insert a graphic image containing a diagram of the recommended system architecture | D34: Select here to add attachment | E34: * | F34: See PowerPoint submitted with this document | AF34: =IF(D34="Select here to add attachment","1","") -> 1
F35: =IF(D36="Yes", "Comment","") -> Comment
B36: 1. Will this PMO request require technical resources from IT such as Server and Database resources? OR 2. Does this PMO request introduce a new network-connected device (such as a biomedical, audio/visual, or building management) or changes to an existing device or service, that will require ongoing connectivity and support? | D36: Yes | E36: * | F36: This PMO requires IT involvement to create the required environmnets (servers, DBs) for PeriWatch Vigilance. | S36: =IF(C36="Yes", "1","") | AF36: =IF(D36="Yes", "1","") -> 1
B38: Does this request include a Medical Device/ BioMed Component? NOTE: If answering NO, disregard the remaining Medical Device questions!! | D38: No | E38: * | F38: However it involves connecivity to existing fetal monitors. See above.
B40: Doest this request include a cloud-based or externally-hosted component? NOTE: If answering NO, disregard the remaining Vendor Hosted questions!! | D40: No | E40: * | F40: All to be hosted by NYP
B42: Vendor/NYP IT Owner Comments & Concerns

Sheet BCDR
B1: BCDR
B2: Complete ALL Orange highlighted cells
B3: Question / Description | D3: Answer / Value
B5: Does your application include a technology that can be utilized to provide a highly available system architecture, which meets the Tiering requirements of the system? NOTE: If answering NO, disregard the remaining BCDR questions. | D5: No | E5: *
B7: Please describe what technologies, native to your application, that can be utilized to provide a highly available system architecture that meets the "RTO and "RPO" of the appropriate Tiering level. | D7: There are no native technologies. PeriWatch Vigilance relies on SQL clustering for DB HA and Vmware HA capabilities. Typically, PeriWatch Vigilance is not considered tier 1 application like fetal surveillance. | E7: *
B9: Please let us know below, if your application provides interoperability and support for these technologies, or encounters general issues with using these technologies to provide high availability. | D9: Same as above. | E9: *

Sheet MEDICAL DEVICE
D1: Medical Devices
D2: Complete ALL Orange highlighted cells and where applicable provide additional comments in column I.
A4: MD1 | B4: 1.1 | D4: Device Information | E4: Manufacturer Name | G4: PeriGen Inc. | H4: * | I4: PeriWatch Vigilance is an enterprise-wide system comprised of the following medical devices: PeriWatch Vigilance Surveillance PeriWatch Vigilance Cues PeriWatch Vigilance Curve PeriWatch Vigilance HUB
E5: Device Name | G5: PeriWatch Vigilance | H5: *
E6: Device Model | G6: PeriWatch Vigilance | H6: *
E7: Software Version | G7: 2021.1 | H7: *
E8: Device Category | G8: surveillance | H8: *
E9: Short Description of Medical Device Function | G9: Obstetrical early warning | H9: *
D10: Data Management
B11: 1.2 | E11: Data Management: | F11: Does device display, transmit, or maintain/store private data (including electronic Protected Health Information [ePHI])? | G11: Yes | H11: *
B12: 1.3 | E12: Record Management | F12: How many individual patient records can be stored on the device? | G12: more than 1,000 | H12: *
I13: =IF(G14="No", "Please Explain","")
B14: 1.4 | D14: Device Certification | E14: FDA | F14: Is the device FDA cleared or approved | G14: Yes | H14: * | AG14: =IF(G14="No","1","")
B15: 1.5 | E15: Manufacturer Disclosure Statement for Medical Device Security – MDS2: | F15: Attach device MDS2 form. | G15: Select here to add attachment | H15: * | I15: See MDS2 form submitted with this document | AG15: =IF(G15="Select here to add attachment","1","") -> 1
D16: Operating System Version and Support
A17: MD2 | B17: 2.1 | D17: Operating System Version and Support | E17: OS Name and Version | G17: Windows Server 2019 | H17: *
B18: 2.2 | E18: OS vendor end-of-life support date | G18: NA | H18: *
D19: Operating System Security Features
I20: =IF(G21="No", "Please Explain","") & IF(G21="N/A", "Comments","") -> Comments
B21: 2.3 | D21: Operating System Security features: | E21: OS Features | F21: Hardened OS | G21: N/A | H21: * | I21: Provided/configured by the customer | AG21: =IF(G21="No","1","") & IF(G21="N/A", "2","") -> 2
I22: =IF(G23="No", "Please Explain","") & IF(G23="N/A", "Comments","") -> Comments
B23: 2.4 | F23: Automatic Logoff | G23: N/A | H23: * | I23: Provided/configured by the customer | AG23: =IF(G23="No","1","") & IF(G23="N/A", "2","") -> 2
I24: =IF(G25="No", "Please Explain","") & IF(G25="N/A", "Comments","") -> Comments
B25: 2.4 | E25: Software Firewall | F25: Firewall enabled | G25: N/A | H25: * | I25: Provided/configured by the customer | AG25: =IF(G25="No","1","") & IF(G25="N/A", "2","") -> 2
I26: =IF(G27="No", "Please Explain","") & IF(G27="N/A", "Comments","") -> Comments
B27: 2.5 | F27: Default Deny for Apps, Drivers & Libraries | G27: N/A | H27: * | I27: Provided/configured by the customer | AG27: =IF(G27="No","1","") & IF(G27="N/A", "2","") -> 2
I28: =IF(G29="No", "Please Explain","") & IF(G29="N/A", "Comments","") -> Comments
B29: 2.6 | F29: Device Control, USB Connections Monitoring | G29: N/A | H29: * | I29: Provided/configured by the customer | AG29: =IF(G29="No","1","") & IF(G29="N/A", "2","") -> 2
I30: =IF(G31="No", "Please Explain","") & IF(G31="N/A", "Comments","") -> Comments
B31: 2.7 | F31: Memory Protection | G31: N/A | H31: * | I31: Provided/configured by the customer | AG31: =IF(G31="No","1","") & IF(G31="N/A", "2","") -> 2
I32: =IF(G33="No", "Please Explain","") & IF(G33="N/A", "Comments","") -> Comments
B33: 2.8 | F33: File Integrity Monitoring and Activity Audit Logs | G33: N/A | H33: * | I33: Provided/configured by the customer | AG33: =IF(G33="No","1","") & IF(G33="N/A", "2","") -> 2
I34: =IF(G35="No", "Please Explain","") & IF(G35="N/A", "Comments","") -> Comments
B35: 2.9 | E35: Does the device support Least Privileged Access limiting user access to the minimal level that will allow normal functioning or operation. | G35: N/A | H35: * | I35: Provided/configured by the customer | AG35: =IF(G35="No","1","") & IF(G35="N/A", "2","") -> 2
I36: =IF(G37="No", "Please Explain","") & IF(G37="N/A", "Comments","") -> Comments
B37: 2.1 | E37: CD/USB boot disabled | G37: N/A | H37: * | I37: PeriGen assumes the customer provides a pre-configured VM with all the above configured according to customer IT policies | AG37: =IF(G37="No","1","") & IF(G37="N/A", "2","") -> 2
D38: s
I39: =IF(G40="No", "Please Explain","") -> Please Explain
A40: MD3 | B40: 3.1 | D40: Connectivity | E40: Network Connectivity | F40: Dedicated cable connection (e.g., IEEE 1073, serial port, USB, FireWire, etc.)? | G40: No | H40: * | I40: The device is software only and running on the customer provided VM which include local network connectivity. | AG40: =IF(G40="No","1","") -> 1
I41: =IF(G42="No", "Please Explain","")
B42: 3.2 | F42: Wired network connection (e.g., LAN, WAN, VPN, intranet, Internet, etc.)? | G42: Yes | H42: * | AG42: =IF(G42="No","1","")
I43: =IF(G44="No", "Please Explain","") -> Please Explain
B44: 3.3 | F44: Wireless network connection (e.g., Wi-Fi, Bluetooth, infrared, etc.)? | G44: No | H44: * | AG44: =IF(G44="No","1","") -> 1
I45: =IF(G46="No", "Please Explain","") -> Please Explain
B46: 3.4 | F46: No network connections | G46: No | H46: * | I46: The device is software only and running on the customer provided VM which include local network connectivity. | AG46: =IF(G46="No","1","") -> 1
I47: =IF(G48="No", "Please Explain","")
B48: 3.5 | E48: System Connectivity - Other systems that device is authorized to exchange data. | F48: Connect to electronic medical record (EMR) | G48: Yes | H48: * | AG48: =IF(G48="No","1","")
I49: =IF(G50="No", "Please Explain","") -> Please Explain
B50: 3.6 | F50: Connect to image/data storage (e.g., PACS) | G50: No | H50: * | I50: Not required | AG50: =IF(G50="No","1","") -> 1
I51: =IF(G52="No", "Please Explain","")
B52: 3.7 | F52: Connected to intermediatory system via serial cable (e.g., Monitor, dedicated workstation, terminal server) | H52: * | AG52: =IF(G52="No","1","")
I53: =IF(G54="No", "Please Explain","") -> Please Explain
B54: 3.8 | F54: Remote access to data/images (e.g., physician, clinicians) | G54: No | H54: * | I54: Primarily used in real-time by clinicans in the OB unit. | AG54: =IF(G54="No","1","") -> 1
I55: =IF(G56="No", "Please Explain","")
B56: 3.9 | F56: Remote service (e.g., manufacturer updates, troubleshooting, repair) | G56: Yes | H56: * | AG56: =IF(G56="No","1","")
I57: =IF(G58="No", "Please Explain","") -> Please Explain
B58: 3.1 | F58: Remote control (e.g., modify alarms, configuration settings, level of therapy) | G58: No | H58: * | AG58: =IF(G58="No","1","") -> 1
I59: =IF(G60="No", "Please Explain","") -> Please Explain
B60: 3.11 | F60: Remote management (e.g., clinical updates like drug libraries for infusion pumps) | G60: No | H60: * | AG60: =IF(G60="No","1","") -> 1
I61: =IF(G62="No", "Please Explain","") -> Please Explain
B62: 3.12 | F62: Intra‐communication between medical devices (e.g., diagnostic device “informing” therapeutic devices …. e.g., monitor controlling opioid delivery) | G62: No | H62: * | AG62: =IF(G62="No","1","") -> 1
I63: =IF(G64="No", "Please Explain","") -> Please Explain
B64: 3.13 | F64: No system connectivity | G64: No | H64: * | I64: None other than the above. | AG64: =IF(G64="No","1","") -> 1
B66: 3.14 | E66: Network ports for clinical use: | F66: List all ports and protocols needed for communications | G66: Other than standard ports (SQL, http/https) the following ports are used by the PeriWatch Vigilance system: 8000, 8002, 8014, 8081-8084 | H66: * | AG66: =IF(G66="No","1","")
D67: Device Security - Pathcing and Updates
A68: MD4 | B68: 4.1 | C68: critica | D68: Patching and Updates | E68: Patching requirements and process. | F68: Describe Vendor patching requirements and process. | G68: Customer is in charge of OS patches. PeriGen provides critical patches when needed (rare), regular fixes and enhancements are packaged in maintenance releases once of twice a year. | H68: *
I69: =IF(G70="Not Supported", "Please Explain","")& IF(G70="N/A", "Please Explain","")& IF(G70="Supports Multiple", "Please Explain","") -> Please Explain
B70: 4.2 | E70: Patch Mangement | F70: Does the device support the following? Select all that apply. (if not supported, please explain why in the comments) | G70: Supports Multiple | H70: * | I70: Device supports NYP installed/maintained SCCM Agent for patch deployment Manual updates by NYP Manual updates of vendor software by Vendor (coordinated with NYP) | AG70: =IF(G70="Not Supported","1","") & IF(G70="N/A", "2","") & IF(G70="Supports Multiple", "3","") -> 3
D71: Device Security - Authentication
I72: =IF(G73="No", "Comments","")& IF(G73="N/A", "Comments","")& IF(G73="Supports Multiple", "Please Explain","")
A73: MD5 | B73: 5.1 | D73: Authentication | E73: AD support (if not supported, please explain why in the comments) | F73: Can the device be joined to the NYP AD domain and support domain accounts? | G73: Yes | H73: * | AG73: =IF(G73="No", "1","") & IF(G73="N/A", "2","")
I74: =IF(G75="Yes", "Comments","")& IF(G75="N/A", "Comments","")& IF(G75="Supports Multiple", "Please Explain","")
B75: 5.2 | F75: If joining to the Domain are there any Domain specific security policy restrictions (please specify in Comments) | G75: No | H75: * | AG75: =IF(G75="Yes", "1","") & IF(G75="N/A", "2","")
I76: =IF(G77="No", "Comments","")& IF(G77="N/A", "Comments","")& IF(G77="Supports Multiple", "Please Explain","")
B77: 5.3 | E77: User account control | F77: Does the device support unique user/operator-specific IDs and passwords for multiple users? | G77: Yes | H77: * | AG77: =IF(G77="No", "1","") & IF(G77="N/A", "2","")
I78: =IF(G79="No", "Comments","")& IF(G79="N/A", "Comments","")& IF(G79="Supports Multiple", "Please Explain","")
B79: 5.4 | F79: Can the device be configured to authenticate users through an external authentication service (e.g., MS Active Directory, NDS, LDAP, etc.)? | G79: Yes | H79: * | AG79: =IF(G79="No", "1","") & IF(G79="N/A", "2","")
I80: =IF(G81="Yes", "Comments","")& IF(G81="N/A", "Comments","")
B81: 5.5 | F81: Are any shared user IDs used in this system? | G81: No | H81: * | AG81: =IF(G81="Yes", "1","") & IF(G81="N/A", "2","")
D82: Device Security - Anti Virus
I83: =IF(G84="N/A", "Please Explain","")& IF(G84="Other (embedded Security - whitelisting)", "Please Explain","")
A84: MD6 | B84: 6.1 | D84: Anti Virus | E84: Antivirus / Antimalware Software? | F84: Will the device run an Antivirus / Antimalware Software? (if not supported, please explain why in the comments) | G84: NYP Standard - Cylance malware protection | H84: * | AG84: =IF(G84="Other (embedded Security - whitelisting)", "1","") & IF(G84="N/A", "2","")
I85: =IF(G86="N/A", "Please Explain","")& IF(G86="Not Supported", "Please Explain","")
B86: 6.4 | E86: AV Scanning modes | F86: Supported AVS Scanning modes | G86: Continuously and automatically (on access) | H86: * | I86: Some exclusions are required on the server | AG86: =IF(G86="Not Supported", "1","") & IF(G86="N/A", "2","")
D87: Device Security - Encryption
B88: 6.1 | I88: =IF(G89="N/A", "Comments","")& IF(G89="No", "Comments","")
A89: MD7 | B89: 7.1 | D89: Encryption | E89: Sensitive Data Encryption in Transit | F89: Is TLS1.2 used to encrypt sensitive data in transit | G89: Yes | H89: * | AG89: =IF(G89="No", "1","") & IF(G89="N/A", "2","")
B90: 7.2 | I90: =IF(G91="N/A", "Please Explain","")& IF(G91="Other encryption types. (please specify in Comments)", "Please Explain","")
B91: 7.3 | E91: Sensitive Data Encryption at rest/storage | F91: Select encryption method used to encrypt Sensitive data at rest/storage | G91: NYP Standard - Bit locker through NYP AD Domain rules | H91: * | AG91: =IF(G91="Other encryption types. (please specify in Comments)", "1","") & IF(G91="N/A", "2","")
B92: 7.4 | I92: =IF(G93="N/A", "Please Explain","")& IF(G93="No", "Please Explain","") -> Please Explain
B93: 7.5 | E93: Secure DICOM | F93: Does the device encrypt DICOM images prior to transmission. | G93: N/A | H93: * | I93: DICOM images are not used as part of this solution | AG93: =IF(G93="No", "1","") & IF(G93="N/A", "2","") -> 2
D94: Device Security - Password Policy
D95: Please mark the rest of the PASSWORD POLICY section as N/A if the device will be joined to NYP AD domain and use NYP AD accounts
D96: Passwords (skip this section if the device will be joined to NYP AD domain and use NYP AD accounts) | I96: =IF(G97="No", "Please Explain","")
A97: MD8 | B97: 8.1 | E97: Securing Passwords | F97: Stored in a one-way hash format. | G97: N/A | H97: * | I97: Joined to NYP domain | AG97: =IF(G97="No", "1","")
I98: =IF(G99="No", "Please Explain","")
B99: 8.2 | F99: Force a required password change for first login or on password reset by an administrator. | G99: N/A | H99: * | AG99: =IF(G99="No", "1","")
I100: =IF(G101="Yes", "Please Explain","")
B101: 8.3 | F101: Are there any hardcoded passwords in the device. | G101: N/A | H101: * | AG101: =IF(G101="Yes", "1","")
I102: =IF(G103="No", "Please Explain","")
...

Sheet SECURITY
B1: SECURITY
B2: Please Note: The Security Tab must be completed for all System Requests EXCLUDING Medical Devices. Complete ALL Orange highlighted cells and where applicable provide additional comments in column G.
B4: Question / Description | D4: Answer / Value | G4: Comments and Notes
B5: Application/Solution/Service Information
B6: Vendor Name | D6: PeriGen Inc. | F6: *
B7: Application/Solution/Service Name | D7: PeriWatch Vigilance | F7: *
B8: Software Version | D8: 2021.1 | F8: *
B9: Short Description of Application/Solution or Service being provided | D9: Obstetrical Early Warning system | F9: *
B12: Data Classification
B13: What type of data is created, processed, stored, or received by the system or application (or accessed by the vendor/contractor in case of professional services projects)? (Please select all that apply)
B14: PHI | D14: Yes | F14: *
B15: PII | D15: No | F15: *
B16: PCI | D16: No | F16: * | G16: =IF(D16="Yes","Please attach evidence of PCI Compliance.", "") | AF16: =IF(D16="Yes","1","0") -> 0
B17: PayRoll | D17: No | F17: *
B18: Financial | D18: No | F18: *
G19: =IF(D20="Yes","Please Explain","")
B20: Is there any OTHER data not previously mentioned that is created, processed, stored, or received by the system or application (or accessed by the vendor/contractor in case of professional services projects)? If so, please specify. | D20: No | F20: * | AA20: =IF(D20="Yes", "1","")
B22: Data/Application Hosting
B23: Where is the application/data being processed or stored?
B24: NYP Data Center | D24: Yes | F24: *
B25: Hosted By Vendor | D25: No | F25: *
G26: =IF(D27="Yes", "Comment","")
B27: Is the application/data Hosted by other 3rd Party? If so, provide name | D27: No | AA27: =IF(D27="Yes", "1","")
B28: Is the application/data NYP data stored on a Vendor owned system? | D28: No | F28: *
G29: =IF(D30="N/A", "Comment","")
B30: N/A - (e.g. Standalone, desktop, embedded device)? | D30: No | AA30: =IF(D30="N/A", "1","")
B32: Communication/Transmission Methods
B33: Is NYP data transmitted over a private or public network? (Please select all that apply)
B34: Local NYP local network | D34: Yes | F34: *
B35: WAN | D35: No | F35: *
B36: NYP Virtual Private Network (VPN) | D36: No | F36: *
B37: Internet | D37: No | F37: *
B38: WiFi | D38: Yes | F38: * | G38: only if the customer is using mobile workstations or tablets,
B39: BlueTooth | D39: No | F39: *
B40: Mobile | D40: Yes | F40: * | G40: Not natively. Only if the customer provides secure remote access to mobile devices.
B42: Data Transfers
B43: What type of data is transferred to or from this system/application? (Please select all that apply)
B44: PHI | D44: Yes | F44: *
B45: PII | D45: No | F45: *
B46: PCI | D46: No | F46: *
B47: Payroll data | D47: No | F47: *
B48: Financial records | D48: No | F48: *
G49: =IF(D50="Yes", "Please Specify","") -> Please Specify
B50: Does this system/application transfer any Other – Please describe? | D50: Yes | F50: * | G50: Fetal tracings, vitals, cervical exams, GA/EDD etc. <30 fields received via HL7 from the EMR. | AA50: =IF(D50="Yes", "1","") -> 1
B52: Server or Workstation Information
G53: =IF(D54="Vendor", "Comments","")
B54: Will the server / workstation be built and managed by NYP? (If vendor built/managed, describe OS patching process and frequency, and anti-malware used in the comments section) | D54: NYP | F54: * | AA54: =IF(D54="Vendor", "1","")
B55: OS Name and Version | D55: Windows 2016/2019 and Windows 10 | F55: *
B56: OS vendor end-of-life support date (skip if it is an NYP-built and managed server/workstation) | F56: *
B58: Authentication
G59: =IF(D60="No", "Please Explain","")
B60: Does the system or application support AD and/or Federated Authentication for local and/or remote authentication? | D60: Yes | F60: * | AA60: =IF(D60="No", "2","")
B61: Does the system or application support AD and/or Federated Authentication for local and/or remote authentication? Select All that apply.
G62: =IF(D63="No", "Please Explain","")
B63: Active Directory | D63: Yes | F63: * | AA63: =IF(D63="No", "2","")
G64: =IF(D65="No", "Please Explain","") -> Please Explain
B65: SAML | D65: No | F65: * | AA65: =IF(D65="No", "2","") -> 2
G66: =IF(D67="No", "Please Explain","") -> Please Explain
B67: WS-Federation | D67: No | F67: * | AA67: =IF(D67="No", "2","") -> 2
G68: =IF(D69="No", "Please Explain","") -> Please Explain
B69: Oath | D69: No | F69: * | AA69: =IF(D69="No", "2","") -> 2
G70: =IF(D71="No", "Please Explain","")
B71: OpenID Connect | D71: Yes | F71: * | AA71: =IF(D71="No", "2","")
G72: =IF(D73="No", "Please Explain","") -> Please Explain
B73: WS-Trust | D73: No | F73: * | AA73: =IF(D73="No", "2","") -> 2
G74: =IF(D75="No", "Please Explain","") -> Please Explain
B75: Multi-Factor Authentication | D75: No | F75: * | AA75: =IF(D75="No", "2","") -> 2
B77: Password Policy
B78: Complete this section only if the application does not support NYP AD and/or Federated authentication. (Answer N/A if AD or Federated authentication is supported) | G78: =IF(D79="No", "Comment","")
B79: Does the system or application support comply with NYP's password policy? - A) At least eight characters long. B) Include small letters, capital letters and numbers. C) No dictionary words or commonly known proper nouns. D) Expire after a maximum of 180 day | D79: N/A | F79: * | G79: All managed by AD policies | AA79: =IF(D79="No", "1","")
G80: =IF(D81="No", "Please Explain","")
B81: Are passwords stored in a one-way hash format? | D81: N/A | F81: * | G81: Passwords not stored. | AA81: =IF(D81="No", "1","")
G82: =IF(D83="No", "Please Explain","")
B83: Does the system or application force a required password change for first login or on password reset by an administrator? | D83: N/A | F83: * | G83: see above | AA83: =IF(D83="No", "1","")
G84: =IF(D85="No", "Please Explain","")
B85: Auto-logoff after maximum of 30 min of inactivity | D85: Yes | F85: * | G85: Configurable | AA85: =IF(D85="No", "1","")
G86: =IF(D87="Yes", "Please Explain","")
B87: Are there any Domain specific security policy restrictions? (please specify in Comments) | D87: No | F87: * | AA87: =IF(D87="Yes", "1","")
B89: Account Control/Management
G90: =IF(D91="N/A", "Please Explain","")&IF(D91="No", "Please Explain","")
B91: Does the system/application support Role Based Access Control (RBAC) with unique user/operator-specific IDs and passwords? | D91: Yes | F91: * | AA91: =IF(D91="N/A", "1","")&IF(D91="No", "2","")
G92: =IF(D93="Yes", "Comment","")
B93: Are generic/shared accounts used? | D93: No | F93: * | AA93: =IF(D93="Yes", "1","")
G94: =IF(D95="No", "Comment","")
B95: Are Default and/or guest accounts disabled? | D95: Yes | F95: * | AA95: =IF(D95="No", "1","")
G96: =IF(D97="No", "Comment","") -> Comment
B97: Is Automated User Provisioning and Role Management using an external program/API supported? | D97: No | F97: * | G97: Direct AD authentication | AA97: =IF(D97="No", "1","") -> 1
B98: Who manages access to the system or application? | D98: Customer assigns users to the defined groups. PeriGen/customer assign access to the app based on those groups | F98: *
B99: How is the user’s access removed when it is no longer needed. | D99: By disableing the user in AD or removing them from the authorized AD group | F99: *
B101: User Access Methods
B102: User Access Methods (Check the different methods by which the users can access the system)
B103: SSH | D103: No | F103: *
B104: Web Application | D104: Yes | F104: *
B105: Thick Client Application | D105: Yes | F105: *
B106: Mobile Application | D106: No | F106: *
G107: =IF(D108="Yes", "Comment","")
B108: Can the users can access the system via other method (please specify)? | D108: No | F108: * | AA108: =IF(D108="Yes", "1","")
B110: Privilege Access Methods
B111: Admin Methods Access Methods (Check the different methods by which the users can access the system)
B112: SSH | D112: Yes | F112: *
...

Sheet VENDOR HOSTED
D1: Cloud-based or Externally Hosted Systems
D2: Complete ALL Orange highlighted cells and where applicable provide additional comments incolumn W.
A3: DID | B3: Domain | D3: Control Group | E3: CGID | F3: CID | G3: NYP | H3: Third Party Information Security Assessment Questions | I3: Yes/No/NA | J3: COBIT | K3: HIPAA | L3: ISO27001 | M3: SP800_53 | N3: FedRAMP | O3: PCI_DSS | P3: BITS | Q3: GAPP | R3: SaaS | S3: PaaS | T3: IaaS | U3: SP | V3: CUST | W3: Comments and Notes
D4: Vendor/Cloud Information | H4: VENDOR /3RD PARTY ORGANIZATION NAME(s)
H5: VENDOR CONTACT NAME
H6: VENDOR ROLE
W7: =IF(I8="Yes", "Comments","")
H8: Will subcontractors be involved in services performed by the vendor? If so, list all subcontractors and services they provide. | AO8: =IF(I8="Yes", "1","")
A9: CO | B9: Compliance
W10: =IF(I11="No", "Comments","") & IF(I11="N/A", "Comments","")
A11: CO | B11: Compliance | D11: Independent Audits | E11: CO-02 | F11: CO-02.1 | G11: CR | H11: Have you conducted SAS70 Type II/SSAE 16 SOC2/ISAE3402 or similar third party review of the data center where NYP data is stored? | J11: COBIT 4.1 DS5.5, ME2.5, ME 3.1 PO 9.6 | K11: 45 CFR 164.308 (a)(8) 45 CFR 164.308(a)(1)(ii)(D) | L11: Clause 4.2.3e Clause 5.1 g Clause 5.2.1 d) Clause 6 A.6.1.8 | M11: NIST SP800-53 R3 CA-1 NIST SP800-53 R3 CA-2 NIST SP800-53 R3 CA-6 NIST SP800-53 R3 RA-5 | N11: NIST SP800-53 R3 CA-1_x000D_ NIST SP800-53 R3 CA-2_x000D_ NIST SP800-53 R3 CA-2 (1)_x000D_ NIST SP800-53 R3 CA-6_x000D_ NIST SP800-53 R3 RA-5_x000D_ NIST SP800-53 R3 RA-5 (1)_x000D_ NIST SP800-53 R3 RA-5 (2)_x000D_ NIST SP800-53 R3 RA-5 (3)_x000D_ NIST SP800-53 R3 RA-5 (9)_x000D_ NIST SP800-53 R3 RA-5 (6)_x000D_ | O11: PCI DSS v2.0 11.2 PCI DSS v2.0 11.3 PCI DSS v2.0 6.6 PCI DSS v2.0 12.1.2.b | P11: SIG v6.0: L.2, L.4, L.7, L.9, L.11 | Q11: GAPP Ref 1.2.5 GAPP Ref 1.2.7 GAPP Ref 4.2.1 GAPP Ref 8.2.7 GAPP Ref 10.2.3 GAPP Ref 10.2.5 | R11: Y | S11: Y | T11: Y | U11: Y | V11: Y | AO11: =IF(I11="No","1","")&IF(I11="N/A","2","")
W12: =IF(I13="No", "Comments","") & IF(I13="N/A", "Comments","")
A13: CO | B13: Compliance | E13: CO-02 | F13: CO-02.4 | G13: CR | H13: Does your Internal Audit organization review the compliance and effectiveness of your information security practices and controls? | J13: COBIT 4.1 DS5.5, ME2.5, ME 3.1 PO 9.6 | K13: 45 CFR 164.308 (a)(8) 45 CFR 164.308(a)(1)(ii)(D) | L13: Clause 4.2.3e Clause 5.1 g Clause 5.2.1 d) Clause 6 A.6.1.8 | M13: NIST SP800-53 R3 CA-1 NIST SP800-53 R3 CA-2 NIST SP800-53 R3 CA-6 NIST SP800-53 R3 RA-5 | N13: NIST SP800-53 R3 CA-1_x000D_ NIST SP800-53 R3 CA-2_x000D_ NIST SP800-53 R3 CA-2 (1)_x000D_ NIST SP800-53 R3 CA-6_x000D_ NIST SP800-53 R3 RA-5_x000D_ NIST SP800-53 R3 RA-5 (1)_x000D_ NIST SP800-53 R3 RA-5 (2)_x000D_ NIST SP800-53 R3 RA-5 (3)_x000D_ NIST SP800-53 R3 RA-5 (9)_x000D_ NIST SP800-53 R3 RA-5 (6)_x000D_ | O13: PCI DSS v2.0 11.2 PCI DSS v2.0 11.3 PCI DSS v2.0 6.6 PCI DSS v2.0 12.1.2.b | P13: SIG v6.0: L.2, L.4, L.7, L.9, L.11 | Q13: GAPP Ref 1.2.5 GAPP Ref 1.2.7 GAPP Ref 4.2.1 GAPP Ref 8.2.7 GAPP Ref 10.2.3 GAPP Ref 10.2.5 | R13: Y | S13: Y | T13: Y | U13: Y | V13: Y | AO13: =IF(I13="No","1","")&IF(I13="N/A","2","")
W14: =IF(I15="No", "Comments","") & IF(I15="N/A", "Comments","")
A15: CO | B15: Compliance | E15: CO-02 | F15: CO-02.5 | G15: CR | H15: Does an external firm (such as KPMG, PWC) perform external audits of your company's and partners' information security practices and controls? | J15: COBIT 4.1 DS5.5, ME2.5, ME 3.1 PO 9.6 | K15: 45 CFR 164.308 (a)(8) 45 CFR 164.308(a)(1)(ii)(D) | L15: Clause 4.2.3e Clause 5.1 g Clause 5.2.1 d) Clause 6 A.6.1.8 | M15: NIST SP800-53 R3 CA-1 NIST SP800-53 R3 CA-2 NIST SP800-53 R3 CA-6 NIST SP800-53 R3 RA-5 | N15: NIST SP800-53 R3 CA-1_x000D_ NIST SP800-53 R3 CA-2_x000D_ NIST SP800-53 R3 CA-2 (1)_x000D_ NIST SP800-53 R3 CA-6_x000D_ NIST SP800-53 R3 RA-5_x000D_ NIST SP800-53 R3 RA-5 (1)_x000D_ NIST SP800-53 R3 RA-5 (2)_x000D_ NIST SP800-53 R3 RA-5 (3)_x000D_ NIST SP800-53 R3 RA-5 (9)_x000D_ NIST SP800-53 R3 RA-5 (6)_x000D_ | O15: PCI DSS v2.0 11.2 PCI DSS v2.0 11.3 PCI DSS v2.0 6.6 PCI DSS v2.0 12.1.2.b | P15: SIG v6.0: L.2, L.4, L.7, L.9, L.11 | Q15: GAPP Ref 1.2.5 GAPP Ref 1.2.7 GAPP Ref 4.2.1 GAPP Ref 8.2.7 GAPP Ref 10.2.3 GAPP Ref 10.2.5 | R15: Y | S15: Y | T15: Y | U15: Y | V15: Y | AO15: =IF(I15="No","1","")&IF(I15="N/A","2","")
W16: =IF(I17="No", "Comments","") & IF(I17="N/A", "Comments","") | AO16: =IF(I16="No","1","")&IF(I16="N/A","2","")
A17: CO | B17: Compliance | E17: CO-02 | F17: CO-02.7 | G17: CR | H17: Is a summary of the results of your internal audit and external audits readily available for review? | J17: COBIT 4.1 DS5.5, ME2.5, ME 3.1 PO 9.6 | K17: 45 CFR 164.308 (a)(8) 45 CFR 164.308(a)(1)(ii)(D) | L17: Clause 4.2.3e Clause 5.1 g Clause 5.2.1 d) Clause 6 A.6.1.8 | M17: NIST SP800-53 R3 CA-1 NIST SP800-53 R3 CA-2 NIST SP800-53 R3 CA-6 NIST SP800-53 R3 RA-5 | N17: NIST SP800-53 R3 CA-1_x000D_ NIST SP800-53 R3 CA-2_x000D_ NIST SP800-53 R3 CA-2 (1)_x000D_ NIST SP800-53 R3 CA-6_x000D_ NIST SP800-53 R3 RA-5_x000D_ NIST SP800-53 R3 RA-5 (1)_x000D_ NIST SP800-53 R3 RA-5 (2)_x000D_ NIST SP800-53 R3 RA-5 (3)_x000D_ NIST SP800-53 R3 RA-5 (9)_x000D_ NIST SP800-53 R3 RA-5 (6)_x000D_ | O17: PCI DSS v2.0 11.2 PCI DSS v2.0 11.3 PCI DSS v2.0 6.6 PCI DSS v2.0 12.1.2.b | P17: SIG v6.0: L.2, L.4, L.7, L.9, L.11 | Q17: GAPP Ref 1.2.5 GAPP Ref 1.2.7 GAPP Ref 4.2.1 GAPP Ref 8.2.7 GAPP Ref 10.2.3 GAPP Ref 10.2.5 | R17: Y | S17: Y | T17: Y | U17: Y | V17: Y | AO17: =IF(I17="No","1","")&IF(I17="N/A","2","")
W18: =IF(I19="No", "Comments","") & IF(I19="N/A", "Comments","")
A19: CO | B19: Compliance | E19: CO-03 | F19: CO-03.1 | G19: CR | H19: Can NYP perform vulnerability and penetration tests of the application? | J19: COBIT 4.1 ME 2.6, DS 2.1, DS 2.4 | K19: 45 CFR 164.308(b)(1) (New) 45 CFR 164.308 (b)(4) | L19: A.6.2.3 A.10.2.1 A.10.2.2 A.10.6.2 | M19: NIST SP800-53 R3 CA-3 NIST SP800-53 R3 SA-9 NIST SP800-53 R3 SA-12 NIST SP800-53 R3 SC-7 | O19: PCI DSS v2.0 2.4 PCI DSS v2.0 12.8.2 PCI DSS v2.0 12.8.3 PCI DSS v2.0 12.8.4 Appendix A | P19: AUP v5.0 C.2 SIG v6.0: C.2.4,C.2.6, G.4.1, G.4.2, L.2, L.4, L.7, L.11 | Q19: GAPP Ref 1.2.11 GAPP Ref 4.2.3 GAPP Ref 7.2.4 GAPP Ref 10.2.3 GAPP Ref 10.2.4 | R19: Y | S19: Y | T19: Y | U19: Y | V19: Y | AO19: =IF(I19="No","1","")&IF(I19="N/A","2","")
W20: =IF(I21="No", "Comments","") & IF(I21="N/A", "Comments","")
A21: CO | B21: Compliance | D21: Third Party Audits | E21: CO-03 | F21: CO-03.2 | G21: CR | H21: Do you have an external third-party perform quarterly vulnerability scans and penetration tests on your applications and annual tests of your networks? | J21: COBIT 4.1 ME 2.6, DS 2.1, DS 2.4 | K21: 45 CFR 164.308(b)(1) (New) 45 CFR 164.308 (b)(4) | L21: A.6.2.3 A.10.2.1 A.10.2.2 A.10.6.2 | M21: NIST SP800-53 R3 CA-3 NIST SP800-53 R3 SA-9 NIST SP800-53 R3 SA-12 NIST SP800-53 R3 SC-7 | O21: PCI DSS v2.0 2.4 PCI DSS v2.0 12.8.2 PCI DSS v2.0 12.8.3 PCI DSS v2.0 12.8.4 Appendix A | P21: AUP v5.0 C.2 SIG v6.0: C.2.4,C.2.6, G.4.1, G.4.2, L.2, L.4, L.7, L.11 | Q21: GAPP Ref 1.2.11 GAPP Ref 4.2.3 GAPP Ref 7.2.4 GAPP Ref 10.2.3 GAPP Ref 10.2.4 | R21: Y | S21: Y | T21: Y | U21: Y | V21: Y | AO21: =IF(I21="No","1","")&IF(I21="N/A","2","")
A22: DG | B22: Data Governance | AO22: =IF(I22="No","1","")&IF(I22="N/A","2","")
W23: =IF(I24="No", "Comments","") & IF(I24="N/A", "Comments","")
A24: DG | B24: Data Governance | D24: Retention Policy | E24: DG-04 | F24: DG-04.1 | G24: CR | H24: Do you have technical control capabilities to enforce NYP data retention policies? | J24: COBIT 4.1 DS 4.1, DS 4.2, DS 4.5, DS 4.9, DS 11.6 | K24: 45 CFR 164.308 (a)(7)(ii)(A) 45 CFR 164.310 (d)(2)(iv) 45 CFR 164.308(a)(7)(ii)(D) (New) 45 CFR 164.316(b)(2)(i) (New) | L24: Clause 4.3.3 A.10.5.1 A.10.7.3 | M24: NIST SP800-53 R3 CP-2 NIST SP800-53 R3 CP-6 NIST SP800-53 R3 CP-7 NIST SP800-53 R3 CP-8 NIST SP800-53 R3 CP-9 NIST SP800-53 R3 SI-12 NIST SP800-53 R3 AU-11 | O24: PCI DSS v2.0 3.1 PCI DSS v2.0 3.1.1 PCI DSS v2.0 3.2 PCI DSS v2.0 9.9.1 PCI DSS v2.0 9.5 PCI DSS v2.0 9.6 PCI DSS v2.0 10.7 | P24: SIG v6.0: D.2.2.9 | Q24: GAPP Ref 5.1.0 GAPP Ref 5.1.1 GAPP Ref 5.2.2 GAPP Ref 8.2.6 | R24: Y | S24: Y | T24: Y | U24: Y | V24: Y | AO24: =IF(I24="No","1","")&IF(I24="N/A","2","")
W25: =IF(I26="No", "Comments","") & IF(I26="N/A", "Comments","")
A26: DG | B26: Data Governance | D26: Secure Disposal | E26: DG-05 | F26: DG-05.1 | G26: CR | H26: Do you support secure deletion (ex. degaussing / cryptographic wiping) of archived data as determined by NYP? | J26: COBIT 4.1 DS 11.4 | K26: 45 CFR 164.310 (d)(2)(i) 45 CFR 164.310 (d)(2)(ii) | L26: A.9.2.6 A.10.7.2 | M26: NIST SP800-53 R3 MP-6 NIST SP800-53 R3 PE-1 | N26: NIST SP800-53 R3 MP-6_x000D_ NIST SP800-53 R3 MP-6 (4)_x000D_ NIST SP800-53 R3 PE-1_x000D_ | O26: PCI DSS v2.0 3.1.1 PCI DSS v2.0 9.10 PCI DSS v2.0 9.10.1 PCI DSS v2.0 9.10.2 PCI DSS v2.0 3.1 | P26: SIG v6.0: D.2.2.10, D.2.2.11, D.2.2.14, | Q26: GAPP Ref 5.1.0 GAPP Ref 5.2.3 | R26: Y | S26: Y | T26: Y | U26: Y | V26: Y | AO26: =IF(I26="No","1","")&IF(I26="N/A","2","")
W27: =IF(I28="No", "Comments","") & IF(I28="N/A", "Comments","")
A28: DG | B28: Data Governance | E28: DG-05 | F28: DG-05.2 | G28: CR | H28: Can you provide a published procedure for exiting the service arrangement, including assurance to sanitize all computing resources of NYP's data once NYP has exited your environment or has vacated a resource? | J28: COBIT 4.1 DS 11.4 | K28: 45 CFR 164.310 (d)(2)(i) 45 CFR 164.310 (d)(2)(ii) | L28: A.9.2.6 A.10.7.2 | M28: NIST SP800-53 R3 MP-6 NIST SP800-53 R3 PE-1 | N28: NIST SP800-53 R3 MP-6_x000D_ NIST SP800-53 R3 MP-6 (4)_x000D_ NIST SP800-53 R3 PE-1_x000D_ | O28: PCI DSS v2.0 3.1.1 PCI DSS v2.0 9.10 PCI DSS v2.0 9.10.1 PCI DSS v2.0 9.10.2 PCI DSS v2.0 3.1 | P28: SIG v6.0: D.2.2.10, D.2.2.11, D.2.2.14, | Q28: GAPP Ref 5.1.0 GAPP Ref 5.2.3 | R28: Y | S28: Y | T28: Y | U28: Y | V28: Y | AO28: =IF(I28="No","1","")&IF(I28="N/A","2","")
W29: =IF(I30="No", "Comments","") & IF(I30="N/A", "Comments","")
A30: DG | B30: Data Governance | D30: Nonproduction Data | E30: DG-06 | F30: DG-06.1 | G30: CR | H30: Do you have procedures in place to ensure production data shall not be replicated or used in non-production environments? | K30: 45 CFR 164.308(a)(4)(ii)(B) | L30: A.7.1.3 A.10.1.4 A.12.4.2 A.12.5.1 | M30: NIST SP800-53 R3 SA-11 NIST SP800-53 R3 CM-04 | N30: NIST SP800-53 R3 SA-11_x000D_ NIST SP800-53 R3 SA-11 (1)_x000D_ NIST SP800-53 R3 CM-04_x000D_ | O30: PCI DSS v2.0 6.4.3 | P30: SIG v6.0: I.2.18 | Q30: GAPP Ref 1.2.6 | R30: Y | S30: Y | T30: Y | U30: Y | V30: Y | AO30: =IF(I30="No","1","")&IF(I30="N/A","2","")
A31: FS | B31: Facility Security | AO31: =IF(I31="No","1","")&IF(I31="N/A","2","")
W32: =IF(I33="No", "Comments","") & IF(I33="N/A", "Comments","")
A33: FS | B33: Facility Security | D33: Policy | E33: FS-01 | F33: FS-01.1 | G33: CR | H33: Can you provide evidence that policies and procedures have been established for maintaining a safe and secure working environment in offices (e.g., clean desk sweeps), rooms, facilities and secure area where NYP data is accessed or stored? | J33: COBIT 4.1 DS5.7, DS 12.1, DS 12.4 DS 4.9 | K33: 45 CFR 164.310 (a)(1) 45 CFR 164.310 (a)(2)(ii) 45 CFR 164.308(a)(3)(ii)(A) (New) 45 CFR 164.310 (a)(2)(iii) (New) | L33: A.5.1.1 A.9.1.3 A.9.1.5 | M33: NIST SP800-53 R3 CA-2 NIST SP800-53 R3 PE-1 NIST SP800-53 R3 PE-6 NIST SP800-53 R3 PE-7 NIST SP800-53 R3 PE-8 | N33: NIST SP800-53 R3 CA-2_x000D_ NIST SP800-53 R3 CA-2 (1)_x000D_ NIST SP800-53 R3 PE-1_x000D_ NIST SP800-53 R3 PE-6_x000D_ NIST SP800-53 R3 PE-6 (1)_x000D_ NIST SP800-53 R3 PE-7_x000D_ NIST SP800-53 R3 PE-7 (1)_x000D_ NIST SP800-53 R3 PE-8_x000D_ | O33: PCI DSS v2.0 9.1 PCI DSS v2.0 9.2 PCI DSS v2.0 9.3 PCI DSS v2.0 9.4 | P33: AUP v5.0 F.2 SIG v6.0: F.1.1, F.1.2 F.1.3, F.1.4, F1.5, F.1.6, F.1.7, F.1.8, F.1.9, F.2.1, F.2.2, F.2.3, F.2.4, F.2.5, F2.6, F.2.7, F.2.8, F.2.9, F.2.10, F.2.11, F.2.12, F.2.13, F.2.14, F.2.15, F.2.16, F.2.17, F.2.18,F.2.19, F.2.20 | Q33: GAPP Ref 8.1.0 GAPP Ref 8.1.1 GAPP Ref 8.2.1 | R33: Y | S33: Y | T33: Y | U33: Y | V33: Y | AO33: =IF(I33="No","1","")&IF(I33="N/A","2","")
W34: =IF(I35="No", "Comments","") & IF(I35="N/A", "Comments","")
A35: FS | B35: Facility Security | D35: User Access | E35: FS-02 | F35: FS-02.1 | G35: CR | H35: Is access to the data center limited to only workforce members that require access? | K35: 45 CFR 164.310(a)(1) (New) 45 CFR 164.310(a)(2)(ii) (New) 45 CFR 164.310(b) (New) 45 CFR 164.310 ( c) (New) | L35: A.9.1.1 A.9.1.2 | M35: NIST SP800-53 R3 PE-2 NIST SP800-53 R3 PE-3 NIST SP800-53 R3 PE-4 NIST SP800-53 R3 PE-5 NIST SP800-53 R3 PE-6 | N35: NIST SP800-53 R3 PE-2_x000D_ NIST SP800-53 R3 PE-2 (1)_x000D_ NIST SP800-53 R3 PE-3_x000D_ NIST SP800-53 R3 PE-4_x000D_ NIST SP800-53 R3 PE-5_x000D_ NIST SP800-53 R3 PE-6_x000D_ NIST SP800-53 R3 PE-6 (1)_x000D_ | O35: PCI DSS v2.0 9.1 | P35: AUP v5.0 H.6 SIG v6.0: F.1.2.3, F.1.2.4, F.1.2.5, F.1.2.6, F.1.2.8, F.1.2. 9, F.1.2.10, F.1.2.11, F.1.2.12, F.1.2.13, F.1.2.14, F.1.2.15, F.1.2.24, F.1.4.2, F1.4.6, F.1.4.7, F.1.7, F.1.8, F.2.13, F.2.14, F.2.15, F.2.16, F.2.17, F.2.18 | Q35: GAPP Ref 8.2.1 GAPP Ref 8.2.2 GAPP Ref 8.2.3 | R35: N | S35: N | T35: N | U35: N | V35: N | AO35: =IF(I35="No","1","")&IF(I35="N/A","2","")
W36: =IF(I37="No", "Comments","") & IF(I37="N/A", "Comments","")
A37: FS | B37: Facility Security | D37: Offsite Authorization | E37: FS-06 | F37: FS-06.1 | G37: CR | H37: Do you have documentation that describes scenarios where data may be moved from one physical location to another? (ex. Offsite backups, business continuity failovers, replication). Can you provide that to NYP? | K37: 45 CFR 164.310 (d)(1) (New) | L37: A.9.2.7 A.10.1.2 | M37: NIST SP800-53 R3 MA-1 NIST SP800-53 R3 MA-2 NIST SP800-53 R3 PE-16 | N37: NIST SP800-53 R3 MA-1_x000D_ NIST SP800-53 R3 MA-2_x000D_ NIST SP800-53 R3 MA-2 (1)_x000D_ NIST SP800-53 R3 PE-16_x000D_ | O37: PCI DSS v2.0 9.8 PCI DSS v2.0 9.9 | P37: AUP v5.0 G.21 SIG v6.0:F.2.18 | Q37: GAPP Ref 8.2.5 GAPP Ref 8.2.6 | R37: Y | S37: Y | T37: Y | U37: Y | V37: Y | AO37: =IF(I37="No","1","")&IF(I37="N/A","2","")
W38: =IF(I39="No", "Comments","") & IF(I39="N/A", "Comments","")
A39: FS | B39: Facility Security | D39: Asset Management | E39: FS-08 | F39: FS-08.1 | G39: CR | H39: Do you maintain a complete inventory of all of your critical assets which includes ownership of the asset? | K39: 45 CFR 164.310 (d)(2)(iii) | L39: A.7.1.1 A.7.1.2 | M39: NIST SP800-53 R3 CM-8 | N39: NIST SP800-53 R3 CM-8_x000D_ NIST SP800-53 R3 CM-8 (1)_x000D_ NIST SP800-53 R3 CM-8 (3)_x000D_ NIST SP800-53 R3 CM-8 (5)_x000D_ | O39: PCI DSS v2.0 9.9.1 PCI DSS v2.0 12.3.3 PCI DSS v2.0 12.3.4 | P39: AUP v5.0 D.1 SIG v6.0: D.1.1, D.2.1. D.2.2, | R39: Y | S39: Y | T39: Y | U39: Y | V39: Y | AO39: =IF(I39="No","1","")&IF(I39="N/A","2","")
W40: =IF(I41="No", "Comments","") & IF(I41="N/A", "Comments","")
A41: FS | B41: Facility Security | E41: FS-08 | F41: FS-08.2 | G41: CR | H41: Do you maintain a complete inventory of all of your critical supplier relationships? | K41: 45 CFR 164.310 (d)(2)(iii) | L41: A.7.1.1 A.7.1.2 | M41: NIST SP800-53 R3 CM-8 | N41: NIST SP800-53 R3 CM-8_x000D_ NIST SP800-53 R3 CM-8 (1)_x000D_ NIST SP800-53 R3 CM-8 (3)_x000D_ NIST SP800-53 R3 CM-8 (5)_x000D_ | O41: PCI DSS v2.0 9.9.1 PCI DSS v2.0 12.3.3 PCI DSS v2.0 12.3.4 | P41: AUP v5.0 D.1 SIG v6.0: D.1.1, D.2.1. D.2.2, | R41: Y | S41: Y | T41: Y | U41: Y | V41: Y | AO41: =IF(I41="No","1","")&IF(I41="N/A","2","")
A42: HR | B42: Human Resources Security | AO42: =IF(I42="No","1","")&IF(I42="N/A","2","")
W43: =IF(I44="No", "Comments","") & IF(I44="N/A", "Comments","")
A44: HR | B44: Human Resources Security | D44: Background Screening | E44: HR-01 | F44: HR-01.1 | G44: CR | H44: Pursuant to local laws, regulations, ethics and contractual constraints are all employment candidates, contractors and third parties subject to background verification? | J44: COBIT 4.1 PO 7.6 | L44: A.8.1.2 | M44: NIST SP800-53 R3 PS-2 NIST SP800-53 R3 PS-3 | N44: NIST SP800-53 R3 PS-2_x000D_ NIST SP800-53 R3 PS-3_x000D_ | O44: PCI DSS v2.0 12.7 PCI DSS v2.0 12.8.3 | P44: AUP v5.0 E.2 SIG v6.0: E.2 | Q44: GAPP Ref 1.2.9 | R44: Y | S44: Y | T44: Y | U44: Y | V44: Y | AO44: =IF(I44="No","1","")&IF(I44="N/A","2","")
A45: IS | B45: Information Security | AO45: =IF(I45="No","1","")&IF(I45="N/A","2","")
W46: =IF(I47="No", "Comments","") & IF(I47="N/A", "Comments","")
A47: IS | B47: Information Security | D47: Management Program | E47: IS-01 | F47: IS-01.1 | G47: CR | H47: Do you have a policy or standards document approved by your executive leadership (CEO, COO, CIO, etc.) that describes your Information Security Management Program (ISMP)? | J47: COBIT 4.1 R2 DS5.2 COBIT 4.1 R2 DS5.5 | K47: 45 CFR 164.308(a)(1)(i) 45 CFR 164.308(a)(1)(ii)(B) 45 CFR 164.316(b)(1)(i) 45 CFR 164.308(a)(3)(i) (New) 45 CFR 164.306(a) (New) | L47: Clause 4.2 Clause 5 A.6.1.1 A.6.1.2 A.6.1.3 A.6.1.4 A.6.1.5 A.6.1.6 A.6.1.7 A.6.1.8 | M47: NIST SP800-53 R3 PM-1 NIST SP800-53 R3 PM-2 NIST SP800-53 R3 PM-3 NIST SP800-53 R3 PM-4 NIST SP800-53 R3 PM-5 NIST SP800-53 R3 PM-6 NIST SP800-53 R3 PM-7 NIST SP800-53 R3 PM-8 NIST SP800-53 R3 PM-9 NIST SP800-53 R3 PM-10 NIST SP800-53 R3 PM-11 | N47: NIST SP800-53 R3 PM-1_x000D_ NIST SP800-53 R3 PM-2_x000D_ NIST SP800-53 R3 PM-3_x000D_ NIST SP800-53 R3 PM-4_x000D_ NIST SP800-53 R3 PM-5_x000D_ NIST SP800-53 R3 PM-6_x000D_ NIST SP800-53 R3 PM-7_x000D_ NIST SP800-53 R3 PM-8_x000D_ NIST SP800-53 R3 PM-9_x000D_ NIST SP800-53 R3 PM-10_x000D_ NIST SP800-53 R3 PM-11_x000D_ | O47: PCI DSS v2.0 12.1 PCI DSS v2.0 12.2 | P47: SIG v6.0: A.1, B.1 | Q47: GAPP Ref 8.2.1 | R47: Y | S47: Y | T47: Y | U47: Y | V47: Y | AO47: =IF(I47="No","1","")&IF(I47="N/A","2","")
W48: =IF(I49="Yes", "Comments","")
A49: IS | B49: Information Security | D49: Policy | E49: IS-03 | F49: IS-03.1 | G49: CR | H49: Do your information security and privacy policies and standards align with particular international and industry standards (ISO-27001/2, COBIT, NIST SP 800-36/37/53, etc.)? Please specify. | J49: COBIT 4.1 DS5.2 | K49: 45 CFR 164.316 (a) 45 CFR 164.316 (b)(1)(i) 45 CFR 164.316 (b)(2)(ii) 45 CFR 164.308(a)(2) (New) | L49: Clause 4.2.1 Clause 5 A.5.1.1 A.8.2.2 | O49: PCI DSS v2.0 12.1 PCI DSS v2.0 12.2 | P49: SIG v6.0:B.1 | Q49: GAPP Ref 8.1.0 GAPP Ref 8.1.1 | R49: Y | S49: Y | T49: Y | U49: Y | V49: Y | AO49: =IF(I49="Yes","1","")
W50: =IF(I51="No", "Comments","") & IF(I51="N/A", "Comments","")
F51: IS-03.3 | G51: CR | H51: Do you map your controls, architecture and processes to regulations and/or standards? | AO51: =IF(I51="No","1","")&IF(I51="N/A","2","")
W52: =IF(I53="No", "Comments","") & IF(I53="N/A", "Comments","")
A53: IS | B53: Information Security | D53: Policy Reviews | E53: IS-05 | F53: IS-05.1 | G53: CR | H53: Will you notify NYP when you make material changes to your information security and/or privacy policies? | J53: COBIT 4.1 DS 5.2 DS 5.4 | K53: 45 CFR 164.316 (b)(2)(iii) 45 CFE 164.306(e) (New) | L53: Clause 4.2.3 f) A.5.1.2 | O53: PCI DSS v2.0 12.1.3 | P53: AUP v5.0 B.2 SIG v6.0: B.1.33. B.1.34, | Q53: GAPP Ref 1.2.1 GAPP Ref 8.2.7 GAPP Ref 10.2.3 | R53: Y | S53: Y | T53: Y | U53: Y | V53: Y | AO53: =IF(I53="No","1","")&IF(I53="N/A","2","")
W54: =IF(I55="No", "Comments","") & IF(I55="N/A", "Comments","")
A55: IS | B55: Information Security | D55: Policy Enforcement | E55: IS-06 | F55: IS-06.1 | G55: CR | H55: Is a formal disciplinary or sanction policy established for employees who have violated security policies and procedures? | J55: COBIT 4.1 PO 7.7 | K55: 45 CFR 164.308 (a)(1)(ii)(C) | L55: A.8.2.3 | M55: NIST SP800-53 R3 PL-4 NIST SP800-53 R3 PS-1 NIST SP800-53 R3 PS-8 | N55: NIST SP800-53 R3 PL-4_x000D_ NIST SP800-53 R3 PS-1_x000D_ NIST SP800-53 R3 PS-8_x000D_ | P55: SIG v6.0:B.1.5 | Q55: GAPP Ref 10.2.4 | R55: Y | S55: Y | T55: Y | U55: Y | V55: Y | AO55: =IF(I55="No","1","")&IF(I55="N/A","2","")
W56: =IF(I57="No", "Comments","") & IF(I57="N/A", "Comments","") & IF(I57="Yes", "Please Specify Timing","")
A57: IS | B57: Information Security | D57: User Access Revocation | E57: IS-07 | F57: IS-07.1 | G57: CR | H57: Do you have controls in place ensuring timely removal of systems access to NYP data when no longer required for business purposes? Please specify timing. | J57: COBIT 4.1 DS 5.4 | K57: 45 CFR 164.308 (a)(3)(i) 45 CFR 164.312 (a)(1) 45 CFR 164.312 (a)(2)(ii) 45 CFR 164.308(a)(4)(ii)(B) (New) 45 CFR 164.308(a)(4)(ii)(c ) (New) | L57: A.11.1.1 A.11.2.1 A.11.2.4 A.11.4.1 A.11.5.2 A.11.6.1 | M57: NIST SP800-53 R3 AC-1 NIST SP800-53 R3 IA-1 | N57: NIST SP800-53 R3 AC-1_x000D_ NIST SP800-53 R3 IA-1_x000D_ | O57: PCI DSS v2.0 3.5.1 PCI DSS v2.0 8.5.1 PCI DSS v2.0 12.5.4 | P57: AUP v5.0 B.1 SIG v6.0: B.1.8, B.1.21, B.1.28, E.6.2, H.1.1, K.1.4.5, | Q57: GAPP Ref 8.1.0 | R57: Y | S57: Y | T57: Y | U57: Y | V57: Y | AO57: =IF(I57="No","1","")&IF(I57="N/A","2","")&IF(I57="Yes","3","")
W58: =IF(I59="No", "Comments","") & IF(I59="N/A", "Comments","")
A59: IS | B59: Information Security | D59: User Access Restriction / Authorization | E59: IS-08 | F59: IS-08.1 | G59: CR | H59: Do you have documented procedures on how you grant and approve access to NYP data? | J59: COBIT 4.1 DS5.4 | K59: 45 CFR 164.308 (a)(3)(i) 45 CFR 164.308 (a)(3)(ii)(A) 45 CFR 164.308 (a)(4)(i) 45 CFR 164.308 (a)(4)(ii)(B) 45 CFR 164.308 (a)(4)(ii)(C) 45 CFR 164.312 (a)(1) | L59: A.11.2.1 A.11.2.2 A.11.4.1 A 11.4.2 A.11.6.1 | M59: NIST SP800-53 R3 AC-3 NIST SP800-53 R3 AC-5 NIST SP800-53 R3 AC-6 NIST SP800-53 R3 IA-2 NIST SP800-53 R3 IA-4 NIST SP800-53 R3 IA-5 NIST SP800-53 R3 IA-8 NIST SP800-53 R3 MA-5 NIST SP800-53 R3 PS-6 NIST SP800-53 R3 SA-7 NIST SP800-53 R3 SI-9 | O59: PCI DSS v2.0 7.1 PCI DSS v2.0 7.1.1 PCI DSS v2.0 7.1.2 PCI DSS v2.0 7.1.3 PCI DSS v2.0 7.2.1 PCI DSS v2.0 7.2.2 PCI DSS v2.0 8.5.1 PCI DSS v2.0 12.5.4 | P59: SIG v6.0: H.2.4, H.2.5, | Q59: GAPP Ref 8.2.2 | R59: Y | S59: Y | T59: Y | U59: Y | V59: Y | AO59: =IF(I59="No","1","")&IF(I59="N/A","2","")
W60: =IF(I61="No", "Comments","") & IF(I61="N/A", "Comments","")
A61: IS | B61: Information Security | D61: User Access Reviews | E61: IS-10 | F61: IS-10.1 | G61: CR | H61: Do you require at least annual certification of entitlements for all system users and administrators (exclusive of users maintained by NYP)? | J61: COBIT 4.1 DS5.3 COBIT 4.1 DS5.4 | K61: 45 CFR 164.308 (a)(3)(ii)(B) 45 CFR 164.308 (a)(4)(ii)(C) | L61: A.11.2.4 | M61: NIST SP800-53 R3 AC-2 NIST SP800-53 R3 AU-6 NIST SP800-53 R3 PM-10 NIST SP800-53 R3 PS-6 NIST SP800-53 R3 PS-7 | P61: SIG v6.0:H.2.6, H.2.7, H.2.9, | Q61: GAPP Ref 8.2.1 GAPP Ref 8.2.7 | R61: Y | S61: Y | T61: Y | U61: Y | V61: Y | AO61: =IF(I61="No","1","")&IF(I61="N/A","2","")
W62: =IF(I63="No", "Comments","") & IF(I63="N/A", "Comments","")
A63: IS | B63: Information Security | E63: IS-10 | F63: IS-10.2 | G63: CR | H63: If users are found to have inappropriate entitlements, are all remediation and certification actions recorded? | J63: COBIT 4.1 DS5.3 COBIT 4.1 DS5.4 | K63: 45 CFR 164.308 (a)(3)(ii)(B) 45 CFR 164.308 (a)(4)(ii)(C) | L63: A.11.2.4 | M63: NIST SP800-53 R3 AC-2 NIST SP800-53 R3 AU-6 NIST SP800-53 R3 PM-10 NIST SP800-53 R3 PS-6 NIST SP800-53 R3 PS-7 | P63: SIG v6.0:H.2.6, H.2.7, H.2.9, | Q63: GAPP Ref 8.2.1 GAPP Ref 8.2.7 | R63: Y | S63: Y | T63: Y | U63: Y | V63: Y | AO63: =IF(I63="No","1","")&IF(I63="N/A","2","")
W64: =IF(I65="No", "Comments","") & IF(I65="N/A", "Comments","")
A65: IS | B65: Information Security | E65: IS-10 | F65: IS-10.3 | G65: CR | H65: Will you notify NYP if inappropriate access may have been allowed to NYP data? | J65: COBIT 4.1 DS5.3 COBIT 4.1 DS5.4 | K65: 45 CFR 164.308 (a)(3)(ii)(B) 45 CFR 164.308 (a)(4)(ii)(C) | L65: A.11.2.4 | M65: NIST SP800-53 R3 AC-2 NIST SP800-53 R3 AU-6 NIST SP800-53 R3 PM-10 NIST SP800-53 R3 PS-6 NIST SP800-53 R3 PS-7 | P65: SIG v6.0:H.2.6, H.2.7, H.2.9, | Q65: GAPP Ref 8.2.1 GAPP Ref 8.2.7 | R65: Y | S65: Y | T65: Y | U65: Y | V65: Y | AO65: =IF(I65="No","1","")&IF(I65="N/A","2","")
W66: =IF(I67="No", "Comments","") & IF(I67="N/A", "Comments","")
A67: IS | B67: Information Security | D67: Training / Awareness | E67: IS-11 | F67: IS-11.1 | G67: CR | H67: Are administrators and data stewards properly educated on their legal responsibilities with regard to security and data integrity? | J67: COBIT 4.1 PO 7.4 | K67: 45 CFR 164.308 (a)(5)(i) 45 CFR 164.308 (a)(5)(ii)(A) | L67: Clause 5.2.2 A.8.2.2 | M67: NIST SP800-53 R3 AT-1 NIST SP800-53 R3 AT-2 NIST SP800-53 R3 AT-3 NIST SP800-53 R3 AT-4 | N67: NIST SP800-53 R3 AT-1_x000D_ NIST SP800-53 R3 AT-2_x000D_ NIST SP800-53 R3 AT-3_x000D_ NIST SP800-53 R3 AT-4_x000D_ | O67: PCI DSS v2.0 12.6 PCI DSS v2.0 12.6.1 PCI DSS v2.0 12.6.2 | P67: AUP v5.0 E.1 SIG v6.0:E.4 | Q67: GAPP Ref 1.2.10 GAPP Ref 8.2.1 | R67: Y | S67: Y | T67: Y | U67: Y | V67: Y | AO67: =IF(I67="No","1","")&IF(I67="N/A","2","")
W68: =IF(I69="No", "Comments","") & IF(I69="N/A", "Comments","")
A69: IS | B69: Information Security | D69: User Responsibility | E69: IS-16 | F69: IS-16.1 | G69: CR | H69: Do you specifically train your workforce in their responsibilities for maintaining awareness and compliance with published security policies, procedures, standards and applicable regulatory requirements and do they acknowledge their responsibilities? | J69: COBIT 4.1 PO 4.6 | K69: 45 CFR 164.308 (a)(5)(ii)(D) | L69: Clause 5.2.2 A.8.2.2 A.11.3.1 A.11.3.2 | M69: NIST SP800-53 R3 AT-2 NIST SP800-53 R3 AT-3 NIST SP800-53 R3 AT-4 NIST SP800-53 R3 PL-4 | N69: NIST SP800-53 R3 AT-2_x000D_ NIST SP800-53 R3 AT-3_x000D_ NIST SP800-53 R3 AT-4_x000D_ NIST SP800-53 R3 PL-4_x000D_ | O69: PCI DSS v2.0 8.5.7 PCI DSS v2.0 12.6.1 | P69: AUP v5.0 E.1 SIG v6.0: E.4 | Q69: GAPP Ref 1.2.10 GAPP Ref 8.2.1 | R69: Y | S69: Y | T69: Y | U69: Y | V69: Y | AO69: =IF(I69="No","1","")&IF(I69="N/A","2","")
W70: =IF(I71="Yes", "Specify Encription Methods Used","") & IF(I71="No", "Comments","")& IF(I71="N/A", "Please Explain","")
A71: IS | B71: Information Security | D71: Encryption | E71: IS-19 | F71: IS-19.1 | G71: CR | H71: Do you encrypt NYP data at rest (on disk/storage) within your environment? Please specify encryption methods used. | J71: COBIT 4.1 DS5.8 | K71: 45 CFR 164.312 (a)(2)(iv) 45 CFR 164.312(e)(1) (New) | L71: Clause 4.3.3 A.10.7.3 A.12.3.2 A.15.1.6 | M71: NIST SP800-53 R3 SC-12 NIST SP800-53 R3 SC-13 NIST SP800-53 R3 SC-17 NIST SP800-53 R3 SC-28 | N71: NIST SP800-53 R3 SC-12_x000D_ NIST SP800-53 R3 SC-12 (2)_x000D_ NIST SP800-53 R3 SC-12 (5)_x000D_ NIST SP800-53 R3 SC-13_x000D_ NIST SP800-53 R3 SC-13 (1)_x000D_ NIST SP800-53 R3 SC-17_x000D_ NIST SP800-53 R3 SC-28_x000D_ NIST SP800-53 R3 SC-28 (1)_x000D_ | O71: PCI-DSS v2.0 3.4.1 PCI-DSS v2.0 3.5 PCI-DSS v2.0 3.5.1 PCI-DSS v2.0 3.5.2 PCI-DSS v2.0 3.6 PCI-DSS v2.0 3.6.1 PCI-DSS v2.0 3.6.2 PCI-DSS v2.0 3.6.3 PCI-DSS v2.0 3.6.4 PCI-DSS v2.0 3.6.5 PCI-DSS v2.0 3.6.6 PCI-DSS v2.0 3.6.7 PCI-DSS v2.0 3.6.8 | P71: SIG v6.0: L.6 | Q71: GAPP Ref 8.1.1 GAPP Ref 8.2.1 GAPP Ref 8.2.5 | R71: Y | S71: Y | T71: Y | U71: Y | V71: Y | AO71: =IF(I71="No","1","")&IF(I71="N/A","2","")&IF(I71="Yes","3","")
W72: =IF(I73="Yes", "Specify Encription Methods Used","") & IF(I73="No", "Comments","")& IF(I73="N/A", "Please Explain","")
H73: Do you encrypt all NYP data and transactions that traverse public networks? Please specify encryption methods used. | AO73: =IF(I73="No","1","")&IF(I73="N/A","2","")&IF(I73="Yes","3","")
W74: =IF(I75="Yes", "Specify Encription Methods Used","") & IF(I75="No", "Comments","")& IF(I75="N/A", "Please Explain","")
A75: IS | B75: Information Security | E75: IS-19 | F75: IS-19.2 | G75: CR | H75: Do you encrypt data and virtual machine images in transit across and between networks and hypervisor instances? Please specify encryption methods used. | J75: COBIT 4.1 DS5.8 | K75: 45 CFR 164.312 (a)(2)(iv) 45 CFR 164.312(e)(1) (New) | L75: Clause 4.3.3 A.10.7.3 A.12.3.2 A.15.1.6 | M75: NIST SP800-53 R3 SC-12 NIST SP800-53 R3 SC-13 NIST SP800-53 R3 SC-17 NIST SP800-53 R3 SC-28 | N75: NIST SP800-53 R3 SC-12_x000D_ NIST SP800-53 R3 SC-12 (2)_x000D_ NIST SP800-53 R3 SC-12 (5)_x000D_ NIST SP800-53 R3 SC-13_x000D_ NIST SP800-53 R3 SC-13 (1)_x000D_ NIST SP800-53 R3 SC-17_x000D_ NIST SP800-53 R3 SC-28_x000D_ NIST SP800-53 R3 SC-28 (1)_x000D_ | O75: PCI-DSS v2.0 3.4.1 PCI-DSS v2.0 3.5 PCI-DSS v2.0 3.5.1 PCI-DSS v2.0 3.5.2 PCI-DSS v2.0 3.6 PCI-DSS v2.0 3.6.1 PCI-DSS v2.0 3.6.2 PCI-DSS v2.0 3.6.3 PCI-DSS v2.0 3.6.4 PCI-DSS v2.0 3.6.5 PCI-DSS v2.0 3.6.6 PCI-DSS v2.0 3.6.7 PCI-DSS v2.0 3.6.8 | P75: SIG v6.0: L.6 | Q75: GAPP Ref 8.1.1 GAPP Ref 8.2.1 GAPP Ref 8.2.5 | R75: Y | S75: Y | T75: Y | U75: Y | V75: Y | AO75: =IF(I75="No","1","")&IF(I75="N/A","2","")&IF(I75="Yes","3","")
W76: =IF(I77="No", "Comments","") & IF(I77="N/A", "Comments","")
A77: IS | B77: Information Security | E77: IS-19 | F77: IS-19.4 | G77: CR | H77: Do you maintain key management procedures? | J77: COBIT 4.1 DS5.8 | K77: 45 CFR 164.312 (a)(2)(iv) 45 CFR 164.312(e)(1) (New) | L77: Clause 4.3.3 A.10.7.3 A.12.3.2 A.15.1.6 | M77: NIST SP800-53 R3 SC-12 NIST SP800-53 R3 SC-13 NIST SP800-53 R3 SC-17 NIST SP800-53 R3 SC-28 | N77: NIST SP800-53 R3 SC-12_x000D_ NIST SP800-53 R3 SC-12 (2)_x000D_ NIST SP800-53 R3 SC-12 (5)_x000D_ NIST SP800-53 R3 SC-13_x000D_ NIST SP800-53 R3 SC-13 (1)_x000D_ NIST SP800-53 R3 SC-17_x000D_ NIST SP800-53 R3 SC-28_x000D_ NIST SP800-53 R3 SC-28 (1)_x000D_ | O77: PCI-DSS v2.0 3.4.1 PCI-DSS v2.0 3.5 PCI-DSS v2.0 3.5.1 PCI-DSS v2.0 3.5.2 PCI-DSS v2.0 3.6 PCI-DSS v2.0 3.6.1 PCI-DSS v2.0 3.6.2 PCI-DSS v2.0 3.6.3 PCI-DSS v2.0 3.6.4 PCI-DSS v2.0 3.6.5 PCI-DSS v2.0 3.6.6 PCI-DSS v2.0 3.6.7 PCI-DSS v2.0 3.6.8 | P77: SIG v6.0: L.6 | Q77: GAPP Ref 8.1.1 GAPP Ref 8.2.1 GAPP Ref 8.2.5 | R77: Y | S77: Y | T77: Y | U77: Y | V77: Y | AO77: =IF(I77="No","1","")&IF(I77="N/A","2","")
W78: =IF(I79="No", "Comments","") & IF(I79="N/A", "Comments","")
A79: IS | B79: Information Security | D79: Vulnerability / Patch Management | E79: IS-20 | F79: IS-21.1 | G79: CR | H79: Do you perform vulnerability scans (application, network, and operating system) regularly of assets used for NYP? | J79: COBIT 4.1 AI6.1 COBIT 4.1 AI3.3 COBIT 4.1 DS5.9 | K79: 45 CFR 164.308 (a)(1)(i)(ii)(A) 45 CFR 164.308 (a)(1)(i)(ii)(B) 45 CFR 164.308 (a)(5)(i)(ii)(B) | L79: A.12.5.1 A.12.5.2 A.12.6.1 | M79: NIST SP800-53 R3 CM-3 NIST SP800-53 R3 CM-4 NIST SP800-53 R3 CP-10 NIST SP800-53 R3 RA-5 NIST SP800-53 R3 SA-7 NIST SP800-53 R3 SI-1 NIST SP800-53 R3 SI-2 NIST SP800-53 R3 SI-5 | O79: PCI-DSS v2.0 2.2 PCI-DSS v2.0 6.1 PCI-DSS v2.0 6.2 PCI-DSS v2.0 6.3.2 PCI-DSS v2.0 6.4.5 PCI-DSS v2.0 6.5.X PCI-DSS v2.0 6.6 PCI-DSS v2.0 11.2 PCI-DSS v2.0 11.2.1 PCI-DSS v2.0 11.2.2 PCI-DSS v2.0 11.2.3 | P79: AUP v5.0 I.4 SIG v6.0: G.15.2, I.3 | Q79: GAPP Ref 1.2.6 GAPP Ref 8.2.7 | R79: Y | S79: Y | T79: Y | U79: Y | V79: Y | AO79: =IF(I79="No","1","")&IF(I79="N/A","2","")
W80: =IF(I81="No", "Comments","") & IF(I81="N/A", "Comments","")
A81: IS | B81: Information Security | E81: IS-20 | F81: IS-20.5 | G81: CR | H81: Do you have a capability to rapidly patch vulnerabilities across all of your computing devices, applications, and systems? | J81: COBIT 4.1 AI6.1 COBIT 4.1 AI3.3 COBIT 4.1 DS5.9 | K81: 45 CFR 164.308 (a)(1)(i)(ii)(A) 45 CFR 164.308 (a)(1)(i)(ii)(B) 45 CFR 164.308 (a)(5)(i)(ii)(B) | L81: A.12.5.1 A.12.5.2 A.12.6.1 | M81: NIST SP800-53 R3 CM-3 NIST SP800-53 R3 CM-4 NIST SP800-53 R3 CP-10 NIST SP800-53 R3 RA-5 NIST SP800-53 R3 SA-7 NIST SP800-53 R3 SI-1 NIST SP800-53 R3 SI-2 NIST SP800-53 R3 SI-5 | O81: PCI-DSS v2.0 2.2 PCI-DSS v2.0 6.1 PCI-DSS v2.0 6.2 PCI-DSS v2.0 6.3.2 PCI-DSS v2.0 6.4.5 PCI-DSS v2.0 6.5.X PCI-DSS v2.0 6.6 PCI-DSS v2.0 11.2 PCI-DSS v2.0 11.2.1 PCI-DSS v2.0 11.2.2 PCI-DSS v2.0 11.2.3 | P81: AUP v5.0 I.4 SIG v6.0: G.15.2, I.3 | Q81: GAPP Ref 1.2.6 GAPP Ref 8.2.7 | R81: Y | S81: Y | T81: Y | U81: Y | V81: Y | AO81: =IF(I81="No","1","")&IF(I81="N/A","2","")
W82: =IF(I83="No", "Comments","") & IF(I83="N/A", "Comments","")
A83: IS | B83: Information Security | D83: Antivirus / Malicious Software | E83: IS-21 | F83: IS-21.1 | G83: CR | H83: Do you have anti-malware programs installed on all systems which support NYP? | J83: COBIT 4.1 DS5.9 | K83: 45 CFR 164.308 (a)(5)(ii)(B) | L83: A.10.4.1 | M83: NIST SP800-53 R3 SA-7 NIST SP800-53 R3 SC-5 NIST SP800-53 R3 SI-3 NIST SP800-53 R3 SI-5 NIST SP800-53 R3 SI-7 NIST SP800-53 R3 SI-8 | N83: NIST SP800-53 R3 SA-7_x000D_ NIST SP800-53 R3 SC-5_x000D_ NIST SP800-53 R3 SI-3_x000D_ NIST SP800-53 R3 SI-3 (1)_x000D_ NIST SP800-53 R3 SI-3 (2)_x000D_ NIST SP800-53 R3 SI-3 (3)_x000D_ NIST SP800-53 R3 SI-5_x000D_ NIST SP800-53 R3 SI-7_x000D_ NIST SP800-53 R3 SI-7 (1)_x000D_ NIST SP800-53 R3 SI-8_x000D_ | O83: PCI-DSS v2.0 5.1 PCI-DSS v2.0 5.1.1 PCI-DSS v2.0 5.2 | P83: SIG v6.0:G.7 | Q83: GAPP Ref 8.2.2 | R83: Y | S83: Y | T83: Y | U83: Y | V83: Y | AO83: =IF(I83="No","1","")&IF(I83="N/A","2","")
W84: =IF(I85="No", "Comments","") & IF(I85="N/A", "Comments","")
A85: IS | B85: Information Security | E85: IS-21 | F85: IS-21.2 | G85: CR | H85: Do you ensure that security threat detection systems which use signatures, lists, or behavioral patterns are updated across all infrastructure components within industry accepted timeframes? | J85: COBIT 4.1 DS5.9 | K85: 45 CFR 164.308 (a)(5)(ii)(B) | L85: A.10.4.1 | M85: NIST SP800-53 R3 SA-7 NIST SP800-53 R3 SC-5 NIST SP800-53 R3 SI-3 NIST SP800-53 R3 SI-5 NIST SP800-53 R3 SI-7 NIST SP800-53 R3 SI-8 | N85: NIST SP800-53 R3 SA-7_x000D_ NIST SP800-53 R3 SC-5_x000D_ NIST SP800-53 R3 SI-3_x000D_ NIST SP800-53 R3 SI-3 (1)_x000D_ NIST SP800-53 R3 SI-3 (2)_x000D_ NIST SP800-53 R3 SI-3 (3)_x000D_ NIST SP800-53 R3 SI-5_x000D_ NIST SP800-53 R3 SI-7_x000D_ NIST SP800-53 R3 SI-7 (1)_x000D_ NIST SP800-53 R3 SI-8_x000D_ | O85: PCI-DSS v2.0 5.1 PCI-DSS v2.0 5.1.1 PCI-DSS v2.0 5.2 | P85: SIG v6.0:G.7 | Q85: GAPP Ref 8.2.2 | R85: Y | S85: Y | T85: Y | U85: Y | V85: Y | AO85: =IF(I85="No","1","")&IF(I85="N/A","2","")
W86: =IF(I87="No", "Comments","") & IF(I87="N/A", "Comments","")
A87: IS | B87: Information Security | D87: Incident Management | E87: IS-22 | F87: IS-22.1 | G87: CR | H87: Do you have a documented security incident response plan? | J87: COBIT 4.1 DS5.6 | K87: 45 CFR 164.308 (a)(1)(i) 45 CFR 164.308 (a)(6)(i) 45 CFR 164.308 (a)(3)(ii)(c) | L87: Clause 4.3.3 A.13.1.1 A.13.2.1 | M87: NIST SP800-53 R3 IR-1 NIST SP800-53 R3 IR-2 NIST SP800-53 R3 IR-3 NIST SP800-53 R3 IR-4 NIST SP800-53 R3 IR-5 NIST SP800-53 R3 IR-7 NIST SP800-53 R3 IR-8 NIST SP800-53 R3 PS-4 | N87: NIST SP800-53 R3 IR-1_x000D_ NIST SP800-53 R3 IR-2_x000D_ NIST SP800-53 R3 IR-3_x000D_ NIST SP800-53 R3 IR-4_x000D_ NIST SP800-53 R3 IR-4 (1)_x000D_ NIST SP800-53 R3 IR-5_x000D_ NIST SP800-53 R3 IR-7_x000D_ NIST SP800-53 R3 IR-7 (1)_x000D_ NIST SP800-53 R3 IR-7 (2)_x000D_ NIST SP800-53 R3 IR-8_x000D_ | O87: PCI-DSS v2.0 12.9 PCI-DSS v2.0 12.9.1 PCI-DSS v2.0 12.9.2 PCI-DSS v2.0 12.9.3 PCI-DSS v2.0 12.9.4 PCI-DSS v2.0 12.9.5 PCI-DSS v2.0 12.9.6 | P87: AUP v5.0 J.1 SIG v6.0: J.1.1, J.1.2 | Q87: GAPP Ref 1.2.4 GAPP Ref 1.2.7 GAPP Ref 7.1.2 GAPP Ref 7.2.2 GAPP Ref 7.2.4 GAPP Ref 10.2.1 GAPP Ref 10.2.4 | R87: Y | S87: Y | T87: Y | U87: Y | V87: Y | AO87: =IF(I87="No","1","")&IF(I87="N/A","2","")
W88: =IF(I89="No", "Comments","") & IF(I89="N/A", "Comments","")
H89: Are systems in place to monitor for privacy breaches and notify NYP expeditiously if a privacy event may have impacted our data? | AO89: =IF(I89="No","1","")&IF(I89="N/A","2","")
W90: =IF(I91="No", "Comments","") & IF(I91="N/A", "Comments","")
A91: IS | B91: Information Security | E91: IS-22 | F91: IS-22.3 | G91: CR | H91: Do you publish a roles and responsibilities document specifying what you vs. NYP are responsible for during security incidents? | J91: COBIT 4.1 DS5.6 | K91: 45 CFR 164.308 (a)(1)(i) 45 CFR 164.308 (a)(6)(i) | L91: Clause 4.3.3 A.13.1.1 A.13.2.1 | M91: NIST SP800-53 R3 IR-1 NIST SP800-53 R3 IR-2 NIST SP800-53 R3 IR-3 NIST SP800-53 R3 IR-4 NIST SP800-53 R3 IR-5 NIST SP800-53 R3 IR-7 NIST SP800-53 R3 IR-8 | N91: NIST SP800-53 R3 IR-1_x000D_ NIST SP800-53 R3 IR-2_x000D_ NIST SP800-53 R3 IR-3_x000D_ NIST SP800-53 R3 IR-4_x000D_ NIST SP800-53 R3 IR-4 (1)_x000D_ NIST SP800-53 R3 IR-5_x000D_ NIST SP800-53 R3 IR-7_x000D_ NIST SP800-53 R3 IR-7 (1)_x000D_ NIST SP800-53 R3 IR-7 (2)_x000D_ NIST SP800-53 R3 IR-8_x000D_ | O91: PCI-DSS v2.0 12.9 PCI-DSS v2.0 12.9.1 PCI-DSS v2.0 12.9.2 PCI-DSS v2.0 12.9.3 PCI-DSS v2.0 12.9.4 PCI-DSS v2.0 12.9.5 PCI-DSS v2.0 12.9.6 | P91: AUP v5.0 J.1 SIG v6.0: J.1.1, J.1.2 | Q91: GAPP Ref 1.2.4 GAPP Ref 1.2.7 GAPP Ref 7.1.2 GAPP Ref 7.2.2 GAPP Ref 7.2.4 GAPP Ref 10.2.1 GAPP Ref 10.2.4 | R91: Y | S91: Y | T91: Y | U91: Y | V91: Y | AO91: =IF(I91="No","1","")&IF(I91="N/A","2","")
W92: =IF(I93="No", "Comments","") & IF(I93="N/A", "Comments","")
A93: IS | B93: Information Security | D93: Incident Reporting | E93: IS-23 | F93: IS-23.1 | G93: CR | H93: Does your security information and event management (SIEM) system merge data sources (app logs, firewall logs, IDS logs, physical access logs, etc.) for granular analysis and alerting? | J93: COBIT 4.1 DS5.6 | K93: 45 CFR 164.312 (a)(6)(ii) 16 CFR 318.3 (a) (New) 16 CFR 318.5 (a) (New) 45 CFR 160.410 (a)(1) (New) | L93: Clause 4.3.3 Clause 5.2.2 A.6.1.3 A.8.2.1 A.8.2.2 A.13.1.1 A.13.1.2 A.13.2.1 | M93: NIST SP800-53 R3 IR-2 NIST SP800-53 R3 IR-6 NIST SP800-53 R3 IR-7 NIST SP800-53 R3 SI-4 NIST SP800-53 R3 SI-5 | O93: PCI-DSS v2.0 12.5.2 PCI-DSS v2.0 12.5.3 | P93: AUP v5.0 J.1 AUP v5.0 E.1 SIG v6.0: J.1.1, E.4 | Q93: GAPP Ref 1.2.7 GAPP Ref 1.2.10 GAPP Ref 7.1.2 GAPP Ref 7.2.2 GAPP Ref 7.2.4 GAPP Ref 10.2.4 | R93: Y | S93: Y | T93: Y | U93: Y | V93: Y | AO93: =IF(I93="No","1","")&IF(I93="N/A","2","")
W94: =IF(I95="No", "Comments","") & IF(I95="N/A", "Comments","")
A95: IS | B95: Information Security | E95: IS-23 | F95: IS-23.2 | G95: CR | H95: Does your logging and monitoring framework allow isolation of an incident specific to NYP? | J95: COBIT 4.1 DS5.6 | K95: 45 CFR 164.312 (a)(6)(ii) 16 CFR 318.3 (a) (New) 16 CFR 318.5 (a) (New) 45 CFR 160.410 (a)(1) (New) | L95: Clause 4.3.3 Clause 5.2.2 A.6.1.3 A.8.2.1 A.8.2.2 A.13.1.1 A.13.1.2 A.13.2.1 | M95: NIST SP800-53 R3 IR-2 NIST SP800-53 R3 IR-6 NIST SP800-53 R3 IR-7 NIST SP800-53 R3 SI-4 NIST SP800-53 R3 SI-5 | O95: PCI-DSS v2.0 12.5.2 PCI-DSS v2.0 12.5.3 | P95: AUP v5.0 J.1 AUP v5.0 E.1 SIG v6.0: J.1.1, E.4 | Q95: GAPP Ref 1.2.7 GAPP Ref 1.2.10 GAPP Ref 7.1.2 GAPP Ref 7.2.2 GAPP Ref 7.2.4 GAPP Ref 10.2.4 | R95: Y | S95: Y | T95: Y | U95: Y | V95: Y | AO95: =IF(I95="No","1","")&IF(I95="N/A","2","")
W96: =IF(I97="No", "Comments","") & IF(I97="N/A", "Comments","")
A97: IS | B97: Information Security | D97: Incident Response Legal Preparation | E97: IS-24 | F97: IS-24.1 | G97: CR | H97: Does your incident response capability include the use of legally admissible forensic data collection and analysis techniques? | J97: COBIT 4.1 DS5.6 | K97: 45 CFR 164.308 (a)(6)(ii) | L97: Clause 4.3.3 Clause 5.2.2 A.8.2.2 A.8.2.3 A.13.2.3 A.15.1.3 | M97: NIST SP800-53 R3 AU-6 NIST SP800-53 R3 AU-7 NIST SP800-53 R3 AU-9 NIST SP800-53 R3 AU-11 NIST SP800-53 R3 IR-5 NIST SP800-53 R3 IR-7 NIST SP800-53 R3 IR-8 | P97: AUP v5.0 J.1 AUP v5.0 E.1 SIG v6.0: J.1.1, J.1.2, E.4 | Q97: GAPP Ref 1.2.7 | R97: Y | S97: Y | T97: Y | U97: Y | V97: Y | AO97: =IF(I97="No","1","")&IF(I97="N/A","2","")
W98: =IF(I99="No", "Comments","") & IF(I99="N/A", "Comments","")
A99: IS | B99: Information Security | E99: IS-24 | F99: IS-24.3 | G99: CR | H99: Are you capable of supporting litigation holds (freeze of data from a specific point in time) for NYP without freezing other client data? | J99: COBIT 4.1 DS5.6 | K99: 45 CFR 164.308 (a)(6)(ii) | L99: Clause 4.3.3 Clause 5.2.2 A.8.2.2 A.8.2.3 A.13.2.3 A.15.1.3 | M99: NIST SP800-53 R3 AU-6 NIST SP800-53 R3 AU-7 NIST SP800-53 R3 AU-9 NIST SP800-53 R3 AU-11 NIST SP800-53 R3 IR-5 NIST SP800-53 R3 IR-7 NIST SP800-53 R3 IR-8 | P99: AUP v5.0 J.1 AUP v5.0 E.1 SIG v6.0: J.1.1, J.1.2, E.4 | Q99: GAPP Ref 1.2.7 | R99: Y | S99: Y | T99: Y | U99: Y | V99: Y | AO99: =IF(I99="No","1","")&IF(I99="N/A","2","")
W100: =IF(I101="No", "Comments","") & IF(I101="N/A", "Comments","")
...

Sheet DESIGN
A1: IT Infrastructure Solution Design
A2: Description
A3: Should technical resources be required from NYP for the project, the vendor and NYP BRM representative will attend a Solution Design session alongside technical leads from the infrastructure team to discuss requirements and architect the solution according to NYP technical standards. The output of this session will include artifacts needed for both the implementation of the project and ongoing (day 2) support of the solution/service. The following artifacts will be created for net new systems, or if this is a modification to an existing system, these artifacts will be updated: • Bill of Materials required to build, test, and go live with the solution (BOM) • High Level Architecture Diagram (HLD) • Low Level technical blueprint of the solution (LLD) In addition to any technical documentation and vendor provided reference architectures, please come to Solution Design prepared to discuss the in-depth technical details and infrastructure requirements including, but not limited to the following topics:
A9: Application | B9: Topic | C9: NYP Standards
B10: Data Flows | C10: All data flows associated with the application must be documented in the LLD.
B12: Ports & Protocols | C12: All TCP and UDP ports in use must be documented and known for firewall traversal.
B14: Data Center Resiliency | C14: Built-in application; VMWare Site Recovery Manager; F5 GTM and LTM;
A16: Server | B16: Topic | C16: NYP Standards
B17: Vendor supplied images i.e. OVA, OVF | C17: Supported
B19: Resource requirements i.e. vCPUs, memory, storage. | C19: Customizable, but no resource reservations permitted
B21: Operating Systems supported | C21: RHEL 7.2, Windows Server 2016
B22: Remote Access | C22: NYP PRA Portal, NYP Client VPN, NYP VPN Tunnel
B23: Antivirus | C23: Cylance
B24: Approved Software | C24: BigFix, Splunk, Snow, VMWare Tools, SCCM, IE, .NET, Silverlight
B25: OS Firewall | C25: Deny all inbound ports by default
A26: Storage | B26: Topic | C26: NYP Standards
B27: NAS/SAN Requirements | C27: DellEMC Isilon, Pure FlashArray
B29: Initial capacity requirements and growth projections | C29: Customizable
B31: Data Lifecycle Policies – Retention, Archival, Attrition | C31: Customizable
B32: NAS authentication | C32: Mandatory Active Directory integration
B33: Bandwidth & Latency | C33: Bandwidth requirements and latency thresholds must be specified and documented
B35: Internet connectivity | C35: NYP Web Proxy must be utilized
B36: Site-to-Site VPN | C36: Supported via enterprise VPN infrastructure
B37: Client VPN | C37: NYP utilizes Cisco Anyconnect
B38: Load Balancing | C38: NYP provides global (GTM) and local (LTM) traffic management utilizing F5 technology
A39: Network - WAN/Data Center | B39: Topic | C39: NYP Standards
B40: Bandwidth & Latency | C40: Bandwidth requirements and latency thresholds must be specified and documented
B42: Internet connectivity | C42: NYP Web Proxy must be utilized
B43: Site-to-Site VPN | C43: Supported via enterprise VPN infrastructure
B44: Client VPN | C44: NYP utilizes Cisco Anyconnect
B45: Load Balancing | C45: NYP provides global (GTM) and local (LTM) traffic management utilizing F5 technology
A46: Network - LAN | B46: Topic | C46: NYP Standards
B47: Power-over-Ethernet | C47: 802.3af and 802.3at supported
B48: Multicast | C48: Supported – PIM sparse-mode
B49: Bandwidth | C49: Bandwidth requirements must be specified and documented
A50: Network - WiFi | B50: Topic | C50: NYP Standards
B51: Frequency | C51: 5-Ghz support required for clinical, voice, and video use cases
B53: Security | C53: WPA2 Enterprise
B54: Authentication | C54: 802.1x EAP-TLS, EAP-PEAP
B55: SSID | C55: All devices must use a standard NYP SSID; Rogue and ad-hoc wireless networks are not permitted
A57: Database | B57: Topic | C57: NYP Standards
B58: Platforms | C58: SQL Server 2016, Oracle
B60: Data Lifecycle Policies – Retention, Archival, Attrition | C60: Customizable
B61: Management | C61: Backup policy must be specified and documented; Re-certification requirements must be known
B63: Support | C63: Support model must be documented
A64: Desktop and Citrix | B64: Topic | C64: NYP Standards
B65: Physical Endpoint Requirements
B67: Initial user volume and anticipated growth
B68: Browser and plug-in requirements
B69: Citrix XenApp | C69: Version 7.15
B70: Application Authentication | C70: Ping and Active Directory
B71: External user requirements | C71: Storefront and Anyconnect VPN
B72: Licensing
A73: Operational Support | B73: Topic | C73: NYP Standards
B74: Disaster Recovery | C74: Documented DR Plan
B75: Monitoring | C75: SNMP (NMS), Splunk, Extrahop
B76: Key Performance Metrics | C76: Identify during Solution Design and Document
B77: Security Patching Runbook | C77: Documented procedures;
C78: BigFix Automation Plan
B79: Support Runbook | C79: Troubleshooting procedures, Escalation procedures, Support groups, HLD, LLD, and assets (CI’s) documented for production support.

Sheet Values-DoNotDelete
A1: General-C26 | B1: Yes/No | C1: Attachments | D1: DestructionOfData | E1: CloudProvider | F1: Virtual Networking | G1: VendorServerAuth
A2: Vendor | B2: Yes | C2: Select here to add attachment | D2: Vendor will destroy data in accordance with NIST standards | E2: AWS | F2: VNET | G2: Password
A3: NYP | B3: No | C3: N/A | D3: Vendor will return data to NYP | E3: Azure | F3: VPC | G3: Certificate
B4: N/A | C4: Please attach system architecture diagram | D4: N/A | E4: GCP | F4: Other | G4: Other
E5: Other | F5: N/A | G5: N/A
E6: N/A
A8: NoOfRecords | B8: DR Environment | C8: Security Groups+NACLs | D8: Regions | E8: AV
A9: 1 to 10 | B9: VPN | C9: NSGs | D9: US East | E9: NYP Standard - Cylance malware protection
A10: 11 to 1,000 | B10: Express Route | C10: NACLs | D10: US East 2 | E10: Preinstalled AntiVirus / AntiMalware
A11: more than 1,000 | B11: Direct Connect | C11: Both | D11: US West | E11: Other (embedded Security - whitelisting)
A12: N/A | B12: Internet | C12: Neither | D12: US West 2 | E12: N/A
B13: Other | C13: N/A | D13: Other
B14: N/A | D14: N/A
A16: PatchMgmt | C16: ScanningModes | D16: EncryptionAtRest | E16: 3rdParty SW | F16: RemoteAccess
A17: Manual updates by Vendor | C17: Continuously and automatically (on access) | D17: NYP Standard - Bit locker through NYP AD Domain rules | E17: Not installed | F17: Remote troubleshooting via Remote Desktop
A18: Automated updates by Vendor | C18: On-demand on-line | D18: Other encryption types. (please specify in Comments) | E18: Usage is restricted to service | F18: Remote Monitoring
A19: Device supports NYP installed/maintained SCCM Agent for patch deployment | C19: Scheduled off-line | D19: Industry standard algorithm (e.g. AES 256). | E19: Hardened installation | F19: Remote Software Distribution
A20: Manual updates by NYP | C20: At boot or shutdown time | D20: N/A | E20: Default installation | F20: Anti-Virus Service Management and Updates
A21: Automated Microsoft Security Patches by NYP | C21: On-demand off-line | E21: Not Supported | F21: Not Supported
A22: Part of Corrective Maintenance | C22: Customizable / Configurable | E22: Software-only product | F22: N/A
A23: Not Supported | C23: Not supported | E23: N/A
A24: N/A | C24: N/A
A25: Supports Multiple
