Workbook
Name CORL: [1]Sheet1!$A$1:$A$2
Name Risk: [2]Sheet2!$A$3:$A$7

Sheet Cover Page
A1: Vendor Security Assessment Toolkit by CORL Technologies This document is PROPRIETARY and CONFIDENTIAL Information. It may not be used, disclosed or reproduced, in whole or in part, without the express written permission of CORL Technologies, LLC
A12: Version 3.00 (On Prem+PSQ)

Sheet Instructions
A1: "IRQ" - Inherent Risk Questionnaire - Business Owner to Complete
B2: St. Luke's (SLUHN) Business Owner completes the Inherent Risk Questionnaire ("IRQ") to facilitate better understanding of the scope of business between the Vendor and the organization for the vendor security risk management project.
A4: "VPQ" - Vendor Profile Questionnaire - Vendor to Complete
B5: Please complete this questionnaire as it relates to the business relationship between your organization and St. Luke's (SLUHN). In the "Disclosure Permitted?" column, please indicate if CORL Technologies may disclose the responses provided herein to other CORL Technologies clients who also utilize your organization as a vendor. Allowing such disclosure may expedite future assessments.
A7: Scope - Vendor to Complete
B8: Please identify all environments that will handle, process, transmit, or store St. Luke's (SLUHN) data. Please provided a response to all questions for each identified environment.
A10: "VSQ" - Vendor Security Questionnaire - Excel worksheets 1-17 herein - Vendor to Complete
B11: St. Luke's (SLUHN) is obligated by regulations and internal risk management policies to gain reasonable assurance that its vendors are protecting St. Luke's (SLUHN) data. To meet this obligation, St. Luke's (SLUHN) is requiring vendors to complete this Vendor Security Questionnaire (VSQ) within 15 business days of receiving it. All "N/A" and "Partial" responses MUST be accompanied by an explanation in the comments column. Any questions should be directed to CORL Client Engagement clientengagement@corltech.com.
A13: "Required Evidence" - Evidence and Assurances specific to CLIENT - Vendor to Provide
B14: Upon completion of this questionnaire, CORL and St. Luke's (SLUHN) will obtain evidence and assurances relating to the key controls as defined by the St. Luke's (SLUHN) team. Please indicate within the "Required Evidence" sheet whether you have provided the documentation requested by CORL and St. Luke's (SLUHN). Instructions surrounding Evidence and Assurances: The Vendor Profile Questions (VPQ) & Scope sections include questions that relate to information about your organization and the products and services provided to St. Luke's (SLUHN). The Vendor Security Questionnaire (worksheets 1-17) section relates to questions about overall security controls at the vendor level and product level. All responses require references to documents that provide evidence of the control. If your organization has received a current security certification, please provide documentation in lieu of evidence. Relevant security certifications include, SOC 2 Type 2 (must include Security TSP), HITRUST and/or ISO 27001. Please provide certification and/or evidence documents along with this completed questionnaire to CORL Technologies within 15 business days.

Sheet Data Validation Key
A1: Response Questions | B1: Data Classifications | C1: Types of Data: | D1: Type of Access | E1: Method of Access | F1: Volume of Records | G1: Financial Value | H1: Breah Business Impact | I1: Geographic Scope | J1: Size of Organization (# of Employees) | K1: How data is stored, hosted | L1: App / Product? | M1: Vendor Age / Business Relationship Length
A2: Yes | B2: Company Data | C2: PHI | D2: Intentionally Shared | E2: Electronic | F2: Most of our patients | G2: High | H2: High | I2: International | J2: > 100,000 | K2: In the Cloud | L2: Yes | M2: < 5 Years
A3: No | B3: Restricted Data | C3: PII | D3: Incidental Access | E3: Physical | F3: Most our employees | G3: Medium High | H3: Medium High | I3: National | J3: > 10,001 | K3: On our Network | L3: No | M3: 5 - 10 Years
A4: Partial | B4: Sensitive Data | C4: PCI | D4: No Access | E4: Electronic and Physical | F4: Data related to a specific business unit or division | G4: Medium | H4: Medium | I4: Single-State | J4: > 1001 | K4: At the Vendor's Location | M4: 11 - 20 Years
A5: N/A | B5: Internal Data | C5: Intellectual property | F5: Data related to a specific service line or facility | G5: Medium Low | H5: Medium Low | J5: > 501 | M5: > 20 Years
B6: Public Data | C6: PHI, PII | F6: Very specific and limited focus | G6: Low | H6: Low | J6: > 51
C7: PHI, PCI | G7: None | H7: None | J7: > 1
C8: PHI, Intellectual property
C9: PCI, PII
C10: PCI, Intellectual property
C11: PII, Intellectual property
C12: All Data types
A20: Key | C20: Overrides
A21: Tier 1 | C21: No Override
A22: Tier 2 | C22: Adequate
A23: Tier 3 | C23: Inadequate
A24: Conditional to other Questions | C24: N/A
A25: Response acceptance dependent on the business relationship btwn client and vendor
A26: Questions dependent on comments and QA by CE

Sheet IRQ
A1: Inherent Risk Questionnaire ("IRQ")
A2: Official Name of Vendor: | D2: Vendor POC Name:
A3: Vendor-specific business unit / division, if applicable: | D3: Vendor POC Title:
A4: Vendor Website Domain(s): | D4: Vendor POC Email:
A5: Date IRQ Completed: | D5: Vendor POC Phone #:
A6: Control Question # | B6: Control Name | C6: Control Questions | D6: Response | E6: Notes
A7: Inherent Risk Questions:
A8: 1 | B8: Products and Applications | C8: Does your organization use a vendor specific service/product(s)? (if "Yes" please list the names of the services/products in "Notes")
A9: 2 | B9: Accessible Data | C9: Type of data vendor will have access to:
A10: 3 | B10: Data Storage | C10: Where will the data of your organization be stored, hosted?
A11: 4 | B11: Report Support | C11: Does vendor provide remote support?
A12: 5 | B12: Records | C12: Volume of your organization's records accessible by vendor:
A13: 6 | B13: Vendor Business Operations | C13: Geographic scope of the vendor (if vendor has international operations, please list country name(s) in "Notes"):
A14: 7 | B14: Vendor Age | C14: How long has the vendor been in business in general?
A15: 8 | B15: Business Relationship Length | C15: How long has the vendor been in business with your organization?
A16: 9 | B16: Annual Revenue | C16: What is the vendor's annual revenue?
A17: 10 | B17: Vendor Size | C17: Size of the vendor (# of employees):
A18: 11 | B18: Business Associate Agreement (BAA) | C18: Is there an executed Business Associate Agreement between your organization and the vendor?
A19: 12 | B19: Information Security Agreement (ISA) | C19: Is there an executed Information Security Agreement between your organization and the vendor?
A20: 13 | B20: Security Assessment Activities | C20: Has your organization completed security assessment activities on the vendor in the past? (if "Yes" please describe the assessment scope and approximate timeframe in "Notes"):

Sheet IVPQ
A1: Initial Vendor Profile Questionnaire - for CLIENT NAME
A2: Vendor name: | D2: Name:
A3: Service(s) / Product(s) provided: | D3: Title:
A4: Vendor Website Domain(s): | D4: Email:
A5: Date Completed: | D5: Phone:
A6: Control Question # | B6: Control Name | C6: Control Questions | D6: Response: | E6: Comments/ Notes: | F6: Evidence Provided | G6: NIST SP800-53 R4: Control # | H6: HIPAA CFR Control Reference(s):
A7: Vendor Discovery Questions:
A8: 1.1 | B8: Accessible Data | C8: Will you have access to the following types of data: | G8: N/A | H8: N/A
A9: 1.1-a | B9: Accessible Data | C9: PHI (Protected Health Information) | G9: N/A | H9: N/A
A10: 1.1-b | B10: Accessible Data | C10: Intellectual Property | G10: N/A | H10: N/A
A11: 1.1-c | B11: Accessible Data | C11: Financial Property | G11: N/A | H11: N/A
A12: 1.1-d | B12: Accessible Data | C12: PII (Personally Identifiable Information) | G12: N/A | H12: N/A
A13: 1.1-e | B13: Accessible Data | C13: PCI (Payment Card Industry) | G13: N/A | H13: N/A
A14: 1.1-f | B14: Accessible Data | C14: Employee Information | G14: N/A | H14: N/A
A15: 1.2 | B15: Security Leadership | C15: Do you have a designated responsible leader for information security? If so, please explain their title and role in the comments section. | G15: N/A | H15: N/A
A16: 1.3 | B16: Security Assurances | C16: Has your company attained any of the following security certifications or external, independent validations of the following:? | G16: N/A | H16: N/A
A17: 1.3-a | B17: Security Assurances | C17: SOC (indicate SOC 1, 2 or 3 and type 1 or 2) | F17: Example evidence: certification document | G17: N/A | H17: N/A
A18: 1.3-b | B18: Security Assurances | C18: HITRUST | F18: Example evidence: certification document | G18: N/A | H18: N/A
A19: 1.3-c | B19: Security Assurances | C19: PCI Compliance | F19: Example evidence: certification document | G19: N/A | H19: N/A
A20: 1.3-d | B20: Security Assurances | C20: ISO 27001 | F20: Example evidence: certification document | G20: N/A | H20: N/A
A21: 1.3-e | B21: Security Assurances | C21: FedRAMP | F21: Example evidence: certification document | G21: N/A | H21: N/A
A22: 1.3-f | B22: Security Assurances | C22: HIPAA (please provide type of assessment performed and certifying organization in the comments section) | F22: Example evidence: certification document | G22: N/A | H22: N/A
A23: 1.3-g | B23: Security Assurances | C23: NIST (please provide type of assessment performed and certifying organization in the comments section) | F23: Example evidence: certification document | G23: N/A | H23: N/A
A24: 1.3-h | B24: Security Assurances | C24: Other? (please specify in the comments section) | F24: Example evidence: certification document | G24: N/A | H24: N/A
A25: 1.4 | B25: Cyber Liability Insurance | C25: Do you maintain cyber liability insurance in addition to general liability insurance? If Yes, please explain how much in the comments section. | F25: Example evidence: insurance policy | G25: N/A | H25: N/A
A26: 1.5 | B26: Contractors/Subcontractors | C26: Do you use any employees, contractors or subcontractors outside of the United States? | E26: Please list locations and approximate # of employees at each location | G26: N/A | H26: N/A
A27: 1.6 | B27: Contractors/Subcontractors | C27: Do any of your subcontractors (foreign or domestic) have access to sensitive and/or confidential data? If yes, please name the companies and services they provide to you in the comments section. | E27: Please provide a list of sub-contractors | G27: N/A | H27: N/A
A28: 1.7 | B28: Employee Screenings | C28: Do you conduct background checks for all employees, contractors and subcontractors? If not, for which areas/positions do you require a background check. Please explain in the comments section. | G28: PS-3 | H28: 164.308(a)(3)(ii)(B)
A29: 1.8 | B29: Data Storage | C29: Is this a remote hosted or cloud system? If yes, please answer the following questions. | G29: N/A | H29: N/A
A30: 1.8-a | B30: Data Storage | C30: Do you have any data centers outside of the United States? | G30: N/A | H30: N/A
A31: 1.8-b | B31: Data Storage | C31: Can data be restricted to be stored only within the United States? | G31: N/A | H31: N/A
A32: 1.9 | B32: Data Storage | C32: Will data be stored at an encrypted data center? | E32: Please list names of recognized data centers | G32: SC-13 | H32: 164.312(a)(2)(iv) 164.312(e)(2)(ii)
A33: 1.1 | B33: Data Center Security Assurances | C33: What certifications does your data center have or external, independent validations of the following:? | G33: N/A | H33: N/A
A34: 1.10-a | B34: Data Center Security Assurances | C34: SOC (indicate SOC 1, 2, or 3 and type 1 or 2) | G34: N/A | H34: N/A
A35: 1.10-b | B35: Data Center Security Assurances | C35: PCI Compliance | G35: N/A | H35: N/A
A36: 1.10-c | B36: Data Center Security Assurances | C36: HITRUST | G36: N/A | H36: N/A
A37: 1.10-d | B37: Data Center Security Assurances | C37: ISO 27001 | G37: N/A | H37: N/A
A38: 1.10-e | B38: Data Center Security Assurances | C38: FedRAMP | G38: N/A | H38: N/A
A39: 1.10-f | B39: Data Center Security Assurances | C39: HIPAA (please provide type of assessment performed and certifying organization in the comments section) | G39: N/A | H39: N/A
A40: 1.10-g | B40: Data Center Security Assurances | C40: NIST (please provide type of assessment performed and certifying organization in the comments section) | G40: N/A | H40: N/A
A41: 1.10-h | B41: Data Center Security Assurances | C41: Other (please specify in the comments section) | G41: N/A | H41: N/A
A42: 1.11 | B42: Data Breach History | C42: Has your organization ever experienced a data breach? If so, please explain in the comments box. | G42: N/A | H42: N/A

Sheet Vendor Profile Questionnaire
A1: Instructions: Please complete this questionnaire as it relates to the business relationship between your organization and St. Luke's (SLUHN). In the "Disclosure Permitted?" column, please indicate if CORL Technologies may disclose the responses provided herein to other CORL Technologies clients who also utilize PeriGen. Allowing such disclosure may expedite future assessments.
A2: Initial Vendor Profile Questionnaire - on behalf of St. Luke's (SLUHN)
A3: Vendor name: | B3: PeriGen | D3: Name: | E3: Bruno Bendavid
A4: Service(s) / Product(s) provided: | B4: PeriCALM Tracings | D4: Title: | E4: SVP Product Management
A5: Vendor Website Domain(s): | B5: www.perigen.com | D5: Email: | E5: bruno.bendavid@perigen.com
A6: Date Completed: | B6: 43817 | D6: Phone: | E6: 514-978-0611
A7: Vendor Discovery Questions:
A8: Questions | B8: Response | C8: Disclosure Permitted? | D8: Comments
A10: Does PeriGen have a designated leader responsible for information security? | B10: Yes | C10: Yes
A11: Name of Information Security leader? | B11: Bruno Bendavid | C11: Yes
A12: Title | B12: SVP Product Management | C12: Yes
A13: Role | B13: Product Management | C13: Yes
A14: Does PeriGen employ an information security team? | B14: No | C14: Yes
A15: Number of full-time information security personnel? | B15: No. Role part of product development | C15: Yes
A16: Does PeriGen employ an incident response officer? | C16: Yes
A17: Name of incident response officer? | B17: Bruno Bendavid | C17: Yes
A18: Title | B18: SVP Product Management | C18: Yes
A19: Email | B19: bruno.bendavid@perigen.coom | C19: Yes
A20: Phone | B20: 514-978-0611 | C20: Yes
A21: Does PeriGen outsource information security functions to a third party? If yes, please provide the name and scope of services provided in the comments section. | B21: Yes | C21: Yes | D21: IT infrastructure management
A22: Does VENDOR maintain cyber liability insurance in addition to general liability insurance? If Yes, please explain how much in the comments section. | B22: Yes | C22: Yes | D22: Liability insurance is set to $5 million (both general and cyber)
A23: Does PeriGen have any employees or physical office locations outside of the United States? | B23: Yes | C23: Yes
A24: Is any St. Luke's (SLUHN) data accessed, transmitted, or stored outside of the United States? | B24: No | C24: Yes | D24: PeriGen has technical resources residing outside the United States; Montreal, Canada and Tel Aviv, Israel. The primary support center is in Cary, NC (PeriGen HQ). These resources may from time to time analyze and troubleshoot the solution which may require access to ePHI data via approved connections. ePHI is never copied or stored outside the US.
A25: What year was PeriGen founded? | B25: 36164 | C25: Yes
A26: Approximately how many people does PeriGen employ? | B26: <100 | C26: Yes
A27: Has PeriGen ever experienced a data breach? If so, please explain in the comments section. | B27: No | C27: Yes
A28: Is there a current BAA in place? | B28: Yes | C28: Yes
A29: Does PeriGen utilize any subcontractors with access to St. Luke's (SLUHN) data? If yes, please provide the name of the subcontractor(s) in the comments section. | B29: No | C29: Yes
A30: Please describe how your organization obtains data from St. Luke's (SLUHN). Include file type(s) and the medium(s) utilized to transmit the data (e.g., SFTP, Encrypted email). | B30: No data collected outside the servers hosted by the SLUHN | C30: N/A

Sheet Scope
A1: Vendor Scope Questions
A2: Instructions: Please identify all environments that will handle, process, transmit, or store St. Luke's (SLUHN) data. Please provided a response to all questions for each identified environment. | B2: Environment 1 | D2: Environment 2 | F2: Environment 3
B3: Response | C3: Comments | D3: Response | E3: Comments | F3: Response | G3: Comments
A4: Please identity the environment (e.g., back office, systems involved in support /maintenance services, applications/softwares) in the "response" column and provide a brief description in the comments section: | B4: PeriCALM Tracings Fetal monitoring application | C4: Dedicated and fully hospital hosted fetal monitoring, documentation, alerts, archiving and decision support
A5: Is the identified environment either of the following:
A6: Service | B6: No
A7: Product | B7: Yes
A8: What is the volume of St. Luke's (SLUHN) records that the identified environment will transmit, process, or store? | B8: Data is only stored on hospital hosted servers. An estimate of volume of data stored on hospital servers including long term archive files is ~10GB (steady state) + 5GB per year as continuous archive files per pregnancy
A9: Please indicate if the identified environment will: | B9: If "yes", please provide details in the comments section.
A10: have access into the St. Luke's (SLUHN) network for remote Support | B10: Yes | C10: All access to the PeriGen servers is done via SecureLink approved infrastructure for 24/7/365 support
A11: have access into the St. Luke's (SLUHN) network to provide onsite support | B11: Yes | C11: PeriGen support staff have user access credentials to PeriGen server(s) only. This can be used for onsite support/operations if required by the customer
A12: Have access to infrastructure that stores or transmits St. Luke's (SLUHN) data: | B12: No | C12: No if the question pertains to physical access
A13: Have access to a database or application that stores or transmits St. Luke's (SLUHN) data: | B13: Yes | C13: Only to the PeriGen application DB and ADT/EMR HL7 data interfaces
A14: Receive transmitted data from St. Luke's (SLUHN) | B14: Yes | C14: Only ADT inbound
A15: Not access St. Luke's (SLUHN)'s information | B15: No
A16: What types of St. Luke's (SLUHN) information will the identified environment have access to: | B16: If "yes", please provide details in the comments section.
A17: PHI (Protected Health Information) | B17: Yes | C17: Only data supplied via the ADT inbound interface
A18: PII (Personally Identifiable Information) | B18: No
A19: PCI (Payment Card Industry) | B19: No
A20: Employee Information | B20: No
A21: St. Luke's (SLUHN) Internal/Proprietary Information | B21: No
A22: Please indicate if the identified environment will utilize the following device(s) to access and/or transmit St. Luke's (SLUHN) data: | B22: If "yes", please provide details in the comments section.
A23: St. Luke's (SLUHN) Workstation | B23: Yes | C23: The PeriCALM application is installed on workstation at the bedside and nursing stations. Data is communicated between workstations and server. Not data is cached or saved on the workstation.
A24: PeriGen Workstation | B24: No | C24: unclear. PeriGen does not provide any workstation hardware. Only customer supplied stations are in scope.
A25: St. Luke's (SLUHN) Mobile Device | B25: No
A26: PeriGen Mobile Device | B26: No
A27: Medical Device | B27: Yes | C27: The system interfaces to fetal monitor to collect the fetal tracing, trasmit it to the main server which publishes it to all open client application instances on the network
A28: Other Method? Please explain in the comments section | B28: No
A29: Please indicate all locations where the data will be stored for the identified environment: | B29: If "yes", please provide details in the comments section.
A30: St. Luke's (SLUHN) Data Center | B30: Yes | C30: All data is stored on the main DB/App server and possibly on the long term data archival system used by the customer at the data center. No data is stored on client workstations
A31: PeriGen Data Center | B31: No
A32: 3rd Party Data Center | B32: No
A33: St. Luke's (SLUHN) Workstation | B33: No
A34: PeriGen Workstation | B34: No
A35: St. Luke's (SLUHN) Mobile Device | B35: No
A36: PeriGen Mobiel Device | B36: No
A37: Medical Device | B37: No
A38: Other? Please explain in the comments section | B38: No
A39: Does the identified environment maintain any of the following security assurances:
A40: SSAE 16 / SOC 1 Type 1 | B40: No
A41: SSAE 16 / SOC 1 Type 2 | B41: No
A42: SOC 2 Type 1 | B42: No
A43: SOC 2 Type 2 | B43: No
A44: SOC 3 | B44: No
A45: HITRUST | B45: No
A46: PCI Compliance | B46: No
A47: ISO 27001:2013 | B47: No
A48: FedRAMP | B48: No
A49: HIPAA (please provide type of assessment performed and certifying organization in the comments section) | B49: Yes | C49: HIPAA compliance functions are coded within the system design. To date there has not been an external assessment. PeriGen is presently engaged to perfrom such an audit
A50: NIST (please provide type of assessment performed and certifying organization in the comments section) | B50: No | C50: Although many NIST guidelines are built into system design there was no certification perfromed
A51: Other? (please specify in the comments section) | B51: No
A52: Is any of the St. Luke's (SLUHN) data not covered by the scope of the above identified certifications? | B52: No
A53: Is all St. Luke's (SLUHN) data encrypted at rest within the identified environment? If so, please provide the level of encryption utilized in the comments section | B53: No | C53: Archives file are archived as encrypted and compressed XML (AES-256). Real-time database (Objectivity/DB) which reside on the main server hosted at University of Utah is not encrypted at rest.
A54: Does PeriGen adhere to information system security engineering principles in the specification, design, development, implementation, and modification of the identified environment? | B54: Yes
A55: For the identified environment, may CORL Technologies disclose the responses provided herein to other CORL Technologies clients who also utilize PeriGen? Allowing such disclosure may expedite future assessments. | B55: Yes

Sheet Network_Architecture_Diagrams
A1: Objective: | B1: Summary/Explanation (if diagrams are not available): | C1: Evidence/Assurance
A2: Please provide any and all network architecture diagram(s) within this worksheet: | C2: Please attach network architecture diagram(s) or provide screenshots below:

Sheet Connectivity Mapping
A1: Objective: | B1: Summary/Explanation: | C1: Evidence/Assurance
A2: Please provide a summary of how you will be connecting to the St.Luke's (SLUHN) Network (if applicable) | B2: Connectivity is perfromed by SecureLink which is already approved and operational. | C2: If necessary please provide supporting documentation

Sheet Required Evidence
A1: Key Control Question Reference # | B1: Key Control: | C1: Control Area # | D1: Evidence Requested: | E1: Provided to CORL? | F1: Vendor Comments
A2: CM-2.1 | B2: Baseline Configuration | C2: CM-2 | D2: Provide the most recent Baseline Configuration document for the information system (e.g., hardening procedures for Window OS, baseline security settings for sever AND application builds.) | E2: Yes | F2: Guidelines and environments provided by the customer based on PeriGen provided specifications. See the attached System Specification.
A3: CM-3.1 - CM-3.6 | B3: Configuration Change Control | C3: CM-3 | D3: Configuration Change Control procedures | E3: Yes | F3: See attached SDLC master policy/procedure | G3: There are no specific procedures for "configuration change controls". Product development life cycle and change control in general are embedded within QMS SOPs and Procedures propriatary to PeriGen
A4: CM-5.1 | B4: Access Restrictions for Change | C4: CM-5 | D4: Configuration Change Control procedures | E4: Yes | F4: See attached SDLC master policy/procedure
A5: CM-6.1 - CM-6.3 | B5: Configuration Settings | C5: CM-6 | D5: Provide report monitoring records related to most recent changes to the Configuration settings information system | E5: No | F5: Tracking is done within our development systems (VSTS). It isnt possible/practical to provide such a report.
A6: CM-7.1 | B6: Least Functionality | C6: CM-7 | D6: (See CM 2.1 - Most recent Baseline Configuration) | E6: Yes | F6: See the attached system specifications
A7: CM-8.1 - CM-8.2 | B7: Information System Component Inventory | C7: CM-8 | D7: Provide documentation that demonstrates information system Component Inventory is maintained and kept up to date. | E7: Yes | F7: See 2 examples of system specifictaion for the version 3.18.04 and 3.18.05
A8: CM-9.1 - CM-9.4 | B8: Configuration Management Plan | C8: CM-9 | D8: Provide Software Development/Deployment Life Cycle (SDLC) documentation which includes secure coding procedures, where applicable. | E8: Yes | F8: See attached SDLC master policy/procedure | G8: PeriGen SDLC procedures are extensive and propriatary in compliance with FDA and MDSAP guidelines for class II Medical Devices. Secure coding practices are followed but not formally captured in a procedure. This is planned for 2020
A9: CM-10.1 | B9: Software Usage Restrictions | C9: CM-10 | D9: Provide Acceptable Use policy. Provide samples of software licensing documentation. | E9: Yes | F9: This is the clause in standard PeriGen contracts regarding Acceptable Use: "PeriGen grants to Customer a non-exclusive, non-transferable license (“License”) to use the Software solely at the applicable Facility(ies) listed in the Order Form, solely in object code form and solely for Customer’s internal use. Customer shall ensure that all Staff responsible for using the Software are properly trained. Customer will be allowed to make and retain a copy of the Software for back up purposes only, in accordance with Customer’s standard policies. Each copy of the Software is subject to all of the terms and conditions of this Agreement and must contain the same titles, trademarks, and copyright notices as the original. Customer and its Staff shall not (i) copy, modify or change the Software in any manner except as may be expressly permitted herein; (ii) make any modifications to the operation or installation of the Software without the written consent of PeriGen; (iii) sell, rent, lease, lend, reproduce, license, sublicense, distribute or otherwise transfer the Software or decompile, disassemble or reverse engineer the Software or any PeriGen Intellectual Property, in whole or in part; (iv) write or develop any derivative technology including, without limitation, any other software program based upon the Software or any PeriGen Intellectual Property; (v) use the Software to provide any facility management, service bureau or similar services to third parties; (vi) modify or attempt to modify the Software’s configuration without the prior written consent of PeriGen, to be given in PeriGen’s sole discretion, and any intervention or actions required to be taken by PeriGen with respect to such unauthorized modifications shall be at Customer’s expense; or (vii) remove any copyright, patent, trademark or other proprietary or restrictive notice or legend contained or included in any PeriGen Intellectual Property or any copies thereof. Customer shall only use PeriGen-certified FDA compliant fetal monitor cables, if applicable. "
A10: CM-11.1 | B10: User-Installed Software | C10: CM-11 | D10: Provide documentation that demonstrates unapproved software is prohibited from use on the information system. Provide evidence of any mechanisms that prevent unapproved software from being used. | E10: N/A | F10: Controlled by customer IT policies. Only PeriGen employees can install the customer approved software version. Signed document are maintained for each installation. See an attached example. | G10: Maybe clause in contract and allowed change control (like MS patches)
A11: IA-5.2 - IA-5.8 | B11: Authenticator Management | C11: IA-5 | D11: Provide Password policy and procedures, including length and complexity requirements as well as process initial password distribution and changing of factory defaults. | E11: Yes | F11: See the attached PeriGen Privacy & Security Policy and Procedures document
A12: MA-4.1 - MA-4.5 | B12: Non-local Maintenance | C12: MA-4 | D12: Provide policy and procedures surrounding secure remote support of the information system. | E12: Yes | F12: See the attached PeriGen Privacy & Security Policy and Procedures document
A13: RA-5.1 | B13: Vulnerability Scanning | C13: RA-5 | D13: Provide Vulnerability Management procedures and copy of the most recent vulnerability scans of all systems which process, transmit, or store client data | E13: Yes | F13: See the attached PeriGen Privacy & Security Policy and Procedures document
A14: SC-15.1 - SC-15.3 | B14: Collaborative Computing Devices | C14: SC-15 | D14: Provide hardware configuration specifications that demonstrate remote activation of collaborative computing devices are prohibited | E14: N/A | F14: There are no collaborative devices being used at PeriGen as specified in 15.1
A15: SC-8.1, SC-8.2, SC-28.1 | B15: Encryption | C15: SC-8, SC-28 | D15: Provide Encryption policy and procedures for information in transit and information at rest. | E15: Yes | F15: See the attached PeriGen Privacy & Security Policy and Procedures document
A16: SC-18.1 | B16: Mobile Code | C16: SC-18 | D16: Provide Communications Protection policy and Mobile Code Implementation policy | E16: N/A | F16: No mobile code applicable for PeriCALM Tracings
A17: SI-2.1 - SI-2.3 | B17: Flaw Remediation | C17: SI-2 | D17: Provide documentation that all identified vulnerabilities are remediated in a timely manner. | E17: Partial | F17: Embedded in SDLC process. Each flaw is assessed individulay and scheduled for release according to severity/priority. There is no direct document to demonstrate that other than what is covered in SDLC policy.
A18: SI-3.1 - SI-3.4 | B18: Malicious Code Protection | C18: SI-3 | D18: Provide evidence that malware protection solutions are implemented on servers, workstations, and all other end points that process, transmit, or store client data. | E18: Yes | F18: See attached sample report from our automated system
A19: SI-4.1 | B19: Information Systems Monitoring | C19: SI-4 | D19: Provide evidence that intrusion detection and intrusion prevention solutions are implemented and monitored. | E19: Yes | F19: See attached
A20: SI-7.1 | B20: Software, Firmware, and Information Integrity | C20: SI-7 | D20: Provide evidence that information integrity tools are used. (e.g., tripwire) | E20: No
A21: SI-8.1 | B21: Spam Protection | C21: SI-8 | D21: Provide documentation that spam protection mechanisms are employed at information system entry/exit points and are updated when new releases of such mechanisms are available. | E21: Yes | F21: Corporate policy as of Office 365 E5 service. See the attached screenshot for corporate SPAM settings
A22: SA-4.1 | B22: Acquisition Process | C22: SA-4 | D22: Please provide Vendor Management Policy/ Procedures | E22: No
A23: SA-12 | B23: Supply Chain Protection | C23: SA-12 | D23: Please provide Vendor Management Policy/ Procedures | E23: No
A24: IR-8 | B24: Incident Response Plan | C24: IR-8 | D24: Please provide comprehensive Incident Response Plan | E24: Yes | F24: See the attached PeriGen Privacy & Security Policy and Procedures document

Sheet Product Security Questionnaire
A1: Initial Product Profile
A2: Vendor: PeriGen | B2: Completed by: | C2: Name: Bruno Bendavid | D2: Title: SVP Product Management
A3: Product name: PeriCALM Tracings | C3: Phone: 514-978-0611 | D3: Email: bruno.bendavid@perigen.com
A4: Date Completed: Dec 18, 2019
A5: Questions | B5: Yes/No | C5: Comments
A6: (1) Will PeriCALM process transmit or store the following types of St. Luke's (SLUHN)'s data:
A7: • Protected Health Information (PHI) | B7: Yes
A8: • Personally Identifiable Information (PII) | B8: Yes
A9: • Payment Card Industry (PCI) | B9: No
A10: • Employee Information | B10: No
A11: • Other? Please explain in the comments section
A12: (2) Please select the implementation method for the product that St. Luke's (SLUHN) is utilizing/will utilize:
A13: • Software-as-a-Service | B13: No
A14: • Locally installed | B14: Yes
A15: • Hybrid (please explain in the comments section)
A16: • Other (please explain in the comments section)
A17: (3) Please describe how the PeriCALM is integrated with the client's infrastructure. | B17: Yes | C17: PeriCALM Tracing server is installed locally at the customers data center. Interfaces include ADT, inbound/outbound HL7 & Single-Sign-On functions with the EMR and diect connectivity to fetal monitors via RS232.
A18: (4) Do you maintain any documentation which include the details of PeriCALM's security configuration specifications? If so, please attach in the comments section. | B18: No | C18: We only maintain configuration parameterrs that were chosen by each customer. Typicaly, all authentication is done based on AD users and groups where group management is done within PeriCALM for authorization. This is controlled by the customer.
A19: (5) Please provide a detailed overview of how PeriCALM will access, transmit, or store St. Luke's (SLUHN) data? | B19: Yes | C19: Assuming that "PeriGen data" means data generated by the customer on the PeriGen server/system. All data obtained at the site (ADT, HL7 interface, fetal monitoring and manual documentation by clinical staff) is stored on the server hosted by the customer. There are no interfaces or transmission of data outside the customer secured network.
A20: (6) Is your organization is providing remote support or maintenance services? If yes, please outline the scope of the data to which your organization will have access. | B20: Yes | C20: PeriGen support has access to the PeriGen main server and the data stored on it for remote support. The data includes limited patient indentifiers (from ADT) and clinical data collected for these patients (tracings and vitals collected from fetal monitors and manually entered data charted by clinicians).
A21: (7) If your organization is providing remote support/maintenance services, please describe the method used to establish remote access to the client's infrastructure/ product. | B21: Yes | C21: All remote access is done via SecureLink which was approved by SLUHN.
A22: (8) Is there a point of contact for which security related questions/concerns about PeriCALM can be resolved? If so, please provide contact information, including: position title, email, and phone number in the comments section. | B22: Yes | C22: Bruno Bendavid. SVP Product Management. Bruno.bendavid@perigen.com, 514-978-0611
A23: (9) In what year was PeriCALM first offered as a product? | C23: Commercialization started in 2003
A25: Comprehensive Product Security Questionnaire
A26: Security Questions: | B26: Response: | C26: Comments/Evidence:
A27: Certifications
A28: (10) Has PeriCALM attained any of the following security certifications:
A29: • SSAE16 (indicate Type 1 or 2) | B29: No
A30: • SOC 2 (indicate Type 1 or 2) | B30: No
A31: • SOC 3 (indicate Trust Service Principles maintained) | B31: No
A32: • HITRUST | B32: No
A33: • ISO 27001 | B33: No
A34: • FedRamp | B34: No
A35: • CSA STAR (indicate Certification or Attestation) | B35: No
A36: • PCI DSS | B36: No
A37: • Other? Please explain the in comments section. | B37: No
A38: (11) Has PeriCALM attained any of the following miscellaneous certifications:
A39: • HackerSafe | B39: No
A40: • SquareTrade | B40: No
A41: • Qualys | B41: No
A42: • SysTrust/WebTrust | B42: No
A43: • Symantec Certified | B43: No
A44: • Truste | B44: No
A45: • Safe Harbor | B45: No
A46: • CSA STAR Self-Assessment | B46: No
A47: Vulnerability Testing & Patching
A48: (13) If PeriCALM is locally installed at the client's premises, does your organization perform vulnerability testing as part of the product's development lifecycle and whenever new vulnerabilities are identified in the industry? | B48: Yes
A49: (14) If PeriCALM is a hosted solution, does your organization perform periodic vulnerability testing ? If so, how frequently (weekly, monthly, quarterly, etc.) and what tools are used for testing? | B49: N/A (comment required) | C49: Not a hosted solution
A50: (15) If applicable, what was the date of the most recent vulnerability test?
A51: (16) Are there any known vulnerabilities within PeriCALM ? If yes, please provide the details of the existing vulnerabilities and if an fix/patch has been applied or is available to clients for implementation in their environment. | B51: No | C51: None that we are aware of
A52: (18) If the PeriCALM is locally installed at the client's premises, does your organization maintain a formal security patch management process that covers how the product's patches are developed, tested and released to clients? If yes, please provide the documentation. If no formal documentation is maintained, please describe the process in detail. | B52: No | C52: OS Security patches are the responsibility of the customer. PeriGen provides patches on an ongoing basis as part of maintenance release. When such releases are available, PeriGen Ops departement reviewes the version release notes with the customer and ccordinates the right time for deployment/training (if applicable). All versions/patches are first deployed in TEST environment and are approved by the customer prior to deployment to PROD.
A53: (19) If the PeriCALM is a hosted solution, does your organization maintain a formal security patch management process that covers how patches are developed, tested, and applied to the hosted product environment? If yes, please provide the documentation. If no formal documentation is maintained, please describe the process in detail | B53: N/A (comment required) | C53: Not a hosted solution
A54: (20) Has PeriCALM undergone any major platform changes, upgrades, or enhancements in the past six months? If so, please provide a date and brief description of the each change/upgrade/enhancement. | B54: No
A55: Malware Protection
A56: (21) If PeriCALM is locally hosted, does it come with its own malware protection? If not, is PeriCALM capable of integrating with the customer’s existing malware protection such as McAfee or Symantec? | B56: No | C56: The system is known to work with all modern malware protection systems
A57: (22) If PeriCALM is offered as a hosted solution, is server-side malware protection employed? If so, can you provide the name of the malware protection used (e.g., Symantec, McAfee, etc.)? | B57: N/A (comment required) | C57: Hosted by the customer
A58: Security Incident Response
A59: (23) Does your organization maintain a formal incident response policy? If "Yes", please attach the relevant policy documentation. If "No", please explain your incident handling process that applies to the product | B59: Yes
A60: Access Controls & Audit logging
A61: (24) Does PeriCALM maintain audit logging capabilities? If so, please indicate which of the following events are captured by the PeriCALM audit log:
A62: • Login | B62: Yes
A63: • Log off | B63: Yes
A64: • Failed login attempts | B64: Yes
A65: • Files/records viewed | B65: Yes
A66: • Files/records modified | B66: Yes
A67: • Files/records deleted | B67: Yes
A68: (25) Does PeriCALM support role-based account management and access controls (RBAC) that are managed by St. Luke's (SLUHN)? | B68: Yes | C68: User authentication is AD based. Only groups are managed in the PeriCALM systems. Users are fully managed by AD. AD Group names must mirror groups created in PeriCALM and authenticated users that belonging to a matching group receive those PeriCALM configured group authorization settings,
A69: (26) If RBAC is supported, can a St. Luke's (SLUHN) administrator create/customize unique roles & permissions? | B69: Yes
A70: (27) Does PeriCALM support federated identity? If so, how is federated identity achieved (e.g., Active Directory, LDAP, SAML, Single Sign-On, etc.)? | B70: Yes
A71: Data Encryption
A72: (28) If the PeriCALM is locally hosted, can St. Luke's (SLUHN) configure the PeriCALM to encrypt data-in-transit, as per their encryption policies? If so, Please provide all cipher suites supported by the PeriCALM for data-in-transit encryption (e.g., TLS_RSA_WITH_AES_256_CBC_SHA256, TLS_RSA_WITH_RC4_128_SHA, etc.). | B72: No
A73: (29) If the PeriCALM is locally hosted, can St. Luke's (SLUHN) configure the PeriCALM to encrypt data-in-rest, as per their encryption policies? If so, Please provide all cipher suites supported by the PeriCALM for data-at-rest encryption (e.g., AES 128, 3DES, AES 256, etc.)? | B73: No | C73: Not natively. Server OS level encryption is possible. Archive files are encrypted with AES256.
A74: (30) If the PeriCALM is a hosted solution, can PeriCALM encrypt data-in-transit? If so, Please provide all cipher suites supported by PeriCALM for data-in-transit encryption (e.g., TLS_RSA_WITH_AES_256_CBC_SHA256, TLS_RSA_WITH_RC4_128_SHA, etc.). | B74: N/A (comment required)
A75: (31) If the PeriCALM is a hosted solution, can PeriCALM encrypt data-at-rest? If so, Please provide all cipher suites supported by the PeriCALM for data-at-rest encryption (e.g., AES 128, 3DES, AES 256, etc.)? | B75: N/A (comment required)
A76: Data Center & Disaster Recovery
A77: (32) Is PeriCALM hosted in a certified data center? If so, what certification(s) does the data center maintain, and can you please attach copies of the full audit reports in the comments section? | B77: No
A78: (33) Does VENDOR maintain a disaster recovery policy which applies to PeriCALM ? What are the disaster recovery capabilities of PeriCALM ? If so, please describe the policy and attach any relevant documentation. | B78: Yes | C78: The system includes backup tasks of the object-oriented DB used by PeriCALM. These are backed-up by customer enterprise backup tasks. In addition, the system relies on customer VM infrastructure (HA options) and internal backup inrastructure for disaster recovery.
A79: Authentication
A80: (34) What are the password length and complexity requirements enforced by PeriCALM? | B80: NA | C80: AD managed
A81: (35) If password requirements are configurable by St. Luke's (SLUHN)'s administrator, what are the default requirements? | B81: NA | C81: AD managed
A82: (36) Does PeriCALM support multi-factor authentication (MFA)? If so, how is MFA achieved? | B82: No
A83: (37) Does PeriCALM maintain an account lock out feature, activated after a certain number of failed login attempts? If so, how many login attempts trigger an account to be locked and what is the process for unlocking the account? | B83: Yes | C83: Configurable
A84: (38) Do all PeriCALM customers access PeriCALM via a single login portal or is each customer’s implementation accessed via a unique login portal? | B84: NA | C84: PeriCALM is a thick client .Net application
A85: (39) Can you provide the URL for the PeriCALM login? If so, please provide. | B85: N/A (comment required) | C85: PeriCALM is a thick client .Net application

Sheet 1. Access Controls
A1: Control Question # | B1: NIST SP800-53 R4: Control # | C1: HIPAA CFR Control Reference(s) | D1: Control Name | E1: Security Questions: | F1: =Scope!$B$4 & " Response:" -> PeriCALM Tracings Fetal monitoring application Response: | G1: =Scope!$B$4 &" Comments:" -> PeriCALM Tracings Fetal monitoring application Comments: | H1: =Scope!$D$4 & " Response:" -> Response: | I1: =Scope!$D$4 & " Comments:" -> Comments: | J1: =Scope!$F$4 & " Response:" -> Response: | K1: =Scope!$F$4 & " Comments:" -> Comments:
A2: Access Control
A3: AC-1.1 | B3: AC-1 | C3: 164.308(a)(3)(i) 164.308(a)(3)(ii)(A) 164.308(a)(4)(i) 164.308(a)(4)(ii)(B) 164.308(a)(4)(ii)(C) 164.312(a)(1) | D3: Access Control Policy and Procedures | E3: Are there formally documented policies and procedures for access control? If yes, please attach. | F3: Yes | G3: Comment is required | I3: Comment is required | K3: Comment is required
A4: AC-3.1 | B4: AC-3 | C4: 164.308(a)(3)(ii)(A) 164.308(a)(4)(ii)(B) 164.308(a)(4)(ii)(C) 164.310(a)(2)(iii) 164.310(b) 164.312(a)(1) 164.312(a)(2)(i) 164.312(a)(2)(ii) 164.312(a)(2)(iv) | D4: Access Enforcement | E4: Does the information system verify the rights of a user to access the information system? (Access Control Lists, Group/Role membership?) If yes, detail how the access is enforced in the comment. | F4: Yes | G4: Access controlled is enforced by groups membership. An AD user must belong to an AD group that is identical by name to an internal PeriCALM group. An authenticated user that belong to such a group inherits its access rights. These rights are controlled by the customer application administrators where AD group membership is controlled by customer IT administrators. | I4: Comment is required | K4: Comment is required
A5: AC-3.2 | B5: N/A | E5: Does the information system support role-based account management and access controls (RBAC)? | F5: Yes | G5: Comment is required | I5: Comment is required | K5: Comment is required
A6: AC-3.3 | B6: N/A | E6: If RBAC is supported, can a customer administrator create/customize unique roles and permissions. | F6: Yes | G6: Comment is required | I6: Comment is required | K6: Comment is required
A7: AC-7.1 | B7: AC-7 | D7: Unsuccessful Logon Attempts | E7: Is an account automatically locked out after a set amount of attempts? If yes, please provide the number of failed attempts that trigger an account to be locked out, in the comments section. | F7: Yes | G7: Via AD authentication controls. | I7: Comment is required | K7: Comment is required
A8: AC-8.1 | B8: AC-8 | D8: System Use Notification | E8: Is there a system use notification displayed before granting access that provides privacy and security notices? | F8: No | G8: Comment is required | I8: Comment is required | K8: Comment is required
A9: AC-9.1 | B9: AC-9 | D9: Previous Logon Notification | E9: Does the system display the last user logon date and time to the user? | F9: No | G9: Comment is required | I9: Comment is required | K9: Comment is required
A10: AC-10.1 | B10: AC-10 | D10: Concurrent Session Control | E10: Does the system limit the number of concurrent sessions for the user? | F10: No | G10: Comment is required | I10: Comment is required | K10: Comment is required
A11: AC-11.1 | B11: AC-11 | C11: 164.310(b) 164.312(a)(2)(iii) | D11: Session Lock | E11: Does the application/system have a session lock after a period of inactivity that requires a user to reauthenticate? | F11: Yes | G11: Comment is required | I11: Comment is required | K11: Comment is required
A12: AC-12.1 | B12: AC-12 | C12: 164.310(b) 164.312(a)(2)(iii) | D12: Session Termination | E12: Does the application/system terminate the session after predefined circumstances? | F12: No | G12: Comment is required | I12: Comment is required | K12: Comment is required
A13: AC-14.1 | B13: AC-14 | D13: Permitted Actions without Identification or Authentication | E13: Does the system prevent user actions that can be performed on the system without identification and authentication? | F13: Yes | G13: Comment is required | I13: Comment is required | K13: Comment is required

Sheet 2. Awareness and Training
A1: Control Question # | B1: NIST SP800-53 R4: Control # | C1: HIPAA CFR Control Reference(s) | D1: Control Name | E1: Security Questions: | F1: =Scope!$B$4 & " Response:" -> PeriCALM Tracings Fetal monitoring application Response: | G1: =Scope!$B$4 &" Comments:" -> PeriCALM Tracings Fetal monitoring application Comments: | H1: =Scope!$D$4 & " Response:" -> Response: | I1: =Scope!$D$4 & " Comments:" -> Comments: | J1: =Scope!$F$4 & " Response:" -> Response: | K1: =Scope!$F$4 & " Comments:" -> Comments:
A2: Awareness and Training
A3: AT-1.1 | B3: AT-1 | C3: 164.308(a)(5)(i) | D3: Security Awareness and Training Policy and Procedures | E3: Are there formally documented procedures for security awareness and training for this information system? If yes, please attach. | F3: Yes | G3: Comment is required | I3: Comment is required | K3: Comment is required
A4: AT-2.1 | B4: AT-2 | C4: 164.308(a)(5)(i) 164.308(a)(5)(ii)(A) 164.308(a)(5)(ii)(B) | D4: Security Awareness | E4: Is basic security awareness training performed for all personnel as a part of the onboarding process? | F4: Yes | G4: Comment is required | I4: Comment is required | K4: Comment is required
A5: AT-2.2 | E5: Is it periodically performed for all users? | F5: Yes | G5: Customer responsibility to train their internal administrators/super-users to periodically train end-users | I5: Comment is required | K5: Comment is required
A6: AT-3.1 | B6: AT-3 | C6: 164.308(a)(5)(i) | D6: Role-Based Security Training | E6: Is there role-based security training for personnel with assigned security roles and responsibilities for this information system before access is granted and when required by information system changes? | F6: No | G6: All security related topics are cover during initial training and user guides | I6: Comment is required | K6: Comment is required
A7: AT-4.1 | B7: AT-4 | C7: 164.308(a)(5)(i) | D7: Security Training Records | E7: Do you document and monitor information system security training activities for individuals? | F7: No | G7: Comment is required | I7: Comment is required | K7: Comment is required

Sheet 3. Audit and Accountability
A1: Control Question # | B1: NIST SP800-53 R4: Control # | C1: HIPAA CFR Control Reference(s) | D1: Control Name | E1: Security Questions: | F1: =Scope!$B$4 & " Response:" -> PeriCALM Tracings Fetal monitoring application Response: | G1: =Scope!$B$4 &" Comments:" -> PeriCALM Tracings Fetal monitoring application Comments: | H1: =Scope!$D$4 & " Response:" -> Response: | I1: =Scope!$D$4 & " Comments:" -> Comments: | J1: =Scope!$F$4 & " Response:" -> Response: | K1: =Scope!$F$4 & " Comments:" -> Comments:
A2: Audit and Accountability
A3: AU-2.1 | B3: AU-2 | C3: 164.308(a)(5)(ii)(C) 164.312(b) | D3: Audit Events | E3: Is the information system actively auditing events such as access to patient information, login/logoffs, account creation, etc.? If yes, please detail the events captured in the comment. | F3: Yes | G3: * logon/logoff * Access from station (hostname) * Screens access by user * All data changes (old values, new values, user, dataTime) All the above include username and dataTime | I3: Comment is required | K3: Comment is required
A4: AU-2.2 | E4: Are the audit logs captured sufficient for incident response and system and user performance/investigation? | F4: Yes | G4: Comment is required | I4: Comment is required | K4: Comment is required
A5: AU-3.1 | B5: AU-3 | C5: 164.312(b) | D5: Content of Audit Records | E5: Does the system create audit records that contain sufficient information to, at a minimum, establish what type of event occurred, when the event occurred, where the event occurred, the source of the event, the outcome (success or failure) of the event, and the identity of any user/subject associated with the event? | F5: Yes | G5: Comment is required | I5: Comment is required | K5: Comment is required
A6: AU-5.1 | B6: AU-5 | D6: Response to Audit Processing Failures | E6: Does the information system generate an alert that notifies the team in the event of an audit processing failure? | F6: No | G6: Comment is required | I6: Comment is required | K6: Comment is required
A7: AU-7.1 | B7: AU-7 | C7: 164.308(a)(1)(ii)(D) 164.312(b) | D7: Audit Reduction and Report Generation | E7: Does the information system provide the capability to generate customizable audit reports? | F7: No | G7: Comment is required | I7: Comment is required | K7: Comment is required
A8: AU-7.2 | E8: Does the generation of an audit report alter the original content or time stamp of the audit record? | F8: No | G8: Comment is required | I8: Comment is required | K8: Comment is required
A9: AU-8.1 | B9: AU-8 | D9: Time Stamps | E9: Are the audit logs time stamped? (Date and Time) | F9: Yes | G9: Comment is required | I9: Comment is required | K9: Comment is required
A10: AU-9.1 | B10: AU-9 | D10: Protection of Audit Information | E10: Does the system/application protect audit information from unauthorized access, modification, and deletion? | F10: Yes | G10: Comment is required | I10: Comment is required | K10: Comment is required
A11: AU-12.1 | B11: AU-12 | D11: Audit Generation | E11: Can the information system be configured to select which auditable events are captured in the audit log? | F11: No | G11: Comment is required | I11: Comment is required | K11: Comment is required

Sheet 5. Configuration
A1: Control Question # | B1: NIST SP800-53 R4: Control # | C1: HIPAA CFR Control Reference(s) | D1: Control Name | E1: Security Questions: | F1: =Scope!$B$4 & " Response:" -> PeriCALM Tracings Fetal monitoring application Response: | G1: =Scope!$B$4 &" Comments:" -> PeriCALM Tracings Fetal monitoring application Comments: | H1: =Scope!$D$4 & " Response:" -> Response: | I1: =Scope!$D$4 & " Comments:" -> Comments: | J1: =Scope!$F$4 & " Response:" -> Response: | K1: =Scope!$F$4 & " Comments:" -> Comments:
A2: Configuration Management
A3: CM-1.1 | B3: CM-1 | D3: Configuration Management Policy and Procedures | E3: Are there documented procedures to outline who/when and how the system/application is configured? If yes, please attach | F3: Yes | G3: Comment is required | I3: Comment is required | K3: Comment is required
A4: CM-2.1 | B4: CM-2 | D4: Baseline Configuration | E4: Do you have a current configuration baseline documented for the information system? (The baseline configuration is a documented, up-to-date specification to which the information system is built.) | F4: No | G4: Configuration is a site/customer specific. The system comes with some defaults (ex: everything is logged) but other configurations like AD/LDAP servers for authentication, interfaces, bed-configurations are all done according to customer needs. | I4: Comment is required | K4: Comment is required
A5: CM-3.1 | B5: CM-3 | D5: Configuration Change Control | E5: Are types of changes to the information system that are configuration-controlled defined? | F5: No | G5: All changes to the system are coordinated with the csustomer and require customer approval. | I5: Comment is required | K5: Comment is required
A6: CM-3.2 | E6: Does the organization review proposed configuration-controlled changes to the information system, using defined security impact analyses? | F6: Yes | G6: Comment is required | I6: Comment is required | K6: Comment is required
A7: CM-3.3 | E7: Are all configuration changes adequately documented? | F7: Yes | G7: Always coordinated with the customer | I7: Comment is required | K7: Comment is required
A8: CM-3.4 | E8: Are all approved configuration controls implemented timely? | F8: Yes | G8: Always coordinated with the customer | I8: Comment is required | K8: Comment is required
A9: CM-3.5 | E9: Does the organization retain records of configuration controlled changes? | F9: Yes | G9: Records are maintained in our corporate ticketing system or as part of formal project(s) to add/change aspects of the system | I9: Comment is required | K9: Comment is required
A10: CM-3.6 | E10: Are there auditing and monitoring activities implemented to assess the configuration-controlled changes? | F10: Partial | G10: Some changes have auditable controls associated, others do not. For example, adding a mapped field from HL7. The new field will show in the audit trail but the action of adding the field in the mapping tables in the DB do not. | I10: Comment is required | K10: Comment is required
A11: CM-4.1 | B11: CM-4 | D11: Security Impact Analysis | E11: Do you analyze changes to the information system to determine potential security impacts prior to change implementation? | F11: No | I11: Comment is required | K11: Comment is required
A12: CM-6.1 | B12: CM-6 | D12: Configuration Settings | E12: Have all the configuration settings been documented that reflect the most restrictive mode consistent with operational requirements? | F12: No | G12: common best practices are used with the limited controls offered by PeriCALM Tracings | I12: Comment is required | K12: Comment is required
A13: CM-6.2 | E13: Is there any automated or manual monitoring of configuration changes? (e.g. Tripwire, manual checklists) | F13: No | G13: Comment is required | I13: Comment is required | K13: Comment is required
A14: CM-6.3 | E14: Do you document and approve deviations from the established configuration settings? | F14: No | G14: Comment is required | I14: Comment is required | K14: Comment is required
A15: CM-7.1 | B15: CM-7 | D15: Least Functionality | E15: Do you restrict or prohibit the use of any functions, ports, protocols and/or services that are not essential to the function of the information system? | F15: Yes | G15: Comment is required | I15: Comment is required | K15: Comment is required
A16: CM-8.1 | B16: CM-8 | C16: 164.310(d)(1) 164.310(d)(2)(iii) | D16: Information System Component Inventory | E16: Do you have an accurate and current documented inventory of the components within the information system? | F16: Yes | G16: Comment is required | I16: Comment is required | K16: Comment is required
A17: CM-8.2 | E17: If yes, do you review and update the information system component inventory regularly? | F17: Yes | G17: We review all components and 3rd party tools when planning major releases | I17: Comment is required | K17: Comment is required
A18: CM-9.1 | B18: CM-9 | D18: Configuration Management Plan | E18: Does the organization develop, document, and implement a configuration management plan for the information system that addresses roles, responsibilities and configuration management processes and procedures? | F18: No | G18: This is customer responsibility | I18: Comment is required | K18: Comment is required
A19: CM-9.2 | E19: Does the organization establish a process for identifying configuration items throughout the system development life cycle? | F19: Yes | G19: All configuration and development items are tracked as part of the product development process | I19: Comment is required | K19: Comment is required
A20: CM-9.3 | E20: Does the organization define configuration items for the information system? | F20: Yes | G20: Hardware specifications, data acquisition devices are documented per release and communicated to the customer when they change | I20: Comment is required | K20: Comment is required
A21: CM-9.4 | E21: Does the organization protect the configuration management plan for unauthorized disclosures and modifications? | F21: Yes | G21: Comment is required | I21: Comment is required | K21: Comment is required
A22: CM-11.1 | B22: CM-11 | D22: User-Installed Software | E22: Is user installation of software restricted and monitored? | F22: N/A | G22: Only designated PeriGen personnel or trained customer IT personnel can install elements of the system | I22: Comment is required | K22: Comment is required
A23: CM-12.1 | B23: N/A | D23: Patch Timeliness | E23: Are patches applied to the information system in a timely manner? If so, how quickly are patches applied? | F23: Yes | G23: Customer controlled | I23: Comment is required | K23: Comment is required
A24: CM-12.2 | D24: Patch Timeliness Policy | E24: Are there standards or policies which define the timing of patching the information system? | F24: No | G24: Customer controlled | I24: Comment is required | K24: Comment is required
A25: CM-13.1 | B25: N/A | D25: Patch Management Environments | E25: Do you use Development, Test, QA, and Production environments during the patch management process? If so, describe the manner in which these environment are utilized? | F25: Yes | G25: Mostly, OS hot-fixes and patches are pushed directly to all environments. PeriGen software is always loaded on the TEST system and only pushed to PROD upon customer approval | I25: Comment is required | K25: Comment is required
A26: CM-14.1 | B26: N/A | D26: Patch Classification | E26: Do you categorize patches based on severity? If yes, please provide the categories, their definitions, and the associated time frames for deploying patches to production environments. | F26: No | G26: Case by case basis | I26: Comment is required | K26: Comment is required
A27: CM-14.2 | B27: N/A | E27: Do you implement patches categorized as "critical" within 72 hours of patch release? | F27: Partial | G27: Case by case basis | I27: Comment is required | K27: Comment is required

Sheet 7. Authentication&Authorization
A1: Control Question # | B1: NIST SP800-53 R4: Control # | C1: HIPAA CFR Control Reference(s) | D1: Control Name | E1: Security Questions: | F1: =Scope!$B$4 & " Response:" -> PeriCALM Tracings Fetal monitoring application Response: | G1: =Scope!$B$4 &" Comments:" -> PeriCALM Tracings Fetal monitoring application Comments: | H1: =Scope!$D$4 & " Response:" -> Response: | I1: =Scope!$D$4 & " Comments:" -> Comments: | J1: =Scope!$F$4 & " Response:" -> Response: | K1: =Scope!$F$4 & " Comments:" -> Comments:
A2: Identification and Authentication
A3: IA-1.1 | B3: IA-1 | D3: Identification and Authentication Policy and Procedures | E3: Does the application/system use managed LDAP services for identification and authentication? If no, detail in the comment column what is used. | F3: Yes | G3: Customer responsibility to provide. PeriCALM Tracings supports authentication via LDAP | I3: Comment is required | K3: Comment is required
A4: IA-2.1 | B4: IA-2 | C4: 164.308(a)(5)(ii)(D) 164.312(a)(2)(i) 164.312(d) | D4: Identification and Authentication (Organizational Users) | E4: Does the information system use multifactor authentication for privileged or non-privileged access? (Uses at least two of: what you have, what you know, what you are. E.g., tokens, passwords, biometrics.) | F4: No | G4: Comment is required | I4: Comment is required | K4: Comment is required
A5: IA-3.1 | B5: IA-3 | C5: 164.312(a)(2)(i) 164.312(d) | D5: Device Identification and Authentication | E5: Does the information system uniquely identify and authenticate devices before establishing a connection? (E.g., MAC, TCP/IP, IEEE 802.1x) | F5: Yes | G5: All stations must be configured for access on the server. Identification is done by hostname (DNS) | I5: Comment is required | K5: Comment is required
A6: IA-4.2 | D6: Identifier Management | E6: Does the application/system prevent reuse of user or device identifiers? | F6: Yes | G6: Comment is required | I6: Comment is required | K6: Comment is required
A7: IA-4.3 | E7: Does the application/system disable the user or device account after a pre-defined period of inactivity? | F7: Yes | G7: Comment is required | I7: Comment is required | K7: Comment is required
A8: IA-5.1 | B8: IA-5 | C8: 164.308(a)(5)(ii)(D) | D8: Authenticator Management | E8: Does the application/system comply with the password complexity as outlined in implemented policies? | F8: N/A | G8: AD controlled | I8: Comment is required | K8: Comment is required
A9: IA-5.2 | E9: Does information system force the End User to comply with the following password requirements regarding complexity, length and change? - Passwords at least 8 characters in length. - Passwords contain the following: - Mixed case alpha characters - at least one numeric digit - at least one non-alphanumeric character - Current password may not be reused - Do current passwords expire every 90 days? - Are passwords stored in an encrypted format? | F9: N/A | G9: AD controlled | I9: Comment is required | K9: Comment is required
A10: IA-5.3 | E10: Are the passwords encrypted within the information system when stored or transmitted? | F10: Yes | G10: Comment is required | I10: Comment is required | K10: Comment is required
A11: IA-5.7 | E11: Is authenticator content protected from unauthorized disclosure and modification? | F11: Yes | G11: Comment is required | I11: Comment is required | K11: Comment is required
A12: IA-5.9 | E12: Is token-based authentication utilized? | F12: Yes | G12: AD controlled | I12: Comment is required | K12: Comment is required
A13: IA-6.1 | B13: IA-6 | C13: 164.308(a)(5)(ii)(D) | D13: Authenticator Feedback | E13: Does the information system obscure the authenticator/password during the authentication process? | F13: Yes | G13: Comment is required | I13: Comment is required | K13: Comment is required
A14: IA-7.1 | B14: IA-7 | C14: 164.308(a)(5)(ii)(D) | D14: Cryptographic Module Authentication | E14: Does the information system use mechanisms for authentication to a cryptographic module? (This control is used for mostly operating systems and appliances used to encrypt something.) | F14: No | G14: Comment is required | I14: Comment is required | K14: Comment is required

Sheet 8. Incident Response
A1: Control Question # | B1: NIST SP800-53 R4: Control # | C1: HIPAA CFR Control Reference(s) | D1: Control Name | E1: Security Questions: | F1: =Scope!$B$4 & " Response:" -> PeriCALM Tracings Fetal monitoring application Response: | G1: =Scope!$B$4 &" Comments:" -> PeriCALM Tracings Fetal monitoring application Comments: | H1: =Scope!$D$4 & " Response:" -> Response: | I1: =Scope!$D$4 & " Comments:" -> Comments: | J1: =Scope!$F$4 & " Response:" -> Response: | K1: =Scope!$F$4 & " Comments:" -> Comments:
A2: Incident Response
A3: IR-1.1 | B3: IR-1 | C3: 164.308(a)(6)(i) | D3: Incident Response Policies and Procedures | E3: Are there formally documented policies and procedures for Incident Response? If yes, please attach. | F3: Yes | G3: Comment is required | I3: Comment is required | K3: Comment is required
A4: IR-2.1 | B4: IR-2 | C4: 164.308(a)(6)(i) | D4: Incident Response Training | E4: Are staff provided with incident response training? | F4: Yes | G4: Comment is required | I4: Comment is required | K4: Comment is required
A5: IR-2.2 | E5: Is incident response training unique based on the role of the individual? | F5: Yes | G5: Comment is required | I5: Comment is required | K5: Comment is required
A6: IR-3.1 | B6: IR-3 | C6: 164.308(a)(6)(i) | D6: Incident Response Testing and Exercises | E6: Are incident response tests conducted? | F6: No | G6: Comment is required | I6: Comment is required | K6: Comment is required
A7: IR-3.2 | E7: Are the incident response test results analyzed? | F7: No | G7: Comment is required | I7: Comment is required | K7: Comment is required
A8: IR-4.1 | B8: IR-4 | C8: 164.308(a)(6)(ii) | D8: Incident Handling | E8: Is there an incident handling process | F8: Yes | G8: Comment is required | I8: Comment is required | K8: Comment is required
A9: IR-5.1 | B9: IR-5 | C9: 164.308(a)(1)(ii)(D) 164.308(a)(6)(ii) | D9: Incident Monitoring | E9: Are security incidents tracked and documented? | F9: Yes | G9: Comment is required | I9: Comment is required | K9: Comment is required
A10: IR-6.1 | B10: IR-6 | C10: 164.308(a)(1)(ii)(D) 164.308(a)(6)(ii) 164.314(a)(2)(i) | D10: Incident Reporting | E10: Are security incidents timely reported to appropriate personnel/ government authorities? | F10: Yes | G10: Comment is required | I10: Comment is required | K10: Comment is required
A11: IR-7.1 | B11: IR-7 | C11: 164.308(a)(6)(ii) | D11: Incident Response Assistance | E11: Are incident response resources used outside of the incident response team? | F11: Yes | G11: If required. Case by case basis. | I11: Comment is required | K11: Comment is required
A12: IR-8.1 | B12: IR-8 | D12: Incident Response Plan | E12: Is there a comprehensive Incident Response Plan? If so, please attach. | F12: Yes | G12: see internal policy | I12: Comment is required | K12: Comment is required
A13: IR-9.1 | B13: IR-9 | D13: Information Spillage Response | E13: Does the organization respond to information spillage appropriately and timely? | F13: Yes | G13: Comment is required | I13: Comment is required | K13: Comment is required

Sheet 9. Maintenance
A1: Control Question # | B1: NIST SP800-53 R4: Control # | C1: HIPAA CFR Control Reference(s) | D1: Control Name | E1: Security Questions: | F1: =Scope!$B$4 & " Response:" -> PeriCALM Tracings Fetal monitoring application Response: | G1: =Scope!$B$4 &" Comments:" -> PeriCALM Tracings Fetal monitoring application Comments: | H1: =Scope!$D$4 & " Response:" -> Response: | I1: =Scope!$D$4 & " Comments:" -> Comments: | J1: =Scope!$F$4 & " Response:" -> Response: | K1: =Scope!$F$4 & " Comments:" -> Comments:
A2: Maintenance
A3: MA-1.1 | B3: MA-1 | C3: 164.310(a)(2)(iv) | D3: System Maintenance Policy and Procedures | E3: Are there formally documented policies and procedures for Maintenance? If yes, please attach. | F3: Yes | G3: PeriGen does not provide propriatary internal QMS documents | I3: Comment is required | K3: Comment is required
A4: MA-2.5 | D4: Controlled Maintenance | E4: Do you check all potentially impacted security controls to verify that the controls are still functioning properly following maintenance or repair actions? (E.g., verify that audit logs are still functioning properly, user level of access is still appropriate.) | F4: Partial | G4: For internal access control to access customer sites - Yes. Regular checks of PeriCALM system is the responsibility of the customer. | I4: Comment is required | K4: Comment is required
A5: MA-3.1 | B5: MA-3 | D5: Maintenance Tools | E5: Does the organization approve, control and monitor information system maintenance tools? | F5: Yes | G5: Yes as part of QA/QC process of product releases. That said, controls on customer provided servers is the responsibility of the customer. | I5: Comment is required | K5: Comment is required
A6: MA-4.1 | B6: MA-4 | D6: Nonlocal Maintenance | E6: Is any nonlocal maintenance and diagnostic activity performed on the information system (such as across the network, either internal or external, using terminal services/RDP)? | F6: Yes | G6: Comment is required | I6: Comment is required | K6: Comment is required
A7: MA-4.2 | E7: Are all nonlocal maintenance and diagnostic activities approved and monitored? | F7: Yes | G7: Since we provide 24/7/365 support, out help desk team along with more senior technical analysts have access to the site remotely to resolve/troubleshoot and system problem. No specific approval is needed other than the original authorization of approved resources to access remote customer sites via SecureLink. | I7: Comment is required | K7: Comment is required
A8: MA-4.3 | E8: Are strong authenticators/passwords used in the establishment of nonlocal maintenance and diagnostic sessions? | F8: Yes | G8: Comment is required | I8: Comment is required | K8: Comment is required
A9: MA-4.4 | E9: Do you maintain records for nonlocal maintenance and diagnostic activities? | F9: Yes | G9: Only Audit logs or access via SecureLink | I9: Comment is required | K9: Comment is required
A10: MA-4.5 | E10: Are the sessions and network connections terminated after the nonlocal maintenance has been completed? | F10: Yes | G10: Comment is required | I10: Comment is required | K10: Comment is required
A11: MA-5.1 | B11: MA-5 | C11: 164.308(a)(3)(ii)(A) | D11: Maintenance Personnel | E11: Do you authorize and maintain a list of authorized maintenance personnel? | F11: Yes | G11: Access to hospital is goverend by individual account / profile in SecureLink. | I11: Comment is required | K11: Comment is required
A12: MA-5.2 | E12: Do you ensure that personnel performing maintenance of the information system have the required access authorizations? | F12: Yes | G12: Comment is required | I12: Comment is required | K12: Comment is required

Sheet 13. Personnel Security
A1: Control Question # | B1: NIST SP800-53 R4: Control # | C1: HIPAA CFR Control Reference(s) | D1: Control Name | E1: Security Questions: | F1: =Scope!$B$4 & " Response:" -> PeriCALM Tracings Fetal monitoring application Response: | G1: =Scope!$B$4 &" Comments:" -> PeriCALM Tracings Fetal monitoring application Comments: | H1: =Scope!$D$4 & " Response:" -> Response: | I1: =Scope!$D$4 & " Comments:" -> Comments: | J1: =Scope!$F$4 & " Response:" -> Response: | K1: =Scope!$F$4 & " Comments:" -> Comments:
A2: Personnel Security
A3: PS-1.1 | B3: PS-1 | C3: 164.308(a)(3)(ii)(A) 164.308(a)(3)(ii)(B) 164.308(a)(3)(ii)(C) | D3: Personnel Security Policies and Procedures | E3: Are there formally documented policies and procedures for Personnel Security? If yes, please attach. | F3: Yes | I3: Comment is required | K3: Comment is required
A4: PS-2.1 | B4: PS-2 | C4: 164.308(a)(3)(ii)(B) | D4: Position Risk Designation | E4: Does the organization assign risk designations to all positions? | F4: No | I4: Comment is required | K4: Comment is required
A5: PS-2.2 | E5: Does the organization establish screening criteria for individuals filling those positions? | F5: Yes | G5: All employees are screened during job interviews | I5: Comment is required | K5: Comment is required
A6: PS-2.3 | E6: Does the organization review and revise position risk designations at least every three years? | F6: No | I6: Comment is required | K6: Comment is required
A7: PS-3.1 | B7: PS-3 | C7: 164.308(a)(3)(ii)(B) | D7: Personnel Screening | E7: Does the organization screen individuals prior to authorizing access to the information system? | F7: Yes | G7: All employees are screened during job interviews | I7: Comment is required | K7: Comment is required
A8: PS-3.2 | E8: Does the organization re-screen individuals with access to the information system? | F8: No | I8: Comment is required | K8: Comment is required
A9: PS-4.1 | B9: PS-4 | C9: 164.308(a)(3)(ii)(C) | D9: Personnel Termination | E9: Does the organization have appropriate termination procedures in place to those with access to the information system? | F9: Yes | I9: Comment is required | K9: Comment is required
A10: PS-5.1 | B10: PS-5 | C10: 164.308(a)(3)(ii)(C) | D10: Personnel Transfer | E10: Does the organization have appropriate transfer procedures in place to those with access to the information system? | F10: No | I10: Comment is required | K10: Comment is required
A11: PS-6.1 | B11: PS-6 | C11: 164.308(a)(3)(ii)(A) 164.308(a)(3)(ii)(B) 164.308(a)(4)(ii)(B) 164.310(b) 164.310(d)(2)(iii) 164.314(a)(1) 164.314(a)(2)(i) 164.314(a)(2)(ii) | D11: Access Agreements | E11: Does the organization have access agreements (reviewed annually) for individuals with access to the information system? | F11: Partial | G11: Access control is granted per unique user account/role (example: technical support analyst). Each employee signs an employment agreement that explicitly covers controls of access to customer data. In addition, HIPAA, Security & Privacy guidelines are revised and signed-off annually by all employees. That said, there are no explicity "access agreements" for individual employees. | I11: Comment is required | K11: Comment is required
A12: PS-7.1 | B12: PS-7 | C12: 164.308(a)(3)(ii)(A) 164.308(a)(4)(ii)(B) 164.308(b)(1) 164.314(a)(1) 164.314(a)(2)(i) 164.314(a)(2)(ii) | D12: Third Party Personnel Security | E12: Does the organization have appropriate third-party access control procedures for external parties granted access to the information system? | F12: Yes | I12: Comment is required | K12: Comment is required
A13: PS-8.1 | B13: PS-8 | C13: 164.308(a)(1)(ii)(C) | D13: Personnel Sanctions | E13: Does the organization have appropriate personnel sanctions policies and procedures? | F13: Yes | I13: Comment is required | K13: Comment is required

Sheet 15. System Acquisition
A1: Control Question # | B1: NIST SP800-53 R4: Control # | C1: HIPAA CFR Control Reference(s) | D1: Control Name | E1: Security Questions: | F1: =Scope!$B$4 & " Response:" -> PeriCALM Tracings Fetal monitoring application Response: | G1: =Scope!$B$4 &" Comments:" -> PeriCALM Tracings Fetal monitoring application Comments: | H1: =Scope!$D$4 & " Response:" -> Response: | I1: =Scope!$D$4 & " Comments:" -> Comments: | J1: =Scope!$F$4 & " Response:" -> Response: | K1: =Scope!$F$4 & " Comments:" -> Comments:
A2: System and Services Acquisition
A3: SA-1.1 | B3: SA-1 | D3: System and Services Acquisition Policy and Procedure | E3: Are there formally documented policies and procedures for System and Services Acquisitions? If yes, please attach. | F3: No | G3: Comment is required | I3: Comment is required | K3: Comment is required
A4: SA-3.1 | B4: SA-3 | D4: System Development Life Cycle | E4: Does the organization define a comprehensive life cycle for the information system? | F4: Yes | G4: Comment is required | I4: Comment is required | K4: Comment is required
A5: SA-4.1 | B5: SA-4 | C5: 164.314(a)(2)(i) | D5: Acquisition Process | E5: Does the organization include the requirements, descriptions, and criteria, explicitly or by reference, in the acquisition contract for the information system, system component, or information system service in accordance with applicable federal laws, Executive Orders, directives, policies, regulations, standards, guidelines, and organizational mission/business needs | F5: Yes | G5: yes as it applies to conracts for customers purchasing the PeriCALM software modules | I5: Comment is required | K5: Comment is required
A6: SA-5.1 | B6: SA-5 | D6: Information System Documentation | E6: Do you have administrator documentation for this information system that describes: 1. Secure configuration, installation, and operation of the system, component, or service; 2. Effective use and maintenance of security functions/mechanisms; and 3. Known vulnerabilities regarding configuration and use of administrative (i.e., privileged) functions; | F6: Yes | G6: Comment is required | I6: Comment is required | K6: Comment is required
A7: SA-5.2 | E7: Do you have user documentation for this information system that describes: 1. User-accessible security functions/mechanisms and how to effectively use those security functions/mechanisms; 2. Methods for user interaction, which enables individuals to use the system, component, or service in a more secure manner; and 3. User responsibilities in maintaining the security of the system, component, or service. | F7: Partial | G7: PeriGen provide end-user and administrator documentation that cover all aspects of the system include acces controls and configurations. PeriGen provide admin training to customer technical staff and ongoing management is customer responsibility | I7: Comment is required | K7: Comment is required
A8: SA-5.4 | E8: Is the documentation protected as required and only distributed to authorized personnel? | F8: No | G8: End-user and admin guides are provided/available to users accessing the system in a clinical setting. Other material is provided directly to staff during training sessions | I8: Comment is required | K8: Comment is required
A9: SA-8.1 | B9: SA-8 | D9: Security Engineering Principles | E9: Does the organization apply information system security engineering principles in the specification, design, development, implementation, and modification of the information system. | F9: Yes | G9: Comment is required | I9: Comment is required | K9: Comment is required
A10: SA-10.1 | B10: SA-10 | D10: Developer Configuration Management | E10: Does the organization require the developer of the information system, system component or information system service to perform configuration, document the changes and implement only organization-approved configuration changes? | F10: Yes | G10: Comment is required | I10: Comment is required | K10: Comment is required
A11: SA-11.1 | B11: SA-11 | D11: Developer Security Testing and Evaluation | E11: Does the organization require the developer of the information system, system component, or information system service to create and implement a security assessment plan, perform tests/evaluations and produce evidence of the execution of the security assessment plan? | F11: Yes | G11: Comment is required | I11: Comment is required | K11: Comment is required

Sheet 16. System Data Protection
A1: Control Question # | B1: NIST SP800-53 R4: Control # | C1: HIPAA CFR Control Reference(s) | D1: Control Name | E1: Security Questions: | F1: =Scope!$B$4 & " Response:" -> PeriCALM Tracings Fetal monitoring application Response: | G1: =Scope!$B$4 &" Comments:" -> PeriCALM Tracings Fetal monitoring application Comments: | H1: =Scope!$D$4 & " Response:" -> Response: | I1: =Scope!$D$4 & " Comments:" -> Comments: | J1: =Scope!$F$4 & " Response:" -> Response: | K1: =Scope!$F$4 & " Comments:" -> Comments:
A2: System and Communications Protection
A3: SC-1.1 | B3: SC-1 | D3: System and Communications Protection Policy and Procedures | E3: Do you have formally documented policies and procedures for System and Communications Protection? If yes, please attach. | F3: No | G3: Comment is required | I3: Comment is required | K3: Comment is required
A4: SC-2.1 | B4: SC-2 | D4: Application Partitioning | E4: Does The information system separate user functionality (including user interface services) from information system management functionality? | F4: Yes | G4: Comment is required | I4: Comment is required | K4: Comment is required
A5: SC-8.1 | B5: SC-8 | C5: 164.312(c)(1) 164.312(c)(2) 164.312(e)(1) *From SC-09 164.312(e)(2)(i) 164.312(e)(2)(ii) *From SC-09 | D5: Transmission Confidentiality and Integrity | E5: Does the application/system utilize cryptographic protocols to protect the integrity of transmitted information? If yes, how is this achieved (e.g., SSL 2, SSL 3, TLS 1.0)? | F5: No | G5: Comment is required | I5: Comment is required | K5: Comment is required
A6: SC-8.2 | E6: Does the application/system employ cryptographic mechanisms to recognize changes to information during transmission (such as hashing algorithms)? | F6: No | G6: Comment is required | I6: Comment is required | K6: Comment is required
A7: SC-10.1 | B7: SC-10 | D7: Network Disconnect | E7: Does the information system terminate network connection associated with a communication session at the end of the session or after no longer than 30 minutes of inactivity? | F7: Yes | G7: Comment is required | I7: Comment is required | K7: Comment is required
A8: SC-13.1 | B8: SC-13 | C8: 164.312(a)(2)(iv) 164.312(e)(2)(ii) | D8: Cryptographic Protection | E8: Does the information system use cryptographic protections? If yes, detail the encryption algorithm and strength in the comment (AES 128, 3DES, etc.) | F8: Partial | G8: Only for archive files (long term encrypted and compressed XML documents) | I8: Comment is required | K8: Comment is required
A9: SC-15.1 | B9: SC-15 | D9: Collaborative Computing Devices | E9: Does the information system support the use of collaborative computing devices (e.g., networked white boards, cameras, microphones)? | F9: No | G9: Comment is required | I9: Comment is required | K9: Comment is required
A10: SC-15.2 | E10: Is remote activation prohibited? | F10: N/A | G10: No such function exist in PeriCALM | I10: Comment is required | K10: Comment is required
A11: SC-15.3 | E11: Does the device indicate to the user that it is actively in use? (E.g., activated microphone or camera has an illuminated indicator light.) | F11: N/A | G11: No such devioces supported. When the system is in use, the UI is showing and active data is being collected/traced on the screen | I11: Comment is required | K11: Comment is required
A12: SC-20.1 | B12: SC-20 | D12: Secure Name/Address Resolution Service (Authoritative Source) | E12: Does the information system provide additional data origin authentication and integrity verification artifacts along with the authoritative name resolution data the system returns in response to external name/address resolution queries? | F12: Yes | G12: Data is trasmitted from client to server over MSMQ messages which rely on DNS hostname validation/registration. Only configured station (by hostname) can open a session to the server and access data if authenticated. | I12: Comment is required | K12: Comment is required
A13: SC-21.1 | B13: SC-21 | D13: Secure Name/Address Resolution Service (Recursive or Caching Resolver) | E13: Does the information system request and perform data origin authentication and data integrity verification on the name/address resolution responses the system receives from authoritative sources? | F13: Yes | G13: as mentioned above | I13: Comment is required | K13: Comment is required
A14: SC-23.1 | B14: SC-23 | D14: Session Authenticity | E14: Does the information system protect the authenticity of communication sessions? | F14: Yes | G14: only by DNS resolution | I14: Comment is required | K14: Comment is required
A15: SC-28.1 | B15: SC-28 | D15: Protection of Information at Rest | E15: Does the organization support the capability to use cryptographic mechanisms to protect information at rest? If yes, please provide the encryption algorithm and strength in the comments section. | F15: No | G15: Not natively. That said, full server/disk encryption is possible | I15: Comment is required | K15: Comment is required

Sheet 17. System Data Integrity
A1: Control Question # | B1: NIST SP800-53 R4: Control # | C1: HIPAA CFR Control Reference(s) | D1: Control Name | E1: Security Questions: | F1: =Scope!$B$4 & " Response:" -> PeriCALM Tracings Fetal monitoring application Response: | G1: =Scope!$B$4 &" Comments:" -> PeriCALM Tracings Fetal monitoring application Comments: | H1: =Scope!$D$4 & " Response:" -> Response: | I1: =Scope!$D$4 & " Comments:" -> Comments: | J1: =Scope!$F$4 & " Response:" -> Response: | K1: =Scope!$F$4 & " Comments:" -> Comments:
A2: System and Information Integrity
A3: SI-1.1 | B3: SI-1 | C3: 164.312(c)(1) | D3: System and Information Integrity Policy and Procedures | E3: Do you have formally documented policies and procedures for System and Information Integrity? If yes, please attach. | F3: No | G3: Comment is required | I3: Comment is required | K3: Comment is required
A4: SI-2.1 | B4: SI-2 | D4: Flaw Remediation | E4: Are information system flaws identified, reported, and corrected? (I.e., are vulnerability scans performed and addressed?) | F4: No | G4: Customers regularly scan our application befor go-lives | I4: Comment is required | K4: Comment is required
A5: SI-2.2 | E5: Are software and firmware updates tested for effectiveness and potential side effects before installation? | F5: Yes | G5: Comment is required | I5: Comment is required | K5: Comment is required
A6: SI-2.3 | E6: Is flaw remediation incorporated into the organizational configuration management process? | F6: Yes | G6: When/if discovered, they are funneled into the Change Control process and based on priority//severity, assigned to a maintenance release or hot-fix | I6: Comment is required | K6: Comment is required

Sheet Override Control Env1
F1: Environment Scope Summary
F2: Service or Product? | G2: Data Types: | H2: Client Data Accessible via: | I2: Certifications | J2: Environment Access
F3: =IF(Scope!B6="Yes",_xlfn.CONCAT("Service ")&IF(Scope!B7="Yes",_xlfn.CONCAT("Product"),""),IF(Scope!B7="Yes",_xlfn.CONCAT("Product"),"Blank")) -> Product | G3: =IF(Scope!#REF!="Yes","PHI","No PHI") -> #REF! | H3: =IF(OR(Scope!B23="Yes",NOT(Scope!C23="")),"Workstation"&_xlfn.CONCAT(" ,",Scope!C23),"") -> Workstation ,The PeriCALM application is installed on workstation at the bedside and nursing stations. Data is communicated between workstations and server. Not data is cached or saved on the workstation. | I3: =IF(Scope!B40="Yes",_xlfn.CONCAT("SOC 1 Type 1 ")&IF(Scope!B41="Yes",_xlfn.CONCAT("SOC 1 Type 2"),""),IF(Scope!B41="Yes",_xlfn.CONCAT("SOC 1 Type 2"),"No SOC 1")) -> No SOC 1 | J3: =IF(Scope!B10="Yes",_xlfn.CONCAT("Remote Access Client Network ")&IF(Scope!B11="Yes",_xlfn.CONCAT("Onsite Network Access"),""),IF(Scope!B11="Yes",_xlfn.CONCAT("Onsite Network Access"),"")) -> Remote Access Client Network Onsite Network Access
F4: =IF(Scope!B6="Yes",Scope!C6,"")& " "&IF(Scope!B7="Yes",Scope!C7,"") | G4: =IF(Scope!B17="Yes","PII","No PII") -> PII | H4: =IF(OR(Scope!B25="Yes",NOT(Scope!#REF!="")),"Mobile Device"&_xlfn.CONCAT(" ,",Scope!#REF!),"") -> #REF! | I4: =IF(Scope!B42="Yes",_xlfn.CONCAT("SOC 2 Type 1 ")&IF(Scope!B43="Yes",_xlfn.CONCAT("SOC 2 Type 2"),""),IF(Scope!B43="Yes",_xlfn.CONCAT("SOC 2 Type 2"),"No SOC 2")) -> No SOC 2 | J4: =IF(Scope!B12="Yes",_xlfn.CONCAT("Access Client Infrastructure ")&IF(Scope!B13="Yes",_xlfn.CONCAT("Access Application/Database"),""),IF(Scope!B13="Yes",_xlfn.CONCAT("Access Application/Database"),"")) -> Access Application/Database
G5: =IF(Scope!B18="Yes","PCI","No PCI") -> No PCI | H5: =IF(OR(Scope!B27="Yes",NOT(Scope!C27="")),"Medical Device"&_xlfn.CONCAT(" ,",Scope!C27),"") -> Medical Device ,The system interfaces to fetal monitor to collect the fetal tracing, trasmit it to the main server which publishes it to all open client application instances on the network | I5: =IF(Scope!B44="Yes",_xlfn.CONCAT("SOC 3 ")&IF(Scope!B45="Yes",_xlfn.CONCAT("HITRUST"),""),IF(Scope!B45="Yes",_xlfn.CONCAT("HITRUST"),"")) | J5: =IF(Scope!B14="Yes",_xlfn.CONCAT("Receive Client Data ")&IF(Scope!B15="Yes",_xlfn.CONCAT("No Access"),""),IF(Scope!B15="Yes",_xlfn.CONCAT("No Access"),"")) -> Receive Client Data
G6: =IF(Scope!B20="Yes",_xlfn.CONCAT("Employee Information ")&IF(Scope!B21="Yes",_xlfn.CONCAT(" Proprietary Information")),IF(Scope!B21="Yes",_xlfn.CONCAT("Proprietary Information"),"No Employee or Proprietary Informaiton")) -> No Employee or Proprietary Informaiton | H6: =IF(OR(Scope!B28="Yes",NOT(Scope!C28="")),"Other"&_xlfn.CONCAT(" ,",Scope!C28),"") | I6: =IF(Scope!B46="Yes",_xlfn.CONCAT("PCI DSS ")&IF(Scope!B46="Yes",_xlfn.CONCAT("ISO 27001"),""),IF(Scope!B46="Yes",_xlfn.CONCAT("ISO 27001"),""))
I7: =IF(Scope!B48="Yes",_xlfn.CONCAT("FedRamp ")&IF(Scope!B49="Yes",_xlfn.CONCAT("HIPAA"),""),IF(Scope!B47="Yes",_xlfn.CONCAT("HIPAA"),""))
A8: Tier | B8: Client Tier | C8: Calc Tier | D8: Control Family | E8: Control Question # | F8: Control Name | G8: Security Question | H8: Comment | I8: Response | J8: Calc Response | K8: Override | L8: Final Response | M8: Reviewer Comments | N8: FindOverrideChanges | O8: Response: | P8: Comments/ Notes: | Q8: FinalResponse | R8: Overrides | S8: OverrideTier | T8: CheckOverrideChanges
A9: 3 | C9: =IF($B9="",$A9,$B9) -> 3 | D9: Access Controls | E9: AC-1.1 | F9: Access Control Policy and Procedures | G9: Are there formally documented policies and procedures for access control? If yes, please attach. | H9: ='1. Access Controls'!$G3 -> Comment is required | I9: ='1. Access Controls'!$F3 -> Yes | J9: =IF($I9="Yes","Adequate",IF($I9="No","Inadequate",IF($I9="Partial","Inadequate",IF($I9="N/A","Inadequate",IF(OR($I9="",$I9=0),"Blank","Error"))))) -> Adequate | K9: No Override | L9: =IF($K9="No Override",$J9,$K9) -> Adequate | N9: =IF($J9=$L9,"","***") | O9: =IF(OR($I9="",$I9=0),"",$I9) -> Yes | P9: =IF(OR($H9="",$H9=0),"",$H9) -> Comment is required | Q9: =$L9 -> Adequate | R9: =$K9 -> No Override | S9: =$C9 -> 3 | T9: =IF($L9=$Q9,"","***")
A10: 1 | C10: =IF($B10="",$A10,$B10) -> 1 | D10: Access Controls | E10: AC-3.1 | F10: Access Enforcement | G10: Does the information system verify the rights of a user to access the information system? (Access Control Lists, Group/Role membership?) If yes, detail how the access is enforced in the comment. | H10: ='1. Access Controls'!$G4 -> Access controlled is enforced by groups membership. An AD user must belong to an AD group that is identical by name to an internal PeriCALM group. An authenticated user that belong to such a group inherits its access rights. These rights are controlled by the customer application administrators where AD group membership is controlled by customer IT administrators. | I10: ='1. Access Controls'!$F4 -> Yes | J10: =IF($I10="Yes","Adequate",IF($I10="No","Inadequate",IF($I10="Partial","Inadequate",IF($I10="N/A","Inadequate",IF(OR($I10="",$I10=0),"Blank","Error"))))) -> Adequate | K10: No Override | L10: =IF($K10="No Override",$J10,$K10) -> Adequate | N10: =IF($J10=$L10,"","***") | O10: =IF(OR($I10="",$I10=0),"",$I10) -> Yes | P10: =IF(OR($H10="",$H10=0),"",$H10) -> Access controlled is enforced by groups membership. An AD user must belong to an AD group that is identical by name to an internal PeriCALM group. An authenticated user that belong to such a group inherits its access rights. These rights are controlled by the customer application administrators where AD group membership is controlled by customer IT administrators. | Q10: =$L10 -> Adequate | R10: =$K10 -> No Override | S10: =$C10 -> 1 | T10: =IF($L10=$Q10,"","***")
A11: 3 | C11: =IF($B11="",$A11,$B11) -> 3 | D11: Access Controls | E11: AC-3.2 | F11: Access Enforcement | G11: Does the information system support role-based account management and access controls (RBAC)? | H11: ='1. Access Controls'!$G5 -> Comment is required | I11: ='1. Access Controls'!$F5 -> Yes | J11: =IF($I11="Yes","Adequate",IF($I11="No","Inadequate",IF($I11="Partial","Inadequate",IF($I11="N/A","Inadequate",IF(OR($I11="",$I11=0),"Blank","Error"))))) -> Adequate | K11: No Override | L11: =IF($K11="No Override",$J11,$K11) -> Adequate | N11: =IF($J11=$L11,"","***") | O11: =IF(OR($I11="",$I11=0),"",$I11) -> Yes | P11: =IF(OR($H11="",$H11=0),"",$H11) -> Comment is required | Q11: =$L11 -> Adequate | R11: =$K11 -> No Override | S11: =$C11 -> 3 | T11: =IF($L11=$Q11,"","***")
A12: 4 | C12: =IF($B12="",$A12,$B12) -> 4 | D12: Access Controls | E12: AC-3.3 | F12: Access Enforcement | G12: If RBAC is supported, can a customer administrator create/customize unique roles and permissions. | H12: ='1. Access Controls'!$G6 -> Comment is required | I12: ='1. Access Controls'!$F6 -> Yes | J12: =IF($I12="Yes","Adequate",IF($I12="No","Inadequate",IF($I12="Partial","Inadequate",IF($I12="N/A","Inadequate",IF(OR($I12="",$I12=0),"Blank","Error"))))) -> Adequate | K12: No Override | L12: =IF($K12="No Override",$J12,$K12) -> Adequate | N12: =IF($J12=$L12,"","***") | O12: =IF(OR($I12="",$I12=0),"",$I12) -> Yes | P12: =IF(OR($H12="",$H12=0),"",$H12) -> Comment is required | Q12: =$L12 -> Adequate | R12: =$K12 -> No Override | S12: =$C12 -> 4 | T12: =IF($L12=$Q12,"","***")
A13: 2 | C13: =IF($B13="",$A13,$B13) -> 2 | D13: Access Controls | E13: AC-7.1 | F13: Unsuccessful Logon Attempts | G13: Is an account automatically locked out after a set amount of login attempts? If yes, please provide the number of failed attempts that trigger an account to be locked out, in the comments section. | H13: ='1. Access Controls'!$G7 -> Via AD authentication controls. | I13: ='1. Access Controls'!$F7 -> Yes | J13: =IF($I13="Yes","Adequate",IF($I13="No","Inadequate",IF($I13="Partial","Inadequate",IF($I13="N/A","Inadequate",IF(OR($I13="",$I13=0),"Blank","Error"))))) -> Adequate | K13: No Override | L13: =IF($K13="No Override",$J13,$K13) -> Adequate | N13: =IF($J13=$L13,"","***") | O13: =IF(OR($I13="",$I13=0),"",$I13) -> Yes | P13: =IF(OR($H13="",$H13=0),"",$H13) -> Via AD authentication controls. | Q13: =$L13 -> Adequate | R13: =$K13 -> No Override | S13: =$C13 -> 2 | T13: =IF($L13=$Q13,"","***")
A14: 4 | C14: =IF($B14="",$A14,$B14) -> 4 | D14: Access Controls | E14: AC-8.1 | F14: System Use Notification | G14: Is there a system use notification displayed before granting access that provides privacy and security notices? | H14: ='1. Access Controls'!$G8 -> Comment is required | I14: ='1. Access Controls'!$F8 -> No | J14: =IF($I14="Yes","Adequate",IF($I14="No","Inadequate",IF($I14="Partial","Inadequate",IF($I14="N/A","Inadequate",IF(OR($I14="",$I14=0),"Blank","Error"))))) -> Inadequate | K14: No Override | L14: =IF($K14="No Override",$J14,$K14) -> Inadequate | N14: =IF($J14=$L14,"","***") | O14: =IF(OR($I14="",$I14=0),"",$I14) -> No | P14: =IF(OR($H14="",$H14=0),"",$H14) -> Comment is required | Q14: =$L14 -> Inadequate | R14: =$K14 -> No Override | S14: =$C14 -> 4 | T14: =IF($L14=$Q14,"","***")
A15: 4 | C15: =IF($B15="",$A15,$B15) -> 4 | D15: Access Controls | E15: AC-9.1 | F15: Previous Logon Notification | G15: Does the system display the last user logon date and time to the user? | H15: ='1. Access Controls'!$G9 -> Comment is required | I15: ='1. Access Controls'!$F9 -> No | J15: =IF($I15="Yes","Adequate",IF($I15="No","Inadequate",IF($I15="Partial","Inadequate",IF($I15="N/A","Inadequate",IF(OR($I15="",$I15=0),"Blank","Error"))))) -> Inadequate | K15: No Override | L15: =IF($K15="No Override",$J15,$K15) -> Inadequate | N15: =IF($J15=$L15,"","***") | O15: =IF(OR($I15="",$I15=0),"",$I15) -> No | P15: =IF(OR($H15="",$H15=0),"",$H15) -> Comment is required | Q15: =$L15 -> Inadequate | R15: =$K15 -> No Override | S15: =$C15 -> 4 | T15: =IF($L15=$Q15,"","***")
A16: 4 | C16: =IF($B16="",$A16,$B16) -> 4 | D16: Access Controls | E16: AC-10.1 | F16: Concurrent Session Control | G16: Does the system limit the number of concurrent sessions for the user? | H16: ='1. Access Controls'!$G10 -> Comment is required | I16: ='1. Access Controls'!$F10 -> No | J16: =IF($I16="Yes","Adequate",IF($I16="No","Inadequate",IF($I16="Partial","Inadequate",IF($I16="N/A","Inadequate",IF(OR($I16="",$I16=0),"Blank","Error"))))) -> Inadequate | K16: No Override | L16: =IF($K16="No Override",$J16,$K16) -> Inadequate | N16: =IF($J16=$L16,"","***") | O16: =IF(OR($I16="",$I16=0),"",$I16) -> No | P16: =IF(OR($H16="",$H16=0),"",$H16) -> Comment is required | Q16: =$L16 -> Inadequate | R16: =$K16 -> No Override | S16: =$C16 -> 4 | T16: =IF($L16=$Q16,"","***")
A17: 2 | C17: =IF($B17="",$A17,$B17) -> 2 | D17: Access Controls | E17: AC-11.1 | F17: Session Lock | G17: Does the application/system have a session lock after a period of inactivity that requires a user to reauthenticate? | H17: ='1. Access Controls'!$G11 -> Comment is required | I17: ='1. Access Controls'!$F11 -> Yes | J17: =IF($I17="Yes","Adequate",IF($I17="No","Inadequate",IF($I17="Partial","Inadequate",IF($I17="N/A","Inadequate",IF(OR($I17="",$I17=0),"Blank","Error"))))) -> Adequate | K17: No Override | L17: =IF($K17="No Override",$J17,$K17) -> Adequate | N17: =IF($J17=$L17,"","***") | O17: =IF(OR($I17="",$I17=0),"",$I17) -> Yes | P17: =IF(OR($H17="",$H17=0),"",$H17) -> Comment is required | Q17: =$L17 -> Adequate | R17: =$K17 -> No Override | S17: =$C17 -> 2 | T17: =IF($L17=$Q17,"","***")
A18: 2 | C18: =IF($B18="",$A18,$B18) -> 2 | D18: Access Controls | E18: AC-12.1 | F18: Session Termination | G18: Does the application/system terminate the session after predefined circumstances? | H18: ='1. Access Controls'!$G12 -> Comment is required | I18: ='1. Access Controls'!$F12 -> No | J18: =IF($I18="Yes","Adequate",IF($I18="No","Inadequate",IF($I18="Partial","Inadequate",IF($I18="N/A","Inadequate",IF(OR($I18="",$I18=0),"Blank","Error"))))) -> Inadequate | K18: No Override | L18: =IF($K18="No Override",$J18,$K18) -> Inadequate | N18: =IF($J18=$L18,"","***") | O18: =IF(OR($I18="",$I18=0),"",$I18) -> No | P18: =IF(OR($H18="",$H18=0),"",$H18) -> Comment is required | Q18: =$L18 -> Inadequate | R18: =$K18 -> No Override | S18: =$C18 -> 2 | T18: =IF($L18=$Q18,"","***")
A19: 2 | C19: =IF($B19="",$A19,$B19) -> 2 | D19: Access Controls | E19: AC-14.1 | F19: Permitted Actions without Identification or Authentication | G19: Does the system prevent user actions that can be performed on the system without identification and authentication? | H19: ='1. Access Controls'!$G13 -> Comment is required | I19: ='1. Access Controls'!$F13 -> Yes | J19: =IF($I19="Yes","Adequate",IF($I19="No","Inadequate",IF($I19="Partial","Inadequate",IF($I19="N/A","Inadequate",IF(OR($I19="",$I19=0),"Blank","Error"))))) -> Adequate | K19: No Override | L19: =IF($K19="No Override",$J19,$K19) -> Adequate | N19: =IF($J19=$L19,"","***") | O19: =IF(OR($I19="",$I19=0),"",$I19) -> Yes | P19: =IF(OR($H19="",$H19=0),"",$H19) -> Comment is required | Q19: =$L19 -> Adequate | R19: =$K19 -> No Override | S19: =$C19 -> 2 | T19: =IF($L19=$Q19,"","***")
A20: 2 | C20: =IF($B20="",$A20,$B20) -> 2 | D20: Awareness and Training | E20: AT-1.1 | F20: Security Awareness and Training Policy and Procedures | G20: Are there formally documented procedures for security awareness and training for this information system? If yes, please attach. | H20: ='2. Awareness and Training'!$G3 -> Comment is required | I20: ='2. Awareness and Training'!$F3 -> Yes | J20: =IF($I20="Yes","Adequate",IF($I20="No","Inadequate",IF($I20="Partial","Inadequate",IF($I20="N/A","Inadequate",IF(OR($I20="",$I20=0),"Blank","Error"))))) -> Adequate | K20: No Override | L20: =IF($K20="No Override",$J20,$K20) -> Adequate | N20: =IF($J20=$L20,"","***") | O20: =IF(OR($I20="",$I20=0),"",$I20) -> Yes | P20: =IF(OR($H20="",$H20=0),"",$H20) -> Comment is required | Q20: =$L20 -> Adequate | R20: =$K20 -> No Override | S20: =$C20 -> 2 | T20: =IF($L20=$Q20,"","***")
A21: 2 | C21: =IF($B21="",$A21,$B21) -> 2 | D21: Awareness and Training | E21: AT-2.1 | F21: Security Awareness | G21: Is basic security awareness training performed for all personnel as a part of the onboarding process? | H21: ='2. Awareness and Training'!$G4 -> Comment is required | I21: ='2. Awareness and Training'!$F4 -> Yes | J21: =IF($I21="Yes","Adequate",IF($I21="No","Inadequate",IF($I21="Partial","Inadequate",IF($I21="N/A","Inadequate",IF(OR($I21="",$I21=0),"Blank","Error"))))) -> Adequate | K21: No Override | L21: =IF($K21="No Override",$J21,$K21) -> Adequate | N21: =IF($J21=$L21,"","***") | O21: =IF(OR($I21="",$I21=0),"",$I21) -> Yes | P21: =IF(OR($H21="",$H21=0),"",$H21) -> Comment is required | Q21: =$L21 -> Adequate | R21: =$K21 -> No Override | S21: =$C21 -> 2 | T21: =IF($L21=$Q21,"","***")
A22: 2 | C22: =IF($B22="",$A22,$B22) -> 2 | D22: Awareness and Training | E22: AT-2.2 | F22: Security Awareness | G22: Is it periodically performed for all users? | H22: ='2. Awareness and Training'!$G5 -> Customer responsibility to train their internal administrators/super-users to periodically train end-users | I22: ='2. Awareness and Training'!$F5 -> Yes | J22: =IF($I22="Yes","Adequate",IF($I22="No","Inadequate",IF($I22="Partial","Inadequate",IF($I22="N/A","Inadequate",IF(OR($I22="",$I22=0),"Blank","Error"))))) -> Adequate | K22: No Override | L22: =IF($K22="No Override",$J22,$K22) -> Adequate | N22: =IF($J22=$L22,"","***") | O22: =IF(OR($I22="",$I22=0),"",$I22) -> Yes | P22: =IF(OR($H22="",$H22=0),"",$H22) -> Customer responsibility to train their internal administrators/super-users to periodically train end-users | Q22: =$L22 -> Adequate | R22: =$K22 -> No Override | S22: =$C22 -> 2 | T22: =IF($L22=$Q22,"","***")
A23: 2 | C23: =IF($B23="",$A23,$B23) -> 2 | D23: Awareness and Training | E23: AT-3.1 | F23: Role-Based Security Training | G23: Is there role-based security training for personnel with assigned security roles and responsibilities for this information system before access is granted and when required by information system changes? | H23: ='2. Awareness and Training'!$G6 -> All security related topics are cover during initial training and user guides | I23: ='2. Awareness and Training'!$F6 -> No | J23: =IF($I23="Yes","Adequate",IF($I23="No","Inadequate",IF($I23="Partial","Inadequate",IF($I23="N/A","Inadequate",IF(OR($I23="",$I23=0),"Blank","Error"))))) -> Inadequate | K23: No Override | L23: =IF($K23="No Override",$J23,$K23) -> Inadequate | N23: =IF($J23=$L23,"","***") | O23: =IF(OR($I23="",$I23=0),"",$I23) -> No | P23: =IF(OR($H23="",$H23=0),"",$H23) -> All security related topics are cover during initial training and user guides | Q23: =$L23 -> Inadequate | R23: =$K23 -> No Override | S23: =$C23 -> 2 | T23: =IF($L23=$Q23,"","***")
A24: 2 | C24: =IF($B24="",$A24,$B24) -> 2 | D24: Awareness and Training | E24: AT-4.1 | F24: Security Training Records | G24: Do you document and monitor information system security training activities for individuals? | H24: ='2. Awareness and Training'!$G7 -> Comment is required | I24: ='2. Awareness and Training'!$F7 -> No | J24: =IF($I24="Yes","Adequate",IF($I24="No","Inadequate",IF($I24="Partial","Inadequate",IF($I24="N/A","Inadequate",IF(OR($I24="",$I24=0),"Blank","Error"))))) -> Inadequate | K24: No Override | L24: =IF($K24="No Override",$J24,$K24) -> Inadequate | N24: =IF($J24=$L24,"","***") | O24: =IF(OR($I24="",$I24=0),"",$I24) -> No | P24: =IF(OR($H24="",$H24=0),"",$H24) -> Comment is required | Q24: =$L24 -> Inadequate | R24: =$K24 -> No Override | S24: =$C24 -> 2 | T24: =IF($L24=$Q24,"","***")
A25: 2 | C25: =IF($B25="",$A25,$B25) -> 2 | D25: Audit and Accountability | E25: AU-2.1 | F25: Audit Events | G25: Is the information system actively auditing events such as access to patient information, login/logoffs, account creation, etc.? If yes, please detail the events captured in the comment. | H25: ='3. Audit and Accountability'!$G3 -> * logon/logoff * Access from station (hostname) * Screens access by user * All data changes (old values, new values, user, dataTime) All the above include username and dataTime | I25: ='3. Audit and Accountability'!$F3 -> Yes | J25: =IF($I25="Yes","Adequate",IF($I25="No","Inadequate",IF($I25="Partial","Inadequate",IF($I25="N/A","Inadequate",IF(OR($I25="",$I25=0),"Blank","Error"))))) -> Adequate | K25: No Override | L25: =IF($K25="No Override",$J25,$K25) -> Adequate | N25: =IF($J25=$L25,"","***") | O25: =IF(OR($I25="",$I25=0),"",$I25) -> Yes | P25: =IF(OR($H25="",$H25=0),"",$H25) -> * logon/logoff * Access from station (hostname) * Screens access by user * All data changes (old values, new values, user, dataTime) All the above include username and dataTime | Q25: =$L25 -> Adequate | R25: =$K25 -> No Override | S25: =$C25 -> 2 | T25: =IF($L25=$Q25,"","***")
A26: 2 | C26: =IF($B26="",$A26,$B26) -> 2 | D26: Audit and Accountability | E26: AU-2.2 | F26: Audit Events | G26: Are the audit logs captured sufficient for incident response and system and user performance/investigation? | H26: ='3. Audit and Accountability'!$G4 -> Comment is required | I26: ='3. Audit and Accountability'!$F4 -> Yes | J26: =IF($I26="Yes","Adequate",IF($I26="No","Inadequate",IF($I26="Partial","Inadequate",IF($I26="N/A","Inadequate",IF(OR($I26="",$I26=0),"Blank","Error"))))) -> Adequate | K26: No Override | L26: =IF($K26="No Override",$J26,$K26) -> Adequate | N26: =IF($J26=$L26,"","***") | O26: =IF(OR($I26="",$I26=0),"",$I26) -> Yes | P26: =IF(OR($H26="",$H26=0),"",$H26) -> Comment is required | Q26: =$L26 -> Adequate | R26: =$K26 -> No Override | S26: =$C26 -> 2 | T26: =IF($L26=$Q26,"","***")
A27: 2 | C27: =IF($B27="",$A27,$B27) -> 2 | D27: Audit and Accountability | E27: AU-3.1 | F27: Content of Audit Records | G27: Does the system create audit records that contain sufficient information to, at a minimum, establish what type of event occurred, when the event occurred, where the event occurred, the source of the event, the outcome (success or failure) of the event, and the identity of any user/subject associated with the event? | H27: ='3. Audit and Accountability'!$G5 -> Comment is required | I27: ='3. Audit and Accountability'!$F5 -> Yes | J27: =IF($I27="Yes","Adequate",IF($I27="No","Inadequate",IF($I27="Partial","Inadequate",IF($I27="N/A","Inadequate",IF(OR($I27="",$I27=0),"Blank","Error"))))) -> Adequate | K27: No Override | L27: =IF($K27="No Override",$J27,$K27) -> Adequate | N27: =IF($J27=$L27,"","***") | O27: =IF(OR($I27="",$I27=0),"",$I27) -> Yes | P27: =IF(OR($H27="",$H27=0),"",$H27) -> Comment is required | Q27: =$L27 -> Adequate | R27: =$K27 -> No Override | S27: =$C27 -> 2 | T27: =IF($L27=$Q27,"","***")
A28: 3 | C28: =IF($B28="",$A28,$B28) -> 3 | D28: Audit and Accountability | E28: AU-5.1 | F28: Response to Audit Processing Failures | G28: Does the information system generate an alert that notifies the team in the event of an audit processing failure? | H28: ='3. Audit and Accountability'!$G6 -> Comment is required | I28: ='3. Audit and Accountability'!$F6 -> No | J28: =IF($I28="Yes","Adequate",IF($I28="No","Inadequate",IF($I28="Partial","Inadequate",IF($I28="N/A","Inadequate",IF(OR($I28="",$I28=0),"Blank","Error"))))) -> Inadequate | K28: No Override | L28: =IF($K28="No Override",$J28,$K28) -> Inadequate | N28: =IF($J28=$L28,"","***") | O28: =IF(OR($I28="",$I28=0),"",$I28) -> No | P28: =IF(OR($H28="",$H28=0),"",$H28) -> Comment is required | Q28: =$L28 -> Inadequate | R28: =$K28 -> No Override | S28: =$C28 -> 3 | T28: =IF($L28=$Q28,"","***")
A29: 3 | C29: =IF($B29="",$A29,$B29) -> 3 | D29: Audit and Accountability | E29: AU-7.1 | F29: Audit Reduction and Report Generation | G29: Does the information system provide the capability to generate customizable audit reports? | H29: ='3. Audit and Accountability'!$G7 -> Comment is required | I29: ='3. Audit and Accountability'!$F7 -> No | J29: =IF($I29="Yes","Adequate",IF($I29="No","Inadequate",IF($I29="Partial","Inadequate",IF($I29="N/A","Inadequate",IF(OR($I29="",$I29=0),"Blank","Error"))))) -> Inadequate | K29: No Override | L29: =IF($K29="No Override",$J29,$K29) -> Inadequate | N29: =IF($J29=$L29,"","***") | O29: =IF(OR($I29="",$I29=0),"",$I29) -> No | P29: =IF(OR($H29="",$H29=0),"",$H29) -> Comment is required | Q29: =$L29 -> Inadequate | R29: =$K29 -> No Override | S29: =$C29 -> 3 | T29: =IF($L29=$Q29,"","***")
A30: 4 | C30: =IF($B30="",$A30,$B30) -> 4 | D30: Audit and Accountability | E30: AU-7.2 | F30: Audit Reduction and Report Generation | G30: Does the generation of an audit report alter the original content or time stamp of the audit record? | H30: ='3. Audit and Accountability'!$G8 -> Comment is required | I30: ='3. Audit and Accountability'!$F8 -> No | J30: =IF($I30="Yes","Inadequate",IF($I30="No","Adequate",IF($I30="Partial","Inadequate",IF($I30="N/A","Inadequate",IF(OR($I30="",$I30=0),"Blank","Error"))))) -> Adequate | K30: No Override | L30: =IF($K30="No Override",$J30,$K30) -> Adequate | N30: =IF($J30=$L30,"","***") | O30: =IF(OR($I30="",$I30=0),"",$I30) -> No | P30: =IF(OR($H30="",$H30=0),"",$H30) -> Comment is required | Q30: =$L30 -> Adequate | R30: =$K30 -> No Override | S30: =$C30 -> 4 | T30: =IF($L30=$Q30,"","***")
A31: 2 | C31: =IF($B31="",$A31,$B31) -> 2 | D31: Audit and Accountability | E31: AU-8.1 | F31: Time Stamps | G31: Are the audit logs time stamped? (Date and Time) | H31: ='3. Audit and Accountability'!$G9 -> Comment is required | I31: ='3. Audit and Accountability'!$F9 -> Yes | J31: =IF($I31="Yes","Adequate",IF($I31="No","Inadequate",IF($I31="Partial","Inadequate",IF($I31="N/A","Inadequate",IF(OR($I31="",$I31=0),"Blank","Error"))))) -> Adequate | K31: No Override | L31: =IF($K31="No Override",$J31,$K31) -> Adequate | N31: =IF($J31=$L31,"","***") | O31: =IF(OR($I31="",$I31=0),"",$I31) -> Yes | P31: =IF(OR($H31="",$H31=0),"",$H31) -> Comment is required | Q31: =$L31 -> Adequate | R31: =$K31 -> No Override | S31: =$C31 -> 2 | T31: =IF($L31=$Q31,"","***")
A32: 2 | C32: =IF($B32="",$A32,$B32) -> 2 | D32: Audit and Accountability | E32: AU-9.1 | F32: Protection of Audit Information | G32: Does the system/application protect audit information from unauthorized access, modification, and deletion? | H32: ='3. Audit and Accountability'!$G10 -> Comment is required | I32: ='3. Audit and Accountability'!$F10 -> Yes | J32: =IF($I32="Yes","Adequate",IF($I32="No","Inadequate",IF($I32="Partial","Inadequate",IF($I32="N/A","Inadequate",IF(OR($I32="",$I32=0),"Blank","Error"))))) -> Adequate | K32: No Override | L32: =IF($K32="No Override",$J32,$K32) -> Adequate | N32: =IF($J32=$L32,"","***") | O32: =IF(OR($I32="",$I32=0),"",$I32) -> Yes | P32: =IF(OR($H32="",$H32=0),"",$H32) -> Comment is required | Q32: =$L32 -> Adequate | R32: =$K32 -> No Override | S32: =$C32 -> 2 | T32: =IF($L32=$Q32,"","***")
A33: 3 | C33: =IF($B33="",$A33,$B33) -> 3 | D33: Audit and Accountability | E33: AU-12.1 | F33: Audit Generation | G33: Can the information system be configured to select which auditable events are captured in the audit log? | H33: ='3. Audit and Accountability'!$G11 -> Comment is required | I33: ='3. Audit and Accountability'!$F11 -> No | J33: =IF($I33="Yes","Adequate",IF($I33="No","Inadequate",IF($I33="Partial","Inadequate",IF($I33="N/A","Inadequate",IF(OR($I33="",$I33=0),"Blank","Error"))))) -> Inadequate | K33: No Override | L33: =IF($K33="No Override",$J33,$K33) -> Inadequate | N33: =IF($J33=$L33,"","***") | O33: =IF(OR($I33="",$I33=0),"",$I33) -> No | P33: =IF(OR($H33="",$H33=0),"",$H33) -> Comment is required | Q33: =$L33 -> Inadequate | R33: =$K33 -> No Override | S33: =$C33 -> 3 | T33: =IF($L33=$Q33,"","***")
A34: 4 | C34: =IF($B34="",$A34,$B34) -> 4 | D34: Configuration Management | E34: CM-1.1 | F34: Configuration Management Policy and Procedures | G34: Are there documented procedures to outline who/when and how the system/application is configured? If yes, please attach | H34: ='5. Configuration'!$G3 -> Comment is required | I34: ='5. Configuration'!$F3 -> Yes | J34: =IF($I34="Yes","Adequate",IF($I34="No","Inadequate",IF($I34="Partial","Inadequate",IF($I34="N/A","Inadequate",IF(OR($I34="",$I34=0),"Blank","Error"))))) -> Adequate | K34: No Override | L34: =IF($K34="No Override",$J34,$K34) -> Adequate | N34: =IF($J34=$L34,"","***") | O34: =IF(OR($I34="",$I34=0),"",$I34) -> Yes | P34: =IF(OR($H34="",$H34=0),"",$H34) -> Comment is required | Q34: =$L34 -> Adequate | R34: =$K34 -> No Override | S34: =$C34 -> 4 | T34: =IF($L34=$Q34,"","***")
A35: 1 | C35: =IF($B35="",$A35,$B35) -> 1 | D35: Configuration Management | E35: CM-2.1 | F35: Baseline Configuration | G35: Do you have a current configuration baseline documented for the information system? (The baseline configuration is a documented, up-to-date specification to which the information system is built.) | H35: ='5. Configuration'!$G4 -> Configuration is a site/customer specific. The system comes with some defaults (ex: everything is logged) but other configurations like AD/LDAP servers for authentication, interfaces, bed-configurations are all done according to customer needs. | I35: ='5. Configuration'!$F4 -> No | J35: =IF($I35="Yes","Adequate",IF($I35="No","Inadequate",IF($I35="Partial","Inadequate",IF($I35="N/A","Inadequate",IF(OR($I35="",$I35=0),"Blank","Error"))))) -> Inadequate | K35: No Override | L35: =IF($K35="No Override",$J35,$K35) -> Inadequate | N35: =IF($J35=$L35,"","***") | O35: =IF(OR($I35="",$I35=0),"",$I35) -> No | P35: =IF(OR($H35="",$H35=0),"",$H35) -> Configuration is a site/customer specific. The system comes with some defaults (ex: everything is logged) but other configurations like AD/LDAP servers for authentication, interfaces, bed-configurations are all done according to customer needs. | Q35: =$L35 -> Inadequate | R35: =$K35 -> No Override | S35: =$C35 -> 1 | T35: =IF($L35=$Q35,"","***")
A36: 1 | C36: =IF($B36="",$A36,$B36) -> 1 | D36: Configuration Management | E36: CM-3.1 | F36: Configuration Change Control | G36: Are types of changes to the information system that are configuration-controlled defined? | H36: ='5. Configuration'!$G5 -> All changes to the system are coordinated with the csustomer and require customer approval. | I36: ='5. Configuration'!$F5 -> No | J36: =IF($I36="Yes","Adequate",IF($I36="No","Inadequate",IF($I36="Partial","Inadequate",IF($I36="N/A","Inadequate",IF(OR($I36="",$I36=0),"Blank","Error"))))) -> Inadequate | K36: No Override | L36: =IF($K36="No Override",$J36,$K36) -> Inadequate | N36: =IF($J36=$L36,"","***") | O36: =IF(OR($I36="",$I36=0),"",$I36) -> No | P36: =IF(OR($H36="",$H36=0),"",$H36) -> All changes to the system are coordinated with the csustomer and require customer approval. | Q36: =$L36 -> Inadequate | R36: =$K36 -> No Override | S36: =$C36 -> 1 | T36: =IF($L36=$Q36,"","***")
A37: 1 | C37: =IF($B37="",$A37,$B37) -> 1 | D37: Configuration Management | E37: CM-3.2 | F37: Configuration Change Control | G37: Does the organization review proposed configuration-controlled changes to the information system, using defined security impact analyses? | H37: ='5. Configuration'!$G6 -> Comment is required | I37: ='5. Configuration'!$F6 -> Yes | J37: =IF($I37="Yes","Adequate",IF($I37="No","Inadequate",IF($I37="Partial","Inadequate",IF($I37="N/A","Inadequate",IF(OR($I37="",$I37=0),"Blank","Error"))))) -> Adequate | K37: No Override | L37: =IF($K37="No Override",$J37,$K37) -> Adequate | N37: =IF($J37=$L37,"","***") | O37: =IF(OR($I37="",$I37=0),"",$I37) -> Yes | P37: =IF(OR($H37="",$H37=0),"",$H37) -> Comment is required | Q37: =$L37 -> Adequate | R37: =$K37 -> No Override | S37: =$C37 -> 1 | T37: =IF($L37=$Q37,"","***")
A38: 1 | C38: =IF($B38="",$A38,$B38) -> 1 | D38: Configuration Management | E38: CM-3.3 | F38: Configuration Change Control | G38: Are all configuration changes adequately documented? | H38: ='5. Configuration'!$G7 -> Always coordinated with the customer | I38: ='5. Configuration'!$F7 -> Yes | J38: =IF($I38="Yes","Adequate",IF($I38="No","Inadequate",IF($I38="Partial","Inadequate",IF($I38="N/A","Inadequate",IF(OR($I38="",$I38=0),"Blank","Error"))))) -> Adequate | K38: No Override | L38: =IF($K38="No Override",$J38,$K38) -> Adequate | N38: =IF($J38=$L38,"","***") | O38: =IF(OR($I38="",$I38=0),"",$I38) -> Yes | P38: =IF(OR($H38="",$H38=0),"",$H38) -> Always coordinated with the customer | Q38: =$L38 -> Adequate | R38: =$K38 -> No Override | S38: =$C38 -> 1 | T38: =IF($L38=$Q38,"","***")
A39: 1 | C39: =IF($B39="",$A39,$B39) -> 1 | D39: Configuration Management | E39: CM-3.4 | F39: Configuration Change Control | G39: Are all approved configuration controls implemented timely? | H39: ='5. Configuration'!$G8 -> Always coordinated with the customer | I39: ='5. Configuration'!$F8 -> Yes | J39: =IF($I39="Yes","Adequate",IF($I39="No","Inadequate",IF($I39="Partial","Inadequate",IF($I39="N/A","Inadequate",IF(OR($I39="",$I39=0),"Blank","Error"))))) -> Adequate | K39: No Override | L39: =IF($K39="No Override",$J39,$K39) -> Adequate | N39: =IF($J39=$L39,"","***") | O39: =IF(OR($I39="",$I39=0),"",$I39) -> Yes | P39: =IF(OR($H39="",$H39=0),"",$H39) -> Always coordinated with the customer | Q39: =$L39 -> Adequate | R39: =$K39 -> No Override | S39: =$C39 -> 1 | T39: =IF($L39=$Q39,"","***")
A40: 1 | C40: =IF($B40="",$A40,$B40) -> 1 | D40: Configuration Management | E40: CM-3.5 | F40: Configuration Change Control | G40: Does the organization retain records of configuration controlled changes? | H40: ='5. Configuration'!$G9 -> Records are maintained in our corporate ticketing system or as part of formal project(s) to add/change aspects of the system | I40: ='5. Configuration'!$F9 -> Yes | J40: =IF($I40="Yes","Adequate",IF($I40="No","Inadequate",IF($I40="Partial","Inadequate",IF($I40="N/A","Inadequate",IF(OR($I40="",$I40=0),"Blank","Error"))))) -> Adequate | K40: No Override | L40: =IF($K40="No Override",$J40,$K40) -> Adequate | N40: =IF($J40=$L40,"","***") | O40: =IF(OR($I40="",$I40=0),"",$I40) -> Yes | P40: =IF(OR($H40="",$H40=0),"",$H40) -> Records are maintained in our corporate ticketing system or as part of formal project(s) to add/change aspects of the system | Q40: =$L40 -> Adequate | R40: =$K40 -> No Override | S40: =$C40 -> 1 | T40: =IF($L40=$Q40,"","***")
A41: 1 | C41: =IF($B41="",$A41,$B41) -> 1 | D41: Configuration Management | E41: CM-3.6 | F41: Configuration Change Control | G41: Are there auditing and monitoring activities implemented to assess the configuration-controlled changes? | H41: ='5. Configuration'!$G10 -> Some changes have auditable controls associated, others do not. For example, adding a mapped field from HL7. The new field will show in the audit trail but the action of adding the field in the mapping tables in the DB do not. | I41: ='5. Configuration'!$F10 -> Partial | J41: =IF($I41="Yes","Adequate",IF($I41="No","Inadequate",IF($I41="Partial","Inadequate",IF($I41="N/A","Inadequate",IF(OR($I41="",$I41=0),"Blank","Error"))))) -> Inadequate | K41: No Override | L41: =IF($K41="No Override",$J41,$K41) -> Inadequate | N41: =IF($J41=$L41,"","***") | O41: =IF(OR($I41="",$I41=0),"",$I41) -> Partial | P41: =IF(OR($H41="",$H41=0),"",$H41) -> Some changes have auditable controls associated, others do not. For example, adding a mapped field from HL7. The new field will show in the audit trail but the action of adding the field in the mapping tables in the DB do not. | Q41: =$L41 -> Inadequate | R41: =$K41 -> No Override | S41: =$C41 -> 1 | T41: =IF($L41=$Q41,"","***")
A42: 3 | C42: =IF($B42="",$A42,$B42) -> 3 | D42: Configuration Management | E42: CM-4.1 | F42: Security Impact Analysis | G42: Do you analyze changes to the information system to determine potential security impacts prior to change implementation? | H42: ='5. Configuration'!$G11 -> 0 | I42: ='5. Configuration'!$F11 -> No | J42: =IF($I42="Yes","Adequate",IF($I42="No","Inadequate",IF($I42="Partial","Inadequate",IF($I42="N/A","Inadequate",IF(OR($I42="",$I42=0),"Blank","Error"))))) -> Inadequate | K42: No Override | L42: =IF($K42="No Override",$J42,$K42) -> Inadequate | N42: =IF($J42=$L42,"","***") | O42: =IF(OR($I42="",$I42=0),"",$I42) -> No | P42: =IF(OR($H42="",$H42=0),"",$H42) | Q42: =$L42 -> Inadequate | R42: =$K42 -> No Override | S42: =$C42 -> 3 | T42: =IF($L42=$Q42,"","***")
A43: 1 | C43: =IF($B43="",$A43,$B43) -> 1 | D43: Configuration Management | E43: CM-6.1 | F43: Configuration Settings | G43: Have all the configuration settings been documented that reflect the most restrictive mode consistent with operational requirements? | H43: ='5. Configuration'!$G12 -> common best practices are used with the limited controls offered by PeriCALM Tracings | I43: ='5. Configuration'!$F12 -> No | J43: =IF($I43="Yes","Adequate",IF($I43="No","Inadequate",IF($I43="Partial","Inadequate",IF($I43="N/A","Inadequate",IF(OR($I43="",$I43=0),"Blank","Error"))))) -> Inadequate | K43: No Override | L43: =IF($K43="No Override",$J43,$K43) -> Inadequate | N43: =IF($J43=$L43,"","***") | O43: =IF(OR($I43="",$I43=0),"",$I43) -> No | P43: =IF(OR($H43="",$H43=0),"",$H43) -> common best practices are used with the limited controls offered by PeriCALM Tracings | Q43: =$L43 -> Inadequate | R43: =$K43 -> No Override | S43: =$C43 -> 1 | T43: =IF($L43=$Q43,"","***")
A44: 1 | C44: =IF($B44="",$A44,$B44) -> 1 | D44: Configuration Management | E44: CM-6.2 | F44: Configuration Settings | G44: Is there any automated or manual monitoring of configuration changes? (e.g. Tripwire, manual checklists) | H44: ='5. Configuration'!$G13 -> Comment is required | I44: ='5. Configuration'!$F13 -> No | J44: =IF($I44="Yes","Adequate",IF($I44="No","Inadequate",IF($I44="Partial","Inadequate",IF($I44="N/A","Inadequate",IF(OR($I44="",$I44=0),"Blank","Error"))))) -> Inadequate | K44: No Override | L44: =IF($K44="No Override",$J44,$K44) -> Inadequate | N44: =IF($J44=$L44,"","***") | O44: =IF(OR($I44="",$I44=0),"",$I44) -> No | P44: =IF(OR($H44="",$H44=0),"",$H44) -> Comment is required | Q44: =$L44 -> Inadequate | R44: =$K44 -> No Override | S44: =$C44 -> 1 | T44: =IF($L44=$Q44,"","***")
A45: 1 | C45: =IF($B45="",$A45,$B45) -> 1 | D45: Configuration Management | E45: CM-6.3 | F45: Configuration Settings | G45: Do you document and approve deviations from the established configuration settings? | H45: ='5. Configuration'!$G14 -> Comment is required | I45: ='5. Configuration'!$F14 -> No | J45: =IF($I45="Yes","Adequate",IF($I45="No","Inadequate",IF($I45="Partial","Inadequate",IF($I45="N/A","Inadequate",IF(OR($I45="",$I45=0),"Blank","Error"))))) -> Inadequate | K45: No Override | L45: =IF($K45="No Override",$J45,$K45) -> Inadequate | N45: =IF($J45=$L45,"","***") | O45: =IF(OR($I45="",$I45=0),"",$I45) -> No | P45: =IF(OR($H45="",$H45=0),"",$H45) -> Comment is required | Q45: =$L45 -> Inadequate | R45: =$K45 -> No Override | S45: =$C45 -> 1 | T45: =IF($L45=$Q45,"","***")
... A58: 2 | C58: =IF($B58="",$A58,$B58) -> 2 | D58: Configuration Management | E58: CM-14.2 | F58: Patch Classification | G58: Do you implement patches categorized as "critical" within 72 hours of patch release? | H58: ='5. Configuration'!$G27 -> Case by case basis | I58: ='5. Configuration'!$F27 -> Partial | J58: =IF($I58="Yes","Adequate",IF($I58="No","Inadequate",IF($I58="Partial","Inadequate",IF($I58="N/A","Inadequate",IF(OR($I58="",$I58=0),"Blank","Error"))))) -> Inadequate | K58: No Override | L58: =IF($K58="No Override",$J58,$K58) -> Inadequate | N58: =IF($J58=$L58,"","***") | O58: =IF(OR($I58="",$I58=0),"",$I58) -> Partial | P58: =IF(OR($H58="",$H58=0),"",$H58) -> Case by case basis | Q58: =$L58 -> Inadequate | R58: =$K58 -> No Override | S58: =$C58 -> 2 | T58: =IF($L58=$Q58,"","***")
A59: 4 | C59: =IF($B59="",$A59,$B59) -> 4 | D59: Authentication & Authorization | E59: IA-1.1 | F59: Identification and Authentication Policy and Procedures | G59: Does the application/system use managed LDAP services for identification and authentication? If no, detail in the comment column what is used. | H59: ='7. Authentication&Authorization'!$G3 -> Customer responsibility to provide. PeriCALM Tracings supports authentication via LDAP | I59: ='7. Authentication&Authorization'!$F3 -> Yes | J59: =IF($I59="Yes","Adequate",IF($I59="No","Adequate",IF($I59="Partial","Inadequate",IF($I59="N/A","Inadequate",IF(OR($I59="",$I59=0),"Blank","Error"))))) -> Adequate | K59: No Override | L59: =IF($K59="No Override",$J59,$K59) -> Adequate | N59: =IF($J59=$L59,"","***") | O59: =IF(OR($I59="",$I59=0),"",$I59) -> Yes | P59: =IF(OR($H59="",$H59=0),"",$H59) -> Customer responsibility to provide. PeriCALM Tracings supports authentication via LDAP | Q59: =$L59 -> Adequate | R59: =$K59 -> No Override | S59: =$C59 -> 4 | T59: =IF($L59=$Q59,"","***")
A60: 4 | C60: =IF($B60="",$A60,$B60) -> 4 | D60: Authentication & Authorization | E60: IA-2.1 | F60: Identification and Authentication (Organizational Users) | G60: Does the information system use multifactor authentication for privileged or non-privileged access? (Uses at least two of: what you have, what you know, what you are. E.g., tokens, passwords, biometrics.) | H60: ='7. Authentication&Authorization'!$G4 -> Comment is required | I60: ='7. Authentication&Authorization'!$F4 -> No | J60: =IF($I60="Yes","Adequate",IF($I60="No","Inadequate",IF($I60="Partial","Inadequate",IF($I60="N/A","Inadequate",IF(OR($I60="",$I60=0),"Blank","Error"))))) -> Inadequate | K60: No Override | L60: =IF($K60="No Override",$J60,$K60) -> Inadequate | N60: =IF($J60=$L60,"","***") | O60: =IF(OR($I60="",$I60=0),"",$I60) -> No | P60: =IF(OR($H60="",$H60=0),"",$H60) -> Comment is required | Q60: =$L60 -> Inadequate | R60: =$K60 -> No Override | S60: =$C60 -> 4 | T60: =IF($L60=$Q60,"","***")
A61: 2 | C61: =IF($B61="",$A61,$B61) -> 2 | D61: Authentication & Authorization | E61: IA-3.1 | F61: Device Identification and Authentication | G61: Does the information system uniquely identify and authenticate devices before establishing a connection? (E.g., MAC, TCP/IP, IEEE 802.1x) | H61: ='7. Authentication&Authorization'!$G5 -> All stations must be configured for access on the server. Identification is done by hostname (DNS) | I61: ='7. Authentication&Authorization'!$F5 -> Yes | J61: =IF($I61="Yes","Adequate",IF($I61="No","Inadequate",IF($I61="Partial","Inadequate",IF($I61="N/A","Inadequate",IF(OR($I61="",$I61=0),"Blank","Error"))))) -> Adequate | K61: No Override | L61: =IF($K61="No Override",$J61,$K61) -> Adequate | N61: =IF($J61=$L61,"","***") | O61: =IF(OR($I61="",$I61=0),"",$I61) -> Yes | P61: =IF(OR($H61="",$H61=0),"",$H61) -> All stations must be configured for access on the server. Identification is done by hostname (DNS) | Q61: =$L61 -> Adequate | R61: =$K61 -> No Override | S61: =$C61 -> 2 | T61: =IF($L61=$Q61,"","***")
A62: 3 | C62: =IF($B62="",$A62,$B62) -> 3 | D62: Authentication & Authorization | E62: IA-4.2 | F62: Identifier Management | G62: Does the application/system prevent reuse of user or device identifiers? | H62: ='7. Authentication&Authorization'!$G6 -> Comment is required | I62: ='7. Authentication&Authorization'!$F6 -> Yes | J62: =IF($I62="Yes","Adequate",IF($I62="No","Inadequate",IF($I62="Partial","Inadequate",IF($I62="N/A","Inadequate",IF(OR($I62="",$I62=0),"Blank","Error"))))) -> Adequate | K62: No Override | L62: =IF($K62="No Override",$J62,$K62) -> Adequate | N62: =IF($J62=$L62,"","***") | O62: =IF(OR($I62="",$I62=0),"",$I62) -> Yes | P62: =IF(OR($H62="",$H62=0),"",$H62) -> Comment is required | Q62: =$L62 -> Adequate | R62: =$K62 -> No Override | S62: =$C62 -> 3 | T62: =IF($L62=$Q62,"","***")
A63: 2 | C63: =IF($B63="",$A63,$B63) -> 2 | D63: Authentication & Authorization | E63: IA-4.3 | F63: Identifier Management | G63: Does the application/system disable the user or device account after a pre-defined period of inactivity? | H63: ='7. Authentication&Authorization'!$G7 -> Comment is required | I63: ='7. Authentication&Authorization'!$F7 -> Yes | J63: =IF($I63="Yes","Adequate",IF($I63="No","Inadequate",IF($I63="Partial","Inadequate",IF($I63="N/A","Inadequate",IF(OR($I63="",$I63=0),"Blank","Error"))))) -> Adequate | K63: No Override | L63: =IF($K63="No Override",$J63,$K63) -> Adequate | N63: =IF($J63=$L63,"","***") | O63: =IF(OR($I63="",$I63=0),"",$I63) -> Yes | P63: =IF(OR($H63="",$H63=0),"",$H63) -> Comment is required | Q63: =$L63 -> Adequate | R63: =$K63 -> No Override | S63: =$C63 -> 2 | T63: =IF($L63=$Q63,"","***")
A64: 3 | C64: =IF($B64="",$A64,$B64) -> 3 | D64: Authentication & Authorization | E64: IA-5.1 | F64: Authenticator Management | G64: Does the application/system comply with the password complexity as outlined in implemented policies? | H64: ='7. Authentication&Authorization'!$G8 -> AD controlled | I64: ='7. Authentication&Authorization'!$F8 -> N/A | J64: =IF($I64="Yes","Adequate",IF($I64="No","Inadequate",IF($I64="Partial","Inadequate",IF($I64="N/A","Inadequate",IF(OR($I64="",$I64=0),"Blank","Error"))))) -> Inadequate | K64: No Override | L64: =IF($K64="No Override",$J64,$K64) -> Inadequate | N64: =IF($J64=$L64,"","***") | O64: =IF(OR($I64="",$I64=0),"",$I64) -> N/A | P64: =IF(OR($H64="",$H64=0),"",$H64) -> AD controlled | Q64: =$L64 -> Inadequate | R64: =$K64 -> No Override | S64: =$C64 -> 3 | T64: =IF($L64=$Q64,"","***")
A65: 1 | C65: =IF($B65="",$A65,$B65) -> 1 | D65: Authentication & Authorization | E65: IA-5.2 | F65: Authenticator Management | G65: Does information system force the End User to comply with the following password requirements regarding complexity, length and change? - Passwords at least 8 characters in length. - Passwords contain the following: - Mixed case alpha characters - at least one numeric digit - at least one non-alphanumeric character - Current password may not be reused - Do current passwords expire every 90 days? - Are passwords stored in an encrypted format? | H65: ='7. Authentication&Authorization'!$G9 -> AD controlled | I65: ='7. Authentication&Authorization'!$F9 -> N/A | J65: =IF($I65="Yes","Adequate",IF($I65="No","Inadequate",IF($I65="Partial","Inadequate",IF($I65="N/A","Inadequate",IF(OR($I65="",$I65=0),"Blank","Error"))))) -> Inadequate | K65: No Override | L65: =IF($K65="No Override",$J65,$K65) -> Inadequate | N65: =IF($J65=$L65,"","***") | O65: =IF(OR($I65="",$I65=0),"",$I65) -> N/A | P65: =IF(OR($H65="",$H65=0),"",$H65) -> AD controlled | Q65: =$L65 -> Inadequate | R65: =$K65 -> No Override | S65: =$C65 -> 1 | T65: =IF($L65=$Q65,"","***")
A66: 1 | C66: =IF($B66="",$A66,$B66) -> 1 | D66: Authentication & Authorization | E66: IA-5.3 | F66: Authenticator Management | G66: Are the passwords encrypted within the information system when stored or transmitted? | H66: ='7. Authentication&Authorization'!$G10 -> Comment is required | I66: ='7. Authentication&Authorization'!$F10 -> Yes | J66: =IF($I66="Yes","Adequate",IF($I66="No","Inadequate",IF($I66="Partial","Inadequate",IF($I66="N/A","Inadequate",IF(OR($I66="",$I66=0),"Blank","Error"))))) -> Adequate | K66: No Override | L66: =IF($K66="No Override",$J66,$K66) -> Adequate | N66: =IF($J66=$L66,"","***") | O66: =IF(OR($I66="",$I66=0),"",$I66) -> Yes | P66: =IF(OR($H66="",$H66=0),"",$H66) -> Comment is required | Q66: =$L66 -> Adequate | R66: =$K66 -> No Override | S66: =$C66 -> 1 | T66: =IF($L66=$Q66,"","***")
A67: 3 | C67: =IF($B67="",$A67,$B67) -> 3 | D67: Authentication & Authorization | E67: IA-5.7 | F67: Authenticator Management | G67: Is authenticator content protected from unauthorized disclosure and modification? | H67: ='7. Authentication&Authorization'!$G11 -> Comment is required | I67: ='7. Authentication&Authorization'!$F11 -> Yes | J67: =IF($I67="Yes","Adequate",IF($I67="No","Inadequate",IF($I67="Partial","Inadequate",IF($I67="N/A","Inadequate",IF(OR($I67="",$I67=0),"Blank","Error"))))) -> Adequate | K67: No Override | L67: =IF($K67="No Override",$J67,$K67) -> Adequate | N67: =IF($J67=$L67,"","***") | O67: =IF(OR($I67="",$I67=0),"",$I67) -> Yes | P67: =IF(OR($H67="",$H67=0),"",$H67) -> Comment is required | Q67: =$L67 -> Adequate | R67: =$K67 -> No Override | S67: =$C67 -> 3 | T67: =IF($L67=$Q67,"","***")
A68: 3 | C68: =IF($B68="",$A68,$B68) -> 3 | D68: Authentication & Authorization | E68: IA-5.9 | F68: Authenticator Management | G68: Is token-based authentication required? | H68: ='7. Authentication&Authorization'!$G12 -> AD controlled | I68: ='7. Authentication&Authorization'!$F12 -> Yes | J68: =IF($I68="Yes","Adequate",IF($I68="No","Inadequate",IF($I68="Partial","Inadequate",IF($I68="N/A","Inadequate",IF(OR($I68="",$I68=0),"Blank","Error"))))) -> Adequate | K68: No Override | L68: =IF($K68="No Override",$J68,$K68) -> Adequate | N68: =IF($J68=$L68,"","***") | O68: =IF(OR($I68="",$I68=0),"",$I68) -> Yes | P68: =IF(OR($H68="",$H68=0),"",$H68) -> AD controlled | Q68: =$L68 -> Adequate | R68: =$K68 -> No Override | S68: =$C68 -> 3 | T68: =IF($L68=$Q68,"","***")
A69: 4 | C69: =IF($B69="",$A69,$B69) -> 4 | D69: Authentication & Authorization | E69: IA-6.1 | F69: Authenticator Feedback | G69: Does the information system obscure the authenticator/password during the authentication process? | H69: ='7. Authentication&Authorization'!$G13 -> Comment is required | I69: ='7. Authentication&Authorization'!$F13 -> Yes | J69: =IF($I69="Yes","Adequate",IF($I69="No","Inadequate",IF($I69="Partial","Inadequate",IF($I69="N/A","Inadequate",IF(OR($I69="",$I69=0),"Blank","Error"))))) -> Adequate | K69: No Override | L69: =IF($K69="No Override",$J69,$K69) -> Adequate | N69: =IF($J69=$L69,"","***") | O69: =IF(OR($I69="",$I69=0),"",$I69) -> Yes | P69: =IF(OR($H69="",$H69=0),"",$H69) -> Comment is required | Q69: =$L69 -> Adequate | R69: =$K69 -> No Override | S69: =$C69 -> 4 | T69: =IF($L69=$Q69,"","***")
A70: 4 | C70: =IF($B70="",$A70,$B70) -> 4 | D70: Authentication & Authorization | E70: IA-7.1 | F70: Cryptographic Module Authentication | G70: Does the information system use mechanisms for authentication to a cryptographic module? (This control is used for mostly operating systems and appliances used to encrypt something.) | H70: ='7. Authentication&Authorization'!$G14 -> Comment is required | I70: ='7. Authentication&Authorization'!$F14 -> No | J70: =IF($I70="Yes","Adequate",IF($I70="No","Inadequate",IF($I70="Partial","Inadequate",IF($I70="N/A","Inadequate",IF(OR($I70="",$I70=0),"Blank","Error"))))) -> Inadequate | K70: No Override | L70: =IF($K70="No Override",$J70,$K70) -> Inadequate | N70: =IF($J70=$L70,"","***") | O70: =IF(OR($I70="",$I70=0),"",$I70) -> No | P70: =IF(OR($H70="",$H70=0),"",$H70) -> Comment is required | Q70: =$L70 -> Inadequate | R70: =$K70 -> No Override | S70: =$C70 -> 4 | T70: =IF($L70=$Q70,"","***")
A71: 1 | C71: =IF($B71="",$A71,$B71) -> 1 | D71: Incident Response | E71: IR-1.1 | F71: Incident Response Policies and Procedures | G71: Are there formally documented policies and procedures for Incident Response? If yes, please attach. | H71: ='8. Incident Response'!$G3 -> Comment is required | I71: ='8. Incident Response'!$F3 -> Yes | J71: =IF($I71="Yes","Adequate",IF($I71="No","Inadequate",IF($I71="Partial","Inadequate",IF($I71="N/A","Inadequate",IF(OR($I71="",$I71=0),"Blank","Error"))))) -> Adequate | K71: No Override | L71: =IF($K71="No Override",$J71,$K71) -> Adequate | N71: =IF($J71=$L71,"","***") | O71: =IF(OR($I71="",$I71=0),"",$I71) -> Yes | P71: =IF(OR($H71="",$H71=0),"",$H71) -> Comment is required | Q71: =$L71 -> Adequate | R71: =$K71 -> No Override | S71: =$C71 -> 1 | T71: =IF($L71=$Q71,"","***")
A72: 2 | C72: =IF($B72="",$A72,$B72) -> 2 | D72: Incident Response | E72: IR-2.1 | F72: Incident Response Training | G72: Are staff provided with incident response training? | H72: ='8. Incident Response'!$G4 -> Comment is required | I72: ='8. Incident Response'!$F4 -> Yes | J72: =IF($I72="Yes","Adequate",IF($I72="No","Inadequate",IF($I72="Partial","Inadequate",IF($I72="N/A","Inadequate",IF(OR($I72="",$I72=0),"Blank","Error"))))) -> Adequate | K72: No Override | L72: =IF($K72="No Override",$J72,$K72) -> Adequate | N72: =IF($J72=$L72,"","***") | O72: =IF(OR($I72="",$I72=0),"",$I72) -> Yes | P72: =IF(OR($H72="",$H72=0),"",$H72) -> Comment is required | Q72: =$L72 -> Adequate | R72: =$K72 -> No Override | S72: =$C72 -> 2 | T72: =IF($L72=$Q72,"","***")
A73: 2 | C73: =IF($B73="",$A73,$B73) -> 2 | D73: Incident Response | E73: IR-2.2 | F73: Incident Response Training | G73: Is incident response training unique based on the role of the individual? | H73: ='8. Incident Response'!$G5 -> Comment is required | I73: ='8. Incident Response'!$F5 -> Yes | J73: =IF($I73="Yes","Adequate",IF($I73="No","Inadequate",IF($I73="Partial","Inadequate",IF($I73="N/A","Inadequate",IF(OR($I73="",$I73=0),"Blank","Error"))))) -> Adequate | K73: No Override | L73: =IF($K73="No Override",$J73,$K73) -> Adequate | N73: =IF($J73=$L73,"","***") | O73: =IF(OR($I73="",$I73=0),"",$I73) -> Yes | P73: =IF(OR($H73="",$H73=0),"",$H73) -> Comment is required | Q73: =$L73 -> Adequate | R73: =$K73 -> No Override | S73: =$C73 -> 2 | T73: =IF($L73=$Q73,"","***")
A74: 2 | C74: =IF($B74="",$A74,$B74) -> 2 | D74: Incident Response | E74: IR-3.1 | F74: Incident Response Testing and Exercises | G74: Are incident response tests conducted? | H74: ='8. Incident Response'!$G6 -> Comment is required | I74: ='8. Incident Response'!$F6 -> No | J74: =IF($I74="Yes","Adequate",IF($I74="No","Inadequate",IF($I74="Partial","Inadequate",IF($I74="N/A","Inadequate",IF(OR($I74="",$I74=0),"Blank","Error"))))) -> Inadequate | K74: No Override | L74: =IF($K74="No Override",$J74,$K74) -> Inadequate | N74: =IF($J74=$L74,"","***") | O74: =IF(OR($I74="",$I74=0),"",$I74) -> No | P74: =IF(OR($H74="",$H74=0),"",$H74) -> Comment is required | Q74: =$L74 -> Inadequate | R74: =$K74 -> No Override | S74: =$C74 -> 2 | T74: =IF($L74=$Q74,"","***")
A75: 2 | C75: =IF($B75="",$A75,$B75) -> 2 | D75: Incident Response | E75: IR-3.2 | F75: Incident Response Testing and Exercises | G75: Are the incident response test results analyzed? | H75: ='8. Incident Response'!$G7 -> Comment is required | I75: ='8. Incident Response'!$F7 -> No | J75: =IF($I75="Yes","Adequate",IF($I75="No","Inadequate",IF($I75="Partial","Inadequate",IF($I75="N/A","Inadequate",IF(OR($I75="",$I75=0),"Blank","Error"))))) -> Inadequate | K75: No Override | L75: =IF($K75="No Override",$J75,$K75) -> Inadequate | N75: =IF($J75=$L75,"","***") | O75: =IF(OR($I75="",$I75=0),"",$I75) -> No | P75: =IF(OR($H75="",$H75=0),"",$H75) -> Comment is required | Q75: =$L75 -> Inadequate | R75: =$K75 -> No Override | S75: =$C75 -> 2 | T75: =IF($L75=$Q75,"","***")
A76: 1 | C76: =IF($B76="",$A76,$B76) -> 1 | D76: Incident Response | E76: IR-4.1 | F76: Incident Handling | G76: Is there an incident handling process | H76: ='8. Incident Response'!$G8 -> Comment is required | I76: ='8. Incident Response'!$F8 -> Yes | J76: =IF($I76="Yes","Adequate",IF($I76="No","Inadequate",IF($I76="Partial","Inadequate",IF($I76="N/A","Inadequate",IF(OR($I76="",$I76=0),"Blank","Error"))))) -> Adequate | K76: No Override | L76: =IF($K76="No Override",$J76,$K76) -> Adequate | N76: =IF($J76=$L76,"","***") | O76: =IF(OR($I76="",$I76=0),"",$I76) -> Yes | P76: =IF(OR($H76="",$H76=0),"",$H76) -> Comment is required | Q76: =$L76 -> Adequate | R76: =$K76 -> No Override | S76: =$C76 -> 1 | T76: =IF($L76=$Q76,"","***")
A77: 1 | C77: =IF($B77="",$A77,$B77) -> 1 | D77: Incident Response | E77: IR-5.1 | F77: Incident Monitoring | G77: Are security incidents tracked and documented? | H77: ='8. Incident Response'!$G9 -> Comment is required | I77: ='8. Incident Response'!$F9 -> Yes | J77: =IF($I77="Yes","Adequate",IF($I77="No","Inadequate",IF($I77="Partial","Inadequate",IF($I77="N/A","Inadequate",IF(OR($I77="",$I77=0),"Blank","Error"))))) -> Adequate | K77: No Override | L77: =IF($K77="No Override",$J77,$K77) -> Adequate | N77: =IF($J77=$L77,"","***") | O77: =IF(OR($I77="",$I77=0),"",$I77) -> Yes | P77: =IF(OR($H77="",$H77=0),"",$H77) -> Comment is required | Q77: =$L77 -> Adequate | R77: =$K77 -> No Override | S77: =$C77 -> 1 | T77: =IF($L77=$Q77,"","***")
A78: 1 | C78: =IF($B78="",$A78,$B78) -> 1 | D78: Incident Response | E78: IR-6.1 | F78: Incident Reporting | G78: Are security incidents timely reported to appropriate personnel/ government authorities? | H78: ='8. Incident Response'!$G10 -> Comment is required | I78: ='8. Incident Response'!$F10 -> Yes | J78: =IF($I78="Yes","Adequate",IF($I78="No","Inadequate",IF($I78="Partial","Inadequate",IF($I78="N/A","Inadequate",IF(OR($I78="",$I78=0),"Blank","Error"))))) -> Adequate | K78: No Override | L78: =IF($K78="No Override",$J78,$K78) -> Adequate | N78: =IF($J78=$L78,"","***") | O78: =IF(OR($I78="",$I78=0),"",$I78) -> Yes | P78: =IF(OR($H78="",$H78=0),"",$H78) -> Comment is required | Q78: =$L78 -> Adequate | R78: =$K78 -> No Override | S78: =$C78 -> 1 | T78: =IF($L78=$Q78,"","***")
A79: 3 | C79: =IF($B79="",$A79,$B79) -> 3 | D79: Incident Response | E79: IR-7.1 | F79: Incident Response Assistance | G79: Are incident response resources used outside of the incident response team? | H79: ='8. Incident Response'!$G11 -> If required. Case by case basis. | I79: ='8. Incident Response'!$F11 -> Yes | J79: =IF($I79="Yes","Adequate",IF($I79="No","Adequate",IF($I79="Partial","Inadequate",IF($I79="N/A","Inadequate",IF(OR($I79="",$I79=0),"Blank","Error"))))) -> Adequate | K79: No Override | L79: =IF($K79="No Override",$J79,$K79) -> Adequate | N79: =IF($J79=$L79,"","***") | O79: =IF(OR($I79="",$I79=0),"",$I79) -> Yes | P79: =IF(OR($H79="",$H79=0),"",$H79) -> If required. Case by case basis. | Q79: =$L79 -> Adequate | R79: =$K79 -> No Override | S79: =$C79 -> 3 | T79: =IF($L79=$Q79,"","***")
A80: 1 | C80: =IF($B80="",$A80,$B80) -> 1 | D80: Incident Response | E80: IR-8.1 | F80: Incident Response Plan | G80: Is there a comprehensive Incident Response Plan? If so, please attach. | H80: ='8. Incident Response'!$G12 -> see internal policy | I80: ='8. Incident Response'!$F12 -> Yes | J80: =IF($I80="Yes","Adequate",IF($I80="No","Inadequate",IF($I80="Partial","Inadequate",IF($I80="N/A","Inadequate",IF(OR($I80="",$I80=0),"Blank","Error"))))) -> Adequate | K80: No Override | L80: =IF($K80="No Override",$J80,$K80) -> Adequate | N80: =IF($J80=$L80,"","***") | O80: =IF(OR($I80="",$I80=0),"",$I80) -> Yes | P80: =IF(OR($H80="",$H80=0),"",$H80) -> see internal policy | Q80: =$L80 -> Adequate | R80: =$K80 -> No Override | S80: =$C80 -> 1 | T80: =IF($L80=$Q80,"","***")
A81: 3 | C81: =IF($B81="",$A81,$B81) -> 3 | D81: Incident Response | E81: IR-9.1 | F81: Information Spillage Response | G81: Does the organization respond to information spillage appropriately and timely? | H81: ='8. Incident Response'!$G13 -> Comment is required | I81: ='8. Incident Response'!$F13 -> Yes | J81: =IF($I81="Yes","Adequate",IF($I81="No","Inadequate",IF($I81="Partial","Inadequate",IF($I81="N/A","Inadequate",IF(OR($I81="",$I81=0),"Blank","Error"))))) -> Adequate | K81: No Override | L81: =IF($K81="No Override",$J81,$K81) -> Adequate | N81: =IF($J81=$L81,"","***") | O81: =IF(OR($I81="",$I81=0),"",$I81) -> Yes | P81: =IF(OR($H81="",$H81=0),"",$H81) -> Comment is required | Q81: =$L81 -> Adequate | R81: =$K81 -> No Override | S81: =$C81 -> 3 | T81: =IF($L81=$Q81,"","***")
A82: 4 | C82: =IF($B82="",$A82,$B82) -> 4 | D82: Maintenance | E82: MA-1.1 | F82: System Maintenance Policy and Procedures | G82: Are there formally documented policies and procedures for Maintenance? If yes, please attach. | H82: ='9. Maintenance'!$G3 -> PeriGen does not provide propriatary internal QMS documents | I82: ='9. Maintenance'!$F3 -> Yes | J82: =IF($I82="Yes","Adequate",IF($I82="No","Inadequate",IF($I82="Partial","Inadequate",IF($I82="N/A","Inadequate",IF(OR($I82="",$I82=0),"Blank","Error"))))) -> Adequate | K82: No Override | L82: =IF($K82="No Override",$J82,$K82) -> Adequate | N82: =IF($J82=$L82,"","***") | O82: =IF(OR($I82="",$I82=0),"",$I82) -> Yes | P82: =IF(OR($H82="",$H82=0),"",$H82) -> PeriGen does not provide propriatary internal QMS documents | Q82: =$L82 -> Adequate | R82: =$K82 -> No Override | S82: =$C82 -> 4 | T82: =IF($L82=$Q82,"","***")
A83: 4 | C83: =IF($B83="",$A83,$B83) -> 4 | D83: Maintenance | E83: MA-2.5 | F83: Controlled Maintenance | G83: Do you check all potentially impacted security controls to verify that the controls are still functioning properly following maintenance or repair actions? (E.g., verify that audit logs are still functioning properly, user level of access is still appropriate.) | H83: ='9. Maintenance'!$G4 -> For internal access control to access customer sites - Yes. Regular checks of PeriCALM system is the responsibility of the customer. | I83: ='9. Maintenance'!$F4 -> Partial | J83: =IF($I83="Yes","Adequate",IF($I83="No","Inadequate",IF($I83="Partial","Inadequate",IF($I83="N/A","Inadequate",IF(OR($I83="",$I83=0),"Blank","Error"))))) -> Inadequate | K83: No Override | L83: =IF($K83="No Override",$J83,$K83) -> Inadequate | N83: =IF($J83=$L83,"","***") | O83: =IF(OR($I83="",$I83=0),"",$I83) -> Partial | P83: =IF(OR($H83="",$H83=0),"",$H83) -> For internal access control to access customer sites - Yes. Regular checks of PeriCALM system is the responsibility of the customer. | Q83: =$L83 -> Inadequate | R83: =$K83 -> No Override | S83: =$C83 -> 4 | T83: =IF($L83=$Q83,"","***")
A84: 4 | C84: =IF($B84="",$A84,$B84) -> 4 | D84: Maintenance | E84: MA-3.1 | F84: Maintenance Tools | G84: Does the organization approve, control and monitor information system maintenance tools? | H84: ='9. Maintenance'!$G5 -> Yes as part of QA/QC process of product releases. That said, controls on customer provided servers is the responsibility of the customer. | I84: ='9. Maintenance'!$F5 -> Yes | J84: =IF($I84="Yes","Adequate",IF($I84="No","Inadequate",IF($I84="Partial","Inadequate",IF($I84="N/A","Inadequate",IF(OR($I84="",$I84=0),"Blank","Error"))))) -> Adequate | K84: No Override | L84: =IF($K84="No Override",$J84,$K84) -> Adequate | N84: =IF($J84=$L84,"","***") | O84: =IF(OR($I84="",$I84=0),"",$I84) -> Yes | P84: =IF(OR($H84="",$H84=0),"",$H84) -> Yes as part of QA/QC process of product releases. That said, controls on customer provided servers is the responsibility of the customer. | Q84: =$L84 -> Adequate | R84: =$K84 -> No Override | S84: =$C84 -> 4 | T84: =IF($L84=$Q84,"","***")
A85: 4 | C85: =IF($B85="",$A85,$B85) -> 4 | D85: Maintenance | E85: MA-4.1 | F85: Nonlocal Maintenance | G85: Is any nonlocal maintenance and diagnostic activity performed on the information system (such as across the network, either internal or external, using terminal services/RDP)? | H85: ='9. Maintenance'!$G6 -> Comment is required | I85: ='9. Maintenance'!$F6 -> Yes | J85: =IF(AND($I85="Yes",$I86="Yes",$I87="Yes",$I88="Yes",$I89="Yes"),"Adequate",IF(AND($I85="Yes",OR(NOT($I86="Yes"),NOT($I87="Yes"),NOT($I88="Yes"),NOT($I89="Yes"))),"Inadequate",IF($I85="No","N/A",IF($I85="Partial","Inadequate",IF($I85="N/A","N/A",IF(OR($I85="",$I85=0),"Blank","Error")))))) -> Adequate | K85: No Override | L85: =IF($K85="No Override",$J85,$K85) -> Adequate | N85: =IF($J85=$L85,"","***") | O85: =IF(OR($I85="",$I85=0),"",$I85) -> Yes | P85: =IF(OR($H85="",$H85=0),"",$H85) -> Comment is required | Q85: =$L85 -> Adequate | R85: =$K85 -> No Override | S85: =$C85 -> 4 | T85: =IF($L85=$Q85,"","***")
A86: 1 | C86: =IF($B86="",$A86,$B86) -> 1 | D86: Maintenance | E86: MA-4.2 | F86: Nonlocal Maintenance | G86: Are all nonlocal maintenance and diagnostic activities approved and monitored? | H86: ='9. Maintenance'!$G7 -> Since we provide 24/7/365 support, out help desk team along with more senior technical analysts have access to the site remotely to resolve/troubleshoot and system problem. No specific approval is needed other than the original authorization of approved resources to access remote customer sites via SecureLink. | I86: ='9. Maintenance'!$F7 -> Yes | J86: =IF(OR($I85="N/A",$I85="No"),"N/A",IF($I86="Yes","Adequate",IF($I86="No","Inadequate",IF($I86="Partial","Inadequate",IF(AND($I86="N/A",NOT($I85="No"),NOT($I85="N/A")),"Inadequate",IF(OR($I86="",$I86=0),"Blank","Error")))))) -> Adequate | K86: No Override | L86: =IF($K86="No Override",$J86,$K86) -> Adequate | N86: =IF($J86=$L86,"","***") | O86: =IF(OR($I86="",$I86=0),"",$I86) -> Yes | P86: =IF(OR($H86="",$H86=0),"",$H86) -> Since we provide 24/7/365 support, out help desk team along with more senior technical analysts have access to the site remotely to resolve/troubleshoot and system problem. No specific approval is needed other than the original authorization of approved resources to access remote customer sites via SecureLink. | Q86: =$L86 -> Adequate | R86: =$K86 -> No Override | S86: =$C86 -> 1 | T86: =IF($L86=$Q86,"","***")
A87: 1 | C87: =IF($B87="",$A87,$B87) -> 1 | D87: Maintenance | E87: MA-4.3 | F87: Nonlocal Maintenance | G87: Are strong authenticators/passwords used in the establishment of nonlocal maintenance and diagnostic sessions? | H87: ='9. Maintenance'!$G8 -> Comment is required | I87: ='9. Maintenance'!$F8 -> Yes | J87: =IF(OR($I85="N/A",$I85="No"),"N/A",IF($I87="Yes","Adequate",IF($I87="No","Inadequate",IF($I87="Partial","Inadequate",IF(AND($I87="N/A",NOT($I85="No"),NOT($I85="N/A")),"Inadequate",IF(OR($I87="",$I87=0),"Blank","Error")))))) -> Adequate | K87: No Override | L87: =IF($K87="No Override",$J87,$K87) -> Adequate | N87: =IF($J87=$L87,"","***") | O87: =IF(OR($I87="",$I87=0),"",$I87) -> Yes | P87: =IF(OR($H87="",$H87=0),"",$H87) -> Comment is required | Q87: =$L87 -> Adequate | R87: =$K87 -> No Override | S87: =$C87 -> 1 | T87: =IF($L87=$Q87,"","***")
A88: 1 | C88: =IF($B88="",$A88,$B88) -> 1 | D88: Maintenance | E88: MA-4.4 | F88: Nonlocal Maintenance | G88: Do you maintain records for nonlocal maintenance and diagnostic activities? | H88: ='9. Maintenance'!$G9 -> Only Audit logs or access via SecureLink | I88: ='9. Maintenance'!$F9 -> Yes | J88: =IF(OR($I85="N/A",$I85="No"),"N/A",IF($I88="Yes","Adequate",IF($I88="No","Inadequate",IF($I88="Partial","Inadequate",IF(AND($I88="N/A",NOT($I85="No"),NOT($I85="N/A")),"Inadequate",IF(OR($I88="",$I88=0),"Blank","Error")))))) -> Adequate | K88: No Override | L88: =IF($K88="No Override",$J88,$K88) -> Adequate | N88: =IF($J88=$L88,"","***") | O88: =IF(OR($I88="",$I88=0),"",$I88) -> Yes | P88: =IF(OR($H88="",$H88=0),"",$H88) -> Only Audit logs or access via SecureLink | Q88: =$L88 -> Adequate | R88: =$K88 -> No Override | S88: =$C88 -> 1 | T88: =IF($L88=$Q88,"","***")
A89: 1 | C89: =IF($B89="",$A89,$B89) -> 1 | D89: Maintenance | E89: MA-4.5 | F89: Nonlocal Maintenance | G89: Are the sessions and network connections terminated after the nonlocal maintenance has been completed? | H89: ='9. Maintenance'!$G10 -> Comment is required | I89: ='9. Maintenance'!$F10 -> Yes | J89: =IF(OR($I85="N/A",$I85="No"),"N/A",IF($I89="Yes","Adequate",IF($I89="No","Inadequate",IF($I89="Partial","Inadequate",IF(AND($I89="N/A",NOT($I85="No"),NOT($I85="N/A")),"Inadequate",IF(OR($I89="",$I89=0),"Blank","Error")))))) -> Adequate | K89: No Override | L89: =IF($K89="No Override",$J89,$K89) -> Adequate | N89: =IF($J89=$L89,"","***") | O89: =IF(OR($I89="",$I89=0),"",$I89) -> Yes | P89: =IF(OR($H89="",$H89=0),"",$H89) -> Comment is required | Q89: =$L89 -> Adequate | R89: =$K89 -> No Override | S89: =$C89 -> 1 | T89: =IF($L89=$Q89,"","***")
A90: 4 | C90: =IF($B90="",$A90,$B90) -> 4 | D90: Maintenance | E90: MA-5.1 | F90: Maintenance Personnel | G90: Do you authorize and maintain a list of authorized maintenance personnel? | H90: ='9. Maintenance'!$G11 -> Access to hospital is goverend by individual account / profile in SecureLink. | I90: ='9. Maintenance'!$F11 -> Yes | J90: =IF($I90="Yes","Adequate",IF($I90="No","Inadequate",IF($I90="Partial","Inadequate",IF($I90="N/A","Inadequate",IF(OR($I90="",$I90=0),"Blank","Error"))))) -> Adequate | K90: No Override | L90: =IF($K90="No Override",$J90,$K90) -> Adequate | N90: =IF($J90=$L90,"","***") | O90: =IF(OR($I90="",$I90=0),"",$I90) -> Yes | P90: =IF(OR($H90="",$H90=0),"",$H90) -> Access to hospital is goverend by individual account / profile in SecureLink. | Q90: =$L90 -> Adequate | R90: =$K90 -> No Override | S90: =$C90 -> 4 | T90: =IF($L90=$Q90,"","***")
A91: 4 | C91: =IF($B91="",$A91,$B91) -> 4 | D91: Maintenance | E91: MA-5.2 | F91: Maintenance Personnel | G91: Do you ensure that personnel performing maintenance of the information system have the required access authorizations? | H91: ='9. Maintenance'!$G12 -> Comment is required | I91: ='9. Maintenance'!$F12 -> Yes | J91: =IF($I91="Yes","Adequate",IF($I91="No","Inadequate",IF($I91="Partial","Inadequate",IF($I91="N/A","Inadequate",IF(OR($I91="",$I91=0),"Blank","Error"))))) -> Adequate | K91: No Override | L91: =IF($K91="No Override",$J91,$K91) -> Adequate | N91: =IF($J91=$L91,"","***") | O91: =IF(OR($I91="",$I91=0),"",$I91) -> Yes | P91: =IF(OR($H91="",$H91=0),"",$H91) -> Comment is required | Q91: =$L91 -> Adequate | R91: =$K91 -> No Override | S91: =$C91 -> 4 | T91: =IF($L91=$Q91,"","***")
A92: 4 | C92: =IF($B92="",$A92,$B92) -> 4 | D92: Personnel Security | E92: PS-1.1 | F92: Personnel Security Policies and Procedures | G92: Are there formally documented policies and procedures for Personnel Security? If yes, please attach. | H92: ='13. Personnel Security'!$G3 -> 0 | I92: ='13. Personnel Security'!$F3 -> Yes | J92: =IF($I92="Yes","Adequate",IF($I92="No","Inadequate",IF($I92="Partial","Inadequate",IF($I92="N/A","Inadequate",IF(OR($I92="",$I92=0),"Blank","Error"))))) -> Adequate | K92: No Override | L92: =IF($K92="No Override",$J92,$K92) -> Adequate | N92: =IF($J92=$L92,"","***") | O92: =IF(OR($I92="",$I92=0),"",$I92) -> Yes | P92: =IF(OR($H92="",$H92=0),"",$H92) | Q92: =$L92 -> Adequate | R92: =$K92 -> No Override | S92: =$C92 -> 4 | T92: =IF($L92=$Q92,"","***")
A93: 4 | C93: =IF($B93="",$A93,$B93) -> 4 | D93: Personnel Security | E93: PS-2.1 | F93: Position Risk Designation | G93: Does the organization assign risk designations to all positions? | H93: ='13. Personnel Security'!$G4 -> 0 | I93: ='13. Personnel Security'!$F4 -> No | J93: =IF($I93="Yes","Adequate",IF($I93="No","Inadequate",IF($I93="Partial","Inadequate",IF($I93="N/A","Inadequate",IF(OR($I93="",$I93=0),"Blank","Error"))))) -> Inadequate | K93: No Override | L93: =IF($K93="No Override",$J93,$K93) -> Inadequate | N93: =IF($J93=$L93,"","***") | O93: =IF(OR($I93="",$I93=0),"",$I93) -> No | P93: =IF(OR($H93="",$H93=0),"",$H93) | Q93: =$L93 -> Inadequate | R93: =$K93 -> No Override | S93: =$C93 -> 4 | T93: =IF($L93=$Q93,"","***")
A94: 4 | C94: =IF($B94="",$A94,$B94) -> 4 | D94: Personnel Security | E94: PS-2.2 | F94: Position Risk Designation | G94: Does the organization establish screening criteria for individuals filling those positions? | H94: ='13. Personnel Security'!$G5 -> All employees are screened during job interviews | I94: ='13. Personnel Security'!$F5 -> Yes | J94: =IF($I94="Yes","Adequate",IF($I94="No","Inadequate",IF($I94="Partial","Inadequate",IF($I94="N/A","Inadequate",IF(OR($I94="",$I94=0),"Blank","Error"))))) -> Adequate | K94: No Override | L94: =IF($K94="No Override",$J94,$K94) -> Adequate | N94: =IF($J94=$L94,"","***") | O94: =IF(OR($I94="",$I94=0),"",$I94) -> Yes | P94: =IF(OR($H94="",$H94=0),"",$H94) -> All employees are screened during job interviews | Q94: =$L94 -> Adequate | R94: =$K94 -> No Override | S94: =$C94 -> 4 | T94: =IF($L94=$Q94,"","***")
A95: 4 | C95: =IF($B95="",$A95,$B95) -> 4 | D95: Personnel Security | E95: PS-2.3 | F95: Position Risk Designation | G95: Does the organization review and revise position risk designations at least every three years? | H95: ='13. Personnel Security'!$G6 -> 0 | I95: ='13. Personnel Security'!$F6 -> No | J95: =IF($I95="Yes","Adequate",IF($I95="No","Inadequate",IF($I95="Partial","Inadequate",IF($I95="N/A","Inadequate",IF(OR($I95="",$I95=0),"Blank","Error"))))) -> Inadequate | K95: No Override | L95: =IF($K95="No Override",$J95,$K95) -> Inadequate | N95: =IF($J95=$L95,"","***") | O95: =IF(OR($I95="",$I95=0),"",$I95) -> No | P95: =IF(OR($H95="",$H95=0),"",$H95) | Q95: =$L95 -> Inadequate | R95: =$K95 -> No Override | S95: =$C95 -> 4 | T95: =IF($L95=$Q95,"","***")
A96: 4 | C96: =IF($B96="",$A96,$B96) -> 4 | D96: Personnel Security | E96: PS-3.1 | F96: Personnel Screening | G96: Does the organization screen individuals prior to authorizing access to the information system? | H96: ='13. Personnel Security'!$G7 -> All employees are screened during job interviews | I96: ='13. Personnel Security'!$F7 -> Yes | J96: =IF($I96="Yes","Adequate",IF($I96="No","Inadequate",IF($I96="Partial","Inadequate",IF($I96="N/A","Inadequate",IF(OR($I96="",$I96=0),"Blank","Error"))))) -> Adequate | K96: No Override | L96: =IF($K96="No Override",$J96,$K96) -> Adequate | N96: =IF($J96=$L96,"","***") | O96: =IF(OR($I96="",$I96=0),"",$I96) -> Yes | P96: =IF(OR($H96="",$H96=0),"",$H96) -> All employees are screened during job interviews | Q96: =$L96 -> Adequate | R96: =$K96 -> No Override | S96: =$C96 -> 4 | T96: =IF($L96=$Q96,"","***")
A97: 4 | C97: =IF($B97="",$A97,$B97) -> 4 | D97: Personnel Security | E97: PS-3.2 | F97: Personnel Screening | G97: Does the organization re-screen individuals with access to the information system? | H97: ='13. Personnel Security'!$G8 -> 0 | I97: ='13. Personnel Security'!$F8 -> No | J97: =IF($I97="Yes","Adequate",IF($I97="No","Inadequate",IF($I97="Partial","Inadequate",IF($I97="N/A","Inadequate",IF(OR($I97="",$I97=0),"Blank","Error"))))) -> Inadequate | K97: No Override | L97: =IF($K97="No Override",$J97,$K97) -> Inadequate | N97: =IF($J97=$L97,"","***") | O97: =IF(OR($I97="",$I97=0),"",$I97) -> No | P97: =IF(OR($H97="",$H97=0),"",$H97) | Q97: =$L97 -> Inadequate | R97: =$K97 -> No Override | S97: =$C97 -> 4 | T97: =IF($L97=$Q97,"","***")
A98: 4 | C98: =IF($B98="",$A98,$B98) -> 4 | D98: Personnel Security | E98: PS-4.1 | F98: Personnel Termination | G98: Does the organization have appropriate termination procedures in place to those with access to the information system? | H98: ='13. Personnel Security'!$G9 -> 0 | I98: ='13. Personnel Security'!$F9 -> Yes | J98: =IF($I98="Yes","Adequate",IF($I98="No","Inadequate",IF($I98="Partial","Inadequate",IF($I98="N/A","Inadequate",IF(OR($I98="",$I98=0),"Blank","Error"))))) -> Adequate | K98: No Override | L98: =IF($K98="No Override",$J98,$K98) -> Adequate | N98: =IF($J98=$L98,"","***") | O98: =IF(OR($I98="",$I98=0),"",$I98) -> Yes | P98: =IF(OR($H98="",$H98=0),"",$H98) | Q98: =$L98 -> Adequate | R98: =$K98 -> No Override | S98: =$C98 -> 4 | T98: =IF($L98=$Q98,"","***")
A99: 4 | C99: =IF($B99="",$A99,$B99) -> 4 | D99: Personnel Security | E99: PS-5.1 | F99: Personnel Transfer | G99: Does the organization have appropriate transfer procedures in place to those with access to the information system? | H99: ='13. Personnel Security'!$G10 -> 0 | I99: ='13. Personnel Security'!$F10 -> No | J99: =IF($I99="Yes","Adequate",IF($I99="No","Inadequate",IF($I99="Partial","Inadequate",IF($I99="N/A","Inadequate",IF(OR($I99="",$I99=0),"Blank","Error"))))) -> Inadequate | K99: No Override | L99: =IF($K99="No Override",$J99,$K99) -> Inadequate | N99: =IF($J99=$L99,"","***") | O99: =IF(OR($I99="",$I99=0),"",$I99) -> No | P99: =IF(OR($H99="",$H99=0),"",$H99) | Q99: =$L99 -> Inadequate | R99: =$K99 -> No Override | S99: =$C99 -> 4 | T99: =IF($L99=$Q99,"","***")
A100: 4 | C100: =IF($B100="",$A100,$B100) -> 4 | D100: Personnel Security | E100: PS-6.1 | F100: Access Agreements | G100: Does the organization have access agreements (reviewed annually) for individuals with access to the information system? | H100: ='13. Personnel Security'!$G11 -> Access control is granted per unique user account/role (example: technical support analyst). Each employee signs an employment agreement that explicitly covers controls of access to customer data. In addition, HIPAA, Security & Privacy guidelines are revised and signed-off annually by all employees. That said, there are no explicity "access agreements" for individual employees. | I100: ='13. Personnel Security'!$F11 -> Partial | J100: =IF($I100="Yes","Adequate",IF($I100="No","Inadequate",IF($I100="Partial","Inadequate",IF($I100="N/A","Inadequate",IF(OR($I100="",$I100=0),"Blank","Error"))))) -> Inadequate | K100: No Override | L100: =IF($K100="No Override",$J100,$K100) -> Inadequate | N100: =IF($J100=$L100,"","***") | O100: =IF(OR($I100="",$I100=0),"",$I100) -> Partial | P100: =IF(OR($H100="",$H100=0),"",$H100) -> Access control is granted per unique user account/role (example: technical support analyst). Each employee signs an employment agreement that explicitly covers controls of access to customer data. In addition, HIPAA, Security & Privacy guidelines are revised and signed-off annually by all employees. That said, there are no explicity "access agreements" for individual employees. | Q100: =$L100 -> Inadequate | R100: =$K100 -> No Override | S100: =$C100 -> 4 | T100: =IF($L100=$Q100,"","***")
A101: 4 | C101: =IF($B101="",$A101,$B101) -> 4 | D101: Personnel Security | E101: PS-7.1 | F101: Third Party Personnel Security | G101: Does the organization have appropriate third-party access control procedures for external parties granted access to the information system? | H101: ='13. Personnel Security'!$G12 -> 0 | I101: ='13. Personnel Security'!$F12 -> Yes | J101: =IF($I101="Yes","Adequate",IF($I101="No","Inadequate",IF($I101="Partial","Inadequate",IF(AND($I101="N/A",'Vendor Profile Questionnaire'!$B$29="No"),"Adequate",IF(AND($I101="N/A",NOT('Vendor Profile Questionnaire'!$B$29="No")),"Inadequate",IF(OR($I101="",$I101=0),"Blank","Error")))))) -> Adequate | K101: No Override | L101: =IF($K101="No Override",$J101,$K101) -> Adequate | N101: =IF($J101=$L101,"","***") | O101: =IF(OR($I101="",$I101=0),"",$I101) -> Yes | P101: =IF(OR($H101="",$H101=0),"",$H101) | Q101: =$L101 -> Adequate | R101: =$K101 -> No Override | S101: =$C101 -> 4 | T101: =IF($L101=$Q101,"","***")
A102: 4 | C102: =IF($B102="",$A102,$B102) -> 4 | D102: Personnel Security | E102: PS-8.1 | F102: Personnel Sanctions | G102: Does the organization have appropriate personnel sanctions policies and procedures? | H102: ='13. Personnel Security'!$G13 -> 0 | I102: ='13. Personnel Security'!$F13 -> Yes | J102: =IF($I102="Yes","Adequate",IF($I102="No","Inadequate",IF($I102="Partial","Inadequate",IF($I102="N/A","Inadequate",IF(OR($I102="",$I102=0),"Blank","Error"))))) -> Adequate | K102: No Override | L102: =IF($K102="No Override",$J102,$K102) -> Adequate | N102: =IF($J102=$L102,"","***") | O102: =IF(OR($I102="",$I102=0),"",$I102) -> Yes | P102: =IF(OR($H102="",$H102=0),"",$H102) | Q102: =$L102 -> Adequate | R102: =$K102 -> No Override | S102: =$C102 -> 4 | T102: =IF($L102=$Q102,"","***")
A103: 4 | C103: =IF($B103="",$A103,$B103) -> 4 | D103: System Acquisition | E103: SA-1.1 | F103: System and Services Acquisition Policy and Procedure | G103: Are there formally documented policies and procedures for System and Services Acquisitions? If yes, please attach. | H103: ='15. System Acquisition'!$G3 -> Comment is required | I103: ='15. System Acquisition'!$F3 -> No | J103: =IF($I103="Yes","Adequate",IF($I103="No","Inadequate",IF($I103="Partial","Inadequate",IF($I103="N/A","Inadequate",IF(OR($I103="",$I103=0),"Blank","Error"))))) -> Inadequate | K103: No Override | L103: =IF($K103="No Override",$J103,$K103) -> Inadequate | N103: =IF($J103=$L103,"","***") | O103: =IF(OR($I103="",$I103=0),"",$I103) -> No | P103: =IF(OR($H103="",$H103=0),"",$H103) -> Comment is required | Q103: =$L103 -> Inadequate | R103: =$K103 -> No Override | S103: =$C103 -> 4 | T103: =IF($L103=$Q103,"","***")
A104: 4 | C104: =IF($B104="",$A104,$B104) -> 4 | D104: System Acquisition | E104: SA-3.1 | F104: System Development Life Cycle | G104: Does the organization define a comprehensive life cycle for the information system? | H104: ='15. System Acquisition'!$G4 -> Comment is required | I104: ='15. System Acquisition'!$F4 -> Yes | J104: =IF($I104="Yes","Adequate",IF($I104="No","Inadequate",IF($I104="Partial","Inadequate",IF($I104="N/A","Inadequate",IF(OR($I104="",$I104=0),"Blank","Error"))))) -> Adequate | K104: No Override | L104: =IF($K104="No Override",$J104,$K104) -> Adequate | N104: =IF($J104=$L104,"","***") | O104: =IF(OR($I104="",$I104=0),"",$I104) -> Yes | P104: =IF(OR($H104="",$H104=0),"",$H104) -> Comment is required | Q104: =$L104 -> Adequate | R104: =$K104 -> No Override | S104: =$C104 -> 4 | T104: =IF($L104=$Q104,"","***")
A105: 1 | C105: =IF($B105="",$A105,$B105) -> 1 | D105: System Acquisition | E105: SA-4.1 | F105: Acquisition Process | G105: Does the organization include the requirements, descriptions, and criteria, explicitly or by reference, in the acquisition contract for the information system, system component, or information system service in accordance with applicable federal laws, Executive Orders, directives, policies, regulations, standards, guidelines, and organizational mission/business needs | H105: ='15. System Acquisition'!$G5 -> yes as it applies to conracts for customers purchasing the PeriCALM software modules | I105: ='15. System Acquisition'!$F5 -> Yes | J105: =IF($I105="Yes","Adequate",IF($I105="No","Inadequate",IF($I105="Partial","Inadequate",IF($I105="N/A","Inadequate",IF(OR($I105="",$I105=0),"Blank","Error"))))) -> Adequate | K105: No Override | L105: =IF($K105="No Override",$J105,$K105) -> Adequate | N105: =IF($J105=$L105,"","***") | O105: =IF(OR($I105="",$I105=0),"",$I105) -> Yes | P105: =IF(OR($H105="",$H105=0),"",$H105) -> yes as it applies to conracts for customers purchasing the PeriCALM software modules | Q105: =$L105 -> Adequate | R105: =$K105 -> No Override | S105: =$C105 -> 1 | T105: =IF($L105=$Q105,"","***")
A106: 4 | C106: =IF($B106="",$A106,$B106) -> 4 | D106: System Acquisition | E106: SA-5.1 | F106: Information System Documentation | G106: Do you have administrator documentation for this information system that describes: 1. Secure configuration, installation, and operation of the system, component, or service; 2. Effective use and maintenance of security functions/mechanisms; and 3. Known vulnerabilities regarding configuration and use of administrative (i.e., privileged) functions; | H106: ='15. System Acquisition'!$G6 -> Comment is required | I106: ='15. System Acquisition'!$F6 -> Yes | J106: =IF($I106="Yes","Adequate",IF($I106="No","Inadequate",IF($I106="Partial","Inadequate",IF($I106="N/A","Inadequate",IF(OR($I106="",$I106=0),"Blank","Error"))))) -> Adequate | K106: No Override | L106: =IF($K106="No Override",$J106,$K106) -> Adequate | N106: =IF($J106=$L106,"","***") | O106: =IF(OR($I106="",$I106=0),"",$I106) -> Yes | P106: =IF(OR($H106="",$H106=0),"",$H106) -> Comment is required | Q106: =$L106 -> Adequate | R106: =$K106 -> No Override | S106: =$C106 -> 4 | T106: =IF($L106=$Q106,"","***")
A107: 4 | C107: =IF($B107="",$A107,$B107) -> 4 | D107: System Acquisition | E107: SA-5.2 | F107: Information System Documentation | G107: Do you have user documentation for this information system that describes: 1. User-accessible security functions/mechanisms and how to effectively use those security functions/mechanisms; 2. Methods for user interaction, which enables individuals to use the system, component, or service in a more secure manner; and 3. User responsibilities in maintaining the security of the system, component, or service. | H107: ='15. System Acquisition'!$G7 -> PeriGen provide end-user and administrator documentation that cover all aspects of the system include acces controls and configurations. PeriGen provide admin training to customer technical staff and ongoing management is customer responsibility | I107: ='15. System Acquisition'!$F7 -> Partial | J107: =IF($I107="Yes","Adequate",IF($I107="No","Inadequate",IF($I107="Partial","Inadequate",IF($I107="N/A","Inadequate",IF(OR($I107="",$I107=0),"Blank","Error"))))) -> Inadequate | K107: No Override | L107: =IF($K107="No Override",$J107,$K107) -> Inadequate | N107: =IF($J107=$L107,"","***") | O107: =IF(OR($I107="",$I107=0),"",$I107) -> Partial | P107: =IF(OR($H107="",$H107=0),"",$H107) -> PeriGen provide end-user and administrator documentation that cover all aspects of the system include acces controls and configurations. PeriGen provide admin training to customer technical staff and ongoing management is customer responsibility | Q107: =$L107 -> Inadequate | R107: =$K107 -> No Override | S107: =$C107 -> 4 | T107: =IF($L107=$Q107,"","***")
A108: 4 | C108: =IF($B108="",$A108,$B108) -> 4 | D108: System Acquisition | E108: SA-5.4 | F108: Information System Documentation | G108: Is the documentation protected as required and only distributed to authorized personnel? | H108: ='15. System Acquisition'!$G8 -> End-user and admin guides are provided/available to users accessing the system in a clinical setting. Other material is provided directly to staff during training sessions | I108: ='15. System Acquisition'!$F8 -> No | J108: =IF($I108="Yes","Adequate",IF($I108="No","Inadequate",IF($I108="Partial","Inadequate",IF(AND($I108="N/A",$I107="No",$I106="No"),"Adequate",IF(AND($I108="N/A",OR(NOT($I107="No"),NOT($I106="No"))),"Inadequate",IF(OR($I108="",$I108=0),"Blank","Error")))))) -> Inadequate | K108: No Override | L108: =IF($K108="No Override",$J108,$K108) -> Inadequate | N108: =IF($J108=$L108,"","***") | O108: =IF(OR($I108="",$I108=0),"",$I108) -> No | P108: =IF(OR($H108="",$H108=0),"",$H108) -> End-user and admin guides are provided/available to users accessing the system in a clinical setting. Other material is provided directly to staff during training sessions | Q108: =$L108 -> Inadequate | R108: =$K108 -> No Override | S108: =$C108 -> 4 | T108: =IF($L108=$Q108,"","***")
A109: 4 | C109: =IF($B109="",$A109,$B109) -> 4 | D109: System Acquisition | E109: SA-8.1 | F109: Security Engineering Principles | G109: Does the organization apply information system security engineering principles in the specification, design, development, implementation, and modification of the information system. | H109: ='15. System Acquisition'!$G9 -> Comment is required | I109: ='15. System Acquisition'!$F9 -> Yes | J109: =IF($I109="Yes","Adequate",IF($I109="No","Inadequate",IF($I109="Partial","Inadequate",IF($I109="N/A","Inadequate",IF(OR($I109="",$I109=0),"Blank","Error"))))) -> Adequate | K109: No Override | L109: =IF($K109="No Override",$J109,$K109) -> Adequate | N109: =IF($J109=$L109,"","***") | O109: =IF(OR($I109="",$I109=0),"",$I109) -> Yes | P109: =IF(OR($H109="",$H109=0),"",$H109) -> Comment is required | Q109: =$L109 -> Adequate | R109: =$K109 -> No Override | S109: =$C109 -> 4 | T109: =IF($L109=$Q109,"","***")
A110: 4 | C110: =IF($B110="",$A110,$B110) -> 4 | D110: System Acquisition | E110: SA-10.1 | F110: Developer Configuration Management | G110: Does the organization require the developer of the information system, system component or information system service to perform configuration, document the changes and implement only organization-approved configuration changes? | H110: ='15. System Acquisition'!$G10 -> Comment is required | I110: ='15. System Acquisition'!$F10 -> Yes | J110: =IF($I110="Yes","Adequate",IF($I110="No","Inadequate",IF($I110="Partial","Inadequate",IF($I110="N/A","Inadequate",IF(OR($I110="",$I110=0),"Blank","Error"))))) -> Adequate | K110: No Override | L110: =IF($K110="No Override",$J110,$K110) -> Adequate | N110: =IF($J110=$L110,"","***") | O110: =IF(OR($I110="",$I110=0),"",$I110) -> Yes | P110: =IF(OR($H110="",$H110=0),"",$H110) -> Comment is required | Q110: =$L110 -> Adequate | R110: =$K110 -> No Override | S110: =$C110 -> 4 | T110: =IF($L110=$Q110,"","***")
A111: 2 | C111: =IF($B111="",$A111,$B111) -> 2 | D111: System Acquisition | E111: SA-11.1 | F111: Developer Security Testing and Evaluation | G111: Does the organization require the developer of the information system, system component, or information system service to create and implement a security assessment plan, perform tests/evaluations and produce evidence of the execution of the security assessment plan? | H111: ='15. System Acquisition'!$G11 -> Comment is required | I111: ='15. System Acquisition'!$F11 -> Yes | J111: =IF($I111="Yes","Adequate",IF($I111="No","Inadequate",IF($I111="Partial","Inadequate",IF($I111="N/A","Inadequate",IF(OR($I111="",$I111=0),"Blank","Error"))))) -> Adequate | K111: No Override | L111: =IF($K111="No Override",$J111,$K111) -> Adequate | N111: =IF($J111=$L111,"","***") | O111: =IF(OR($I111="",$I111=0),"",$I111) -> Yes | P111: =IF(OR($H111="",$H111=0),"",$H111) -> Comment is required | Q111: =$L111 -> Adequate | R111: =$K111 -> No Override | S111: =$C111 -> 2 | T111: =IF($L111=$Q111,"","***")
A112: 4 | C112: =IF($B112="",$A112,$B112) -> 4 | D112: System Data Protection | E112: SC-1.1 | F112: System and Communications Protection Policy and Procedures | G112: Do you have formally documented policies and procedures for System and Communications Protection? If yes, please attach. | H112: ='16. System Data Protection'!$G3 -> Comment is required | I112: ='16. System Data Protection'!$F3 -> No | J112: =IF($I112="Yes","Adequate",IF($I112="No","Inadequate",IF($I112="Partial","Inadequate",IF($I112="N/A","Inadequate",IF(OR($I112="",$I112=0),"Blank","Error"))))) -> Inadequate | K112: No Override | L112: =IF($K112="No Override",$J112,$K112) -> Inadequate | N112: =IF($J112=$L112,"","***") | O112: =IF(OR($I112="",$I112=0),"",$I112) -> No | P112: =IF(OR($H112="",$H112=0),"",$H112) -> Comment is required | Q112: =$L112 -> Inadequate | R112: =$K112 -> No Override | S112: =$C112 -> 4 | T112: =IF($L112=$Q112,"","***")
...

Sheet Override Control Env2
F1: Environment Scope Summary
F2: Service or Product? | G2: Data Types: | H2: Client Data Accessible via: | I2: Certifications | J2: Environment Access
F3: =IF(Scope!D6="Yes",_xlfn.CONCAT("Service ")&IF(Scope!D7="Yes",_xlfn.CONCAT("Product"),""),IF(Scope!D7="Yes",_xlfn.CONCAT("Product"),"Blank")) -> Blank | G3: =IF(Scope!D17="Yes","PHI","No PHI") -> No PHI | H3: =IF(OR(Scope!D23="Yes",NOT(Scope!E23="")),"Workstation"&_xlfn.CONCAT(" ,",Scope!E23),"") | I3: =IF(Scope!D40="Yes",_xlfn.CONCAT("SOC 1 Type 1 ")&IF(Scope!D41="Yes",_xlfn.CONCAT("SOC 1 Type 2"),""),IF(Scope!D41="Yes",_xlfn.CONCAT("SOC 1 Type 2"),"No SOC 1")) -> No SOC 1 | J3: =IF(Scope!D10="Yes",_xlfn.CONCAT("Remote Access Client Network ")&IF(Scope!D11="Yes",_xlfn.CONCAT("Onsite Network Access"),""),IF(Scope!D11="Yes",_xlfn.CONCAT("Onsite Network Access"),""))
F4: =IF(Scope!D6="Yes",Scope!E6,"")& " "&IF(Scope!D7="Yes",Scope!E7,"") | G4: =IF(Scope!D18="Yes","PII","No PII") -> No PII | H4: =IF(OR(Scope!D25="Yes",NOT(Scope!E25="")),"Mobile Device"&_xlfn.CONCAT(" ,",Scope!E25),"") | I4: =IF(Scope!D42="Yes",_xlfn.CONCAT("SOC 2 Type 1 ")&IF(Scope!D43="Yes",_xlfn.CONCAT("SOC 2 Type 2"),""),IF(Scope!D43="Yes",_xlfn.CONCAT("SOC 2 Type 2"),"No SOC 2")) -> No SOC 2 | J4: =IF(Scope!D12="Yes",_xlfn.CONCAT("Access Client Infrastructure ")&IF(Scope!D13="Yes",_xlfn.CONCAT("Access Application/Database"),""),IF(Scope!D13="Yes",_xlfn.CONCAT("Access Application/Database"),""))
G5: =IF(Scope!D19="Yes","PCI","No PCI") -> No PCI | H5: =IF(OR(Scope!D27="Yes",NOT(Scope!E27="")),"Medical Device"&_xlfn.CONCAT(" ,",Scope!E27),"") | I5: =IF(Scope!D44="Yes",_xlfn.CONCAT("SOC 3 ")&IF(Scope!D45="Yes",_xlfn.CONCAT("HITRUST"),""),IF(Scope!D45="Yes",_xlfn.CONCAT("HITRUST"),"")) | J5: =IF(Scope!D14="Yes",_xlfn.CONCAT("Receive Client Data ")&IF(Scope!D15="Yes",_xlfn.CONCAT("No Access"),""),IF(Scope!D15="Yes",_xlfn.CONCAT("No Access"),""))
G6: =IF(Scope!D20="Yes",_xlfn.CONCAT("Employee Information ")&IF(Scope!D21="Yes",_xlfn.CONCAT(" Proprietary Information")),IF(Scope!D21="Yes",_xlfn.CONCAT("Proprietary Information"),"No Employee or Proprietary Informaiton")) -> No Employee or Proprietary Informaiton | H6: =IF(OR(Scope!D28="Yes",NOT(Scope!E28="")),"Other"&_xlfn.CONCAT(" ,",Scope!E28),"") | I6: =IF(Scope!D46="Yes",_xlfn.CONCAT("PCI DSS ")&IF(Scope!D46="Yes",_xlfn.CONCAT("ISO 27001"),""),IF(Scope!D46="Yes",_xlfn.CONCAT("ISO 27001"),""))
I7: =IF(Scope!D48="Yes",_xlfn.CONCAT("FedRamp ")&IF(Scope!D49="Yes",_xlfn.CONCAT("HIPAA"),""),IF(Scope!D47="Yes",_xlfn.CONCAT("HIPAA"),""))
A8: Tier | B8: Client Tier | C8: Calc Tier | D8: Control Family | E8: Control Question # | F8: Control Name | G8: Security Question | H8: Comment | I8: Response | J8: Calc Response | K8: Override | L8: Final Response | M8: Reviewer Comments | N8: FindOverrideChanges | O8: Response: | P8: Comments/ Notes: | Q8: FinalResponse | R8: Overrides | S8: OverrideTier | T8: CheckOverrideChanges
A9: 3 | C9: =IF($B9="",$A9,$B9) -> 3 | D9: Access Controls | E9: AC-1.1 | F9: Access Control Policy and Procedures | G9: Are there formally documented policies and procedures for access control? If yes, please attach. | H9: ='1. Access Controls'!$I3 -> Comment is required | I9: ='1. Access Controls'!$H3 -> 0 | J9: =IF($I9="Yes","Adequate",IF($I9="No","Inadequate",IF($I9="Partial","Inadequate",IF($I9="N/A","Inadequate",IF(OR($I9="",$I9=0),"Blank","Error"))))) -> Blank | K9: No Override | L9: =IF($K9="No Override",$J9,$K9) -> Blank | N9: =IF($J9=$L9,"","***") | O9: =IF(OR($I9="",$I9=0),"",$I9) | P9: =IF(OR($H9="",$H9=0),"",$H9) -> Comment is required | Q9: =$L9 -> Blank | R9: =$K9 -> No Override | S9: =$C9 -> 3 | T9: =IF($L9=$Q9,"","***")
A10: 1 | C10: =IF($B10="",$A10,$B10) -> 1 | D10: Access Controls | E10: AC-3.1 | F10: Access Enforcement | G10: Does the information system verify the rights of a user to access the information system? (Access Control Lists, Group/Role membership?) If yes, detail how the access is enforced in the comment. | H10: ='1. Access Controls'!$I4 -> Comment is required | I10: ='1. Access Controls'!$H4 -> 0 | J10: =IF($I10="Yes","Adequate",IF($I10="No","Inadequate",IF($I10="Partial","Inadequate",IF($I10="N/A","Inadequate",IF(OR($I10="",$I10=0),"Blank","Error"))))) -> Blank | K10: No Override | L10: =IF($K10="No Override",$J10,$K10) -> Blank | N10: =IF($J10=$L10,"","***") | O10: =IF(OR($I10="",$I10=0),"",$I10) | P10: =IF(OR($H10="",$H10=0),"",$H10) -> Comment is required | Q10: =$L10 -> Blank | R10: =$K10 -> No Override | S10: =$C10 -> 1 | T10: =IF($L10=$Q10,"","***")
A11: 3 | C11: =IF($B11="",$A11,$B11) -> 3 | D11: Access Controls | E11: AC-3.2 | F11: Access Enforcement | G11: Does the information system support role-based account management and access controls (RBAC)? | H11: ='1. Access Controls'!$I5 -> Comment is required | I11: ='1. Access Controls'!$H5 -> 0 | J11: =IF($I11="Yes","Adequate",IF($I11="No","Inadequate",IF($I11="Partial","Inadequate",IF($I11="N/A","Inadequate",IF(OR($I11="",$I11=0),"Blank","Error"))))) -> Blank | K11: No Override | L11: =IF($K11="No Override",$J11,$K11) -> Blank | N11: =IF($J11=$L11,"","***") | O11: =IF(OR($I11="",$I11=0),"",$I11) | P11: =IF(OR($H11="",$H11=0),"",$H11) -> Comment is required | Q11: =$L11 -> Blank | R11: =$K11 -> No Override | S11: =$C11 -> 3 | T11: =IF($L11=$Q11,"","***")
A12: 4 | C12: =IF($B12="",$A12,$B12) -> 4 | D12: Access Controls | E12: AC-3.3 | F12: Access Enforcement | G12: If RBAC is supported, can a customer administrator create/customize unique roles and permissions. | H12: ='1. Access Controls'!$I6 -> Comment is required | I12: ='1. Access Controls'!$H6 -> 0 | J12: =IF($I12="Yes","Adequate",IF($I12="No","Inadequate",IF($I12="Partial","Inadequate",IF($I12="N/A","Inadequate",IF(OR($I12="",$I12=0),"Blank","Error"))))) -> Blank | K12: No Override | L12: =IF($K12="No Override",$J12,$K12) -> Blank | N12: =IF($J12=$L12,"","***") | O12: =IF(OR($I12="",$I12=0),"",$I12) | P12: =IF(OR($H12="",$H12=0),"",$H12) -> Comment is required | Q12: =$L12 -> Blank | R12: =$K12 -> No Override | S12: =$C12 -> 4 | T12: =IF($L12=$Q12,"","***")
A13: 2 | C13: =IF($B13="",$A13,$B13) -> 2 | D13: Access Controls | E13: AC-7.1 | F13: Unsuccessful Logon Attempts | G13: Is an account automatically locked out after a set amount of login attempts? If yes, please provide the number of failed attempts that trigger an account to be locked out, in the comments section. | H13: ='1. Access Controls'!$I7 -> Comment is required | I13: ='1. Access Controls'!$H7 -> 0 | J13: =IF($I13="Yes","Adequate",IF($I13="No","Inadequate",IF($I13="Partial","Inadequate",IF($I13="N/A","Inadequate",IF(OR($I13="",$I13=0),"Blank","Error"))))) -> Blank | K13: No Override | L13: =IF($K13="No Override",$J13,$K13) -> Blank | N13: =IF($J13=$L13,"","***") | O13: =IF(OR($I13="",$I13=0),"",$I13) | P13: =IF(OR($H13="",$H13=0),"",$H13) -> Comment is required | Q13: =$L13 -> Blank | R13: =$K13 -> No Override | S13: =$C13 -> 2 | T13: =IF($L13=$Q13,"","***")
A14: 4 | C14: =IF($B14="",$A14,$B14) -> 4 | D14: Access Controls | E14: AC-8.1 | F14: System Use Notification | G14: Is there a system use notification displayed before granting access that provides privacy and security notices? | H14: ='1. Access Controls'!$I8 -> Comment is required | I14: ='1. Access Controls'!$H8 -> 0 | J14: =IF($I14="Yes","Adequate",IF($I14="No","Inadequate",IF($I14="Partial","Inadequate",IF($I14="N/A","Inadequate",IF(OR($I14="",$I14=0),"Blank","Error"))))) -> Blank | K14: No Override | L14: =IF($K14="No Override",$J14,$K14) -> Blank | N14: =IF($J14=$L14,"","***") | O14: =IF(OR($I14="",$I14=0),"",$I14) | P14: =IF(OR($H14="",$H14=0),"",$H14) -> Comment is required | Q14: =$L14 -> Blank | R14: =$K14 -> No Override | S14: =$C14 -> 4 | T14: =IF($L14=$Q14,"","***")
A15: 4 | C15: =IF($B15="",$A15,$B15) -> 4 | D15: Access Controls | E15: AC-9.1 | F15: Previous Logon Notification | G15: Does the system display the last user logon date and time to the user? | H15: ='1. Access Controls'!$I9 -> Comment is required | I15: ='1. Access Controls'!$H9 -> 0 | J15: =IF($I15="Yes","Adequate",IF($I15="No","Inadequate",IF($I15="Partial","Inadequate",IF($I15="N/A","Inadequate",IF(OR($I15="",$I15=0),"Blank","Error"))))) -> Blank | K15: No Override | L15: =IF($K15="No Override",$J15,$K15) -> Blank | N15: =IF($J15=$L15,"","***") | O15: =IF(OR($I15="",$I15=0),"",$I15) | P15: =IF(OR($H15="",$H15=0),"",$H15) -> Comment is required | Q15: =$L15 -> Blank | R15: =$K15 -> No Override | S15: =$C15 -> 4 | T15: =IF($L15=$Q15,"","***")
A16: 4 | C16: =IF($B16="",$A16,$B16) -> 4 | D16: Access Controls | E16: AC-10.1 | F16: Concurrent Session Control | G16: Does the system limit the number of concurrent sessions for the user? | H16: ='1. Access Controls'!$I10 -> Comment is required | I16: ='1. Access Controls'!$H10 -> 0 | J16: =IF($I16="Yes","Adequate",IF($I16="No","Inadequate",IF($I16="Partial","Inadequate",IF($I16="N/A","Inadequate",IF(OR($I16="",$I16=0),"Blank","Error"))))) -> Blank | K16: No Override | L16: =IF($K16="No Override",$J16,$K16) -> Blank | N16: =IF($J16=$L16,"","***") | O16: =IF(OR($I16="",$I16=0),"",$I16) | P16: =IF(OR($H16="",$H16=0),"",$H16) -> Comment is required | Q16: =$L16 -> Blank | R16: =$K16 -> No Override | S16: =$C16 -> 4 | T16: =IF($L16=$Q16,"","***")
A17: 2 | C17: =IF($B17="",$A17,$B17) -> 2 | D17: Access Controls | E17: AC-11.1 | F17: Session Lock | G17: Does the application/system have a session lock after a period of inactivity that requires a user to reauthenticate? | H17: ='1. Access Controls'!$I11 -> Comment is required | I17: ='1. Access Controls'!$H11 -> 0 | J17: =IF($I17="Yes","Adequate",IF($I17="No","Inadequate",IF($I17="Partial","Inadequate",IF($I17="N/A","Inadequate",IF(OR($I17="",$I17=0),"Blank","Error"))))) -> Blank | K17: No Override | L17: =IF($K17="No Override",$J17,$K17) -> Blank | N17: =IF($J17=$L17,"","***") | O17: =IF(OR($I17="",$I17=0),"",$I17) | P17: =IF(OR($H17="",$H17=0),"",$H17) -> Comment is required | Q17: =$L17 -> Blank | R17: =$K17 -> No Override | S17: =$C17 -> 2 | T17: =IF($L17=$Q17,"","***")
A18: 2 | C18: =IF($B18="",$A18,$B18) -> 2 | D18: Access Controls | E18: AC-12.1 | F18: Session Termination | G18: Does the application/system terminate the session after predefined circumstances? | H18: ='1. Access Controls'!$I12 -> Comment is required | I18: ='1. Access Controls'!$H12 -> 0 | J18: =IF($I18="Yes","Adequate",IF($I18="No","Inadequate",IF($I18="Partial","Inadequate",IF($I18="N/A","Inadequate",IF(OR($I18="",$I18=0),"Blank","Error"))))) -> Blank | K18: No Override | L18: =IF($K18="No Override",$J18,$K18) -> Blank | N18: =IF($J18=$L18,"","***") | O18: =IF(OR($I18="",$I18=0),"",$I18) | P18: =IF(OR($H18="",$H18=0),"",$H18) -> Comment is required | Q18: =$L18 -> Blank | R18: =$K18 -> No Override | S18: =$C18 -> 2 | T18: =IF($L18=$Q18,"","***")
A19: 2 | C19: =IF($B19="",$A19,$B19) -> 2 | D19: Access Controls | E19: AC-14.1 | F19: Permitted Actions without Identification or Authentication | G19: Does the system prevent user actions that can be performed on the system without identification and authentication? | H19: ='1. Access Controls'!$I13 -> Comment is required | I19: ='1. Access Controls'!$H13 -> 0 | J19: =IF($I19="Yes","Adequate",IF($I19="No","Inadequate",IF($I19="Partial","Inadequate",IF($I19="N/A","Inadequate",IF(OR($I19="",$I19=0),"Blank","Error"))))) -> Blank | K19: No Override | L19: =IF($K19="No Override",$J19,$K19) -> Blank | N19: =IF($J19=$L19,"","***") | O19: =IF(OR($I19="",$I19=0),"",$I19) | P19: =IF(OR($H19="",$H19=0),"",$H19) -> Comment is required | Q19: =$L19 -> Blank | R19: =$K19 -> No Override | S19: =$C19 -> 2 | T19: =IF($L19=$Q19,"","***")
A20: 2 | C20: =IF($B20="",$A20,$B20) -> 2 | D20: Awareness and Training | E20: AT-1.1 | F20: Security Awareness and Training Policy and Procedures | G20: Are there formally documented procedures for security awareness and training for this information system? If yes, please attach. | H20: ='2. Awareness and Training'!$I3 -> Comment is required | I20: ='2. Awareness and Training'!$H3 -> 0 | J20: =IF($I20="Yes","Adequate",IF($I20="No","Inadequate",IF($I20="Partial","Inadequate",IF($I20="N/A","Inadequate",IF(OR($I20="",$I20=0),"Blank","Error"))))) -> Blank | K20: No Override | L20: =IF($K20="No Override",$J20,$K20) -> Blank | N20: =IF($J20=$L20,"","***") | O20: =IF(OR($I20="",$I20=0),"",$I20) | P20: =IF(OR($H20="",$H20=0),"",$H20) -> Comment is required | Q20: =$L20 -> Blank | R20: =$K20 -> No Override | S20: =$C20 -> 2 | T20: =IF($L20=$Q20,"","***")
A21: 2 | C21: =IF($B21="",$A21,$B21) -> 2 | D21: Awareness and Training | E21: AT-2.1 | F21: Security Awareness | G21: Is basic security awareness training performed for all personnel as a part of the onboarding process? | H21: ='2. Awareness and Training'!$I4 -> Comment is required | I21: ='2. Awareness and Training'!$H4 -> 0 | J21: =IF($I21="Yes","Adequate",IF($I21="No","Inadequate",IF($I21="Partial","Inadequate",IF($I21="N/A","Inadequate",IF(OR($I21="",$I21=0),"Blank","Error"))))) -> Blank | K21: No Override | L21: =IF($K21="No Override",$J21,$K21) -> Blank | N21: =IF($J21=$L21,"","***") | O21: =IF(OR($I21="",$I21=0),"",$I21) | P21: =IF(OR($H21="",$H21=0),"",$H21) -> Comment is required | Q21: =$L21 -> Blank | R21: =$K21 -> No Override | S21: =$C21 -> 2 | T21: =IF($L21=$Q21,"","***")
A22: 2 | C22: =IF($B22="",$A22,$B22) -> 2 | D22: Awareness and Training | E22: AT-2.2 | F22: Security Awareness | G22: Is it periodically performed for all users? | H22: ='2. Awareness and Training'!$I5 -> Comment is required | I22: ='2. Awareness and Training'!$H5 -> 0 | J22: =IF($I22="Yes","Adequate",IF($I22="No","Inadequate",IF($I22="Partial","Inadequate",IF($I22="N/A","Inadequate",IF(OR($I22="",$I22=0),"Blank","Error"))))) -> Blank | K22: No Override | L22: =IF($K22="No Override",$J22,$K22) -> Blank | N22: =IF($J22=$L22,"","***") | O22: =IF(OR($I22="",$I22=0),"",$I22) | P22: =IF(OR($H22="",$H22=0),"",$H22) -> Comment is required | Q22: =$L22 -> Blank | R22: =$K22 -> No Override | S22: =$C22 -> 2 | T22: =IF($L22=$Q22,"","***")
A23: 2 | C23: =IF($B23="",$A23,$B23) -> 2 | D23: Awareness and Training | E23: AT-3.1 | F23: Role-Based Security Training | G23: Is there role-based security training for personnel with assigned security roles and responsibilities for this information system before access is granted and when required by information system changes? | H23: ='2. Awareness and Training'!$I6 -> Comment is required | I23: ='2. Awareness and Training'!$H6 -> 0 | J23: =IF($I23="Yes","Adequate",IF($I23="No","Inadequate",IF($I23="Partial","Inadequate",IF($I23="N/A","Inadequate",IF(OR($I23="",$I23=0),"Blank","Error"))))) -> Blank | K23: No Override | L23: =IF($K23="No Override",$J23,$K23) -> Blank | N23: =IF($J23=$L23,"","***") | O23: =IF(OR($I23="",$I23=0),"",$I23) | P23: =IF(OR($H23="",$H23=0),"",$H23) -> Comment is required | Q23: =$L23 -> Blank | R23: =$K23 -> No Override | S23: =$C23 -> 2 | T23: =IF($L23=$Q23,"","***")
A24: 2 | C24: =IF($B24="",$A24,$B24) -> 2 | D24: Awareness and Training | E24: AT-4.1 | F24: Security Training Records | G24: Do you document and monitor information system security training activities for individuals? | H24: ='2. Awareness and Training'!$I7 -> Comment is required | I24: ='2. Awareness and Training'!$H7 -> 0 | J24: =IF($I24="Yes","Adequate",IF($I24="No","Inadequate",IF($I24="Partial","Inadequate",IF($I24="N/A","Inadequate",IF(OR($I24="",$I24=0),"Blank","Error"))))) -> Blank | K24: No Override | L24: =IF($K24="No Override",$J24,$K24) -> Blank | N24: =IF($J24=$L24,"","***") | O24: =IF(OR($I24="",$I24=0),"",$I24) | P24: =IF(OR($H24="",$H24=0),"",$H24) -> Comment is required | Q24: =$L24 -> Blank | R24: =$K24 -> No Override | S24: =$C24 -> 2 | T24: =IF($L24=$Q24,"","***")
A25: 2 | C25: =IF($B25="",$A25,$B25) -> 2 | D25: Audit and Accountability | E25: AU-2.1 | F25: Audit Events | G25: Is the information system actively auditing events such as access to patient information, login/logoffs, account creation, etc.? If yes, please detail the events captured in the comment. | H25: ='3. Audit and Accountability'!$I3 -> Comment is required | I25: ='3. Audit and Accountability'!$H3 -> 0 | J25: =IF($I25="Yes","Adequate",IF($I25="No","Inadequate",IF($I25="Partial","Inadequate",IF($I25="N/A","Inadequate",IF(OR($I25="",$I25=0),"Blank","Error"))))) -> Blank | K25: No Override | L25: =IF($K25="No Override",$J25,$K25) -> Blank | N25: =IF($J25=$L25,"","***") | O25: =IF(OR($I25="",$I25=0),"",$I25) | P25: =IF(OR($H25="",$H25=0),"",$H25) -> Comment is required | Q25: =$L25 -> Blank | R25: =$K25 -> No Override | S25: =$C25 -> 2 | T25: =IF($L25=$Q25,"","***")
A26: 2 | C26: =IF($B26="",$A26,$B26) -> 2 | D26: Audit and Accountability | E26: AU-2.2 | F26: Audit Events | G26: Are the audit logs captured sufficient for incident response and system and user performance/investigation? | H26: ='3. Audit and Accountability'!$I4 -> Comment is required | I26: ='3. Audit and Accountability'!$H4 -> 0 | J26: =IF($I26="Yes","Adequate",IF($I26="No","Inadequate",IF($I26="Partial","Inadequate",IF($I26="N/A","Inadequate",IF(OR($I26="",$I26=0),"Blank","Error"))))) -> Blank | K26: No Override | L26: =IF($K26="No Override",$J26,$K26) -> Blank | N26: =IF($J26=$L26,"","***") | O26: =IF(OR($I26="",$I26=0),"",$I26) | P26: =IF(OR($H26="",$H26=0),"",$H26) -> Comment is required | Q26: =$L26 -> Blank | R26: =$K26 -> No Override | S26: =$C26 -> 2 | T26: =IF($L26=$Q26,"","***")
A27: 2 | C27: =IF($B27="",$A27,$B27) -> 2 | D27: Audit and Accountability | E27: AU-3.1 | F27: Content of Audit Records | G27: Does the system create audit records that contain sufficient information to, at a minimum, establish what type of event occurred, when the event occurred, where the event occurred, the source of the event, the outcome (success or failure) of the event, and the identity of any user/subject associated with the event? | H27: ='3. Audit and Accountability'!$I5 -> Comment is required | I27: ='3. Audit and Accountability'!$H5 -> 0 | J27: =IF($I27="Yes","Adequate",IF($I27="No","Inadequate",IF($I27="Partial","Inadequate",IF($I27="N/A","Inadequate",IF(OR($I27="",$I27=0),"Blank","Error"))))) -> Blank | K27: No Override | L27: =IF($K27="No Override",$J27,$K27) -> Blank | N27: =IF($J27=$L27,"","***") | O27: =IF(OR($I27="",$I27=0),"",$I27) | P27: =IF(OR($H27="",$H27=0),"",$H27) -> Comment is required | Q27: =$L27 -> Blank | R27: =$K27 -> No Override | S27: =$C27 -> 2 | T27: =IF($L27=$Q27,"","***")
A28: 3 | C28: =IF($B28="",$A28,$B28) -> 3 | D28: Audit and Accountability | E28: AU-5.1 | F28: Response to Audit Processing Failures | G28: Does the information system generate an alert that notifies the team in the event of an audit processing failure? | H28: ='3. Audit and Accountability'!$I6 -> Comment is required | I28: ='3. Audit and Accountability'!$H6 -> 0 | J28: =IF($I28="Yes","Adequate",IF($I28="No","Inadequate",IF($I28="Partial","Inadequate",IF($I28="N/A","Inadequate",IF(OR($I28="",$I28=0),"Blank","Error"))))) -> Blank | K28: No Override | L28: =IF($K28="No Override",$J28,$K28) -> Blank | N28: =IF($J28=$L28,"","***") | O28: =IF(OR($I28="",$I28=0),"",$I28) | P28: =IF(OR($H28="",$H28=0),"",$H28) -> Comment is required | Q28: =$L28 -> Blank | R28: =$K28 -> No Override | S28: =$C28 -> 3 | T28: =IF($L28=$Q28,"","***")
A29: 3 | C29: =IF($B29="",$A29,$B29) -> 3 | D29: Audit and Accountability | E29: AU-7.1 | F29: Audit Reduction and Report Generation | G29: Does the information system provide the capability to generate customizable audit reports? | H29: ='3. Audit and Accountability'!$I7 -> Comment is required | I29: ='3. Audit and Accountability'!$H7 -> 0 | J29: =IF($I29="Yes","Adequate",IF($I29="No","Inadequate",IF($I29="Partial","Inadequate",IF($I29="N/A","Inadequate",IF(OR($I29="",$I29=0),"Blank","Error"))))) -> Blank | K29: No Override | L29: =IF($K29="No Override",$J29,$K29) -> Blank | N29: =IF($J29=$L29,"","***") | O29: =IF(OR($I29="",$I29=0),"",$I29) | P29: =IF(OR($H29="",$H29=0),"",$H29) -> Comment is required | Q29: =$L29 -> Blank | R29: =$K29 -> No Override | S29: =$C29 -> 3 | T29: =IF($L29=$Q29,"","***")
A30: 4 | C30: =IF($B30="",$A30,$B30) -> 4 | D30: Audit and Accountability | E30: AU-7.2 | F30: Audit Reduction and Report Generation | G30: Does the generation of an audit report alter the original content or time stamp of the audit record? | H30: ='3. Audit and Accountability'!$I8 -> Comment is required | I30: ='3. Audit and Accountability'!$H8 -> 0 | J30: =IF($I30="Yes","Inadequate",IF($I30="No","Adequate",IF($I30="Partial","Inadequate",IF($I30="N/A","Inadequate",IF(OR($I30="",$I30=0),"Blank","Error"))))) -> Blank | K30: No Override | L30: =IF($K30="No Override",$J30,$K30) -> Blank | N30: =IF($J30=$L30,"","***") | O30: =IF(OR($I30="",$I30=0),"",$I30) | P30: =IF(OR($H30="",$H30=0),"",$H30) -> Comment is required | Q30: =$L30 -> Blank | R30: =$K30 -> No Override | S30: =$C30 -> 4 | T30: =IF($L30=$Q30,"","***")
A31: 2 | C31: =IF($B31="",$A31,$B31) -> 2 | D31: Audit and Accountability | E31: AU-8.1 | F31: Time Stamps | G31: Are the audit logs time stamped? (Date and Time) | H31: ='3. Audit and Accountability'!$I9 -> Comment is required | I31: ='3. Audit and Accountability'!$H9 -> 0 | J31: =IF($I31="Yes","Adequate",IF($I31="No","Inadequate",IF($I31="Partial","Inadequate",IF($I31="N/A","Inadequate",IF(OR($I31="",$I31=0),"Blank","Error"))))) -> Blank | K31: No Override | L31: =IF($K31="No Override",$J31,$K31) -> Blank | N31: =IF($J31=$L31,"","***") | O31: =IF(OR($I31="",$I31=0),"",$I31) | P31: =IF(OR($H31="",$H31=0),"",$H31) -> Comment is required | Q31: =$L31 -> Blank | R31: =$K31 -> No Override | S31: =$C31 -> 2 | T31: =IF($L31=$Q31,"","***")
A32: 2 | C32: =IF($B32="",$A32,$B32) -> 2 | D32: Audit and Accountability | E32: AU-9.1 | F32: Protection of Audit Information | G32: Does the system/application protect audit information from unauthorized access, modification, and deletion? | H32: ='3. Audit and Accountability'!$I10 -> Comment is required | I32: ='3. Audit and Accountability'!$H10 -> 0 | J32: =IF($I32="Yes","Adequate",IF($I32="No","Inadequate",IF($I32="Partial","Inadequate",IF($I32="N/A","Inadequate",IF(OR($I32="",$I32=0),"Blank","Error"))))) -> Blank | K32: No Override | L32: =IF($K32="No Override",$J32,$K32) -> Blank | N32: =IF($J32=$L32,"","***") | O32: =IF(OR($I32="",$I32=0),"",$I32) | P32: =IF(OR($H32="",$H32=0),"",$H32) -> Comment is required | Q32: =$L32 -> Blank | R32: =$K32 -> No Override | S32: =$C32 -> 2 | T32: =IF($L32=$Q32,"","***")
A33: 3 | C33: =IF($B33="",$A33,$B33) -> 3 | D33: Audit and Accountability | E33: AU-12.1 | F33: Audit Generation | G33: Can the information system be configured to select which auditable events are captured in the audit log? | H33: ='3. Audit and Accountability'!$I11 -> Comment is required | I33: ='3. Audit and Accountability'!$H11 -> 0 | J33: =IF($I33="Yes","Adequate",IF($I33="No","Inadequate",IF($I33="Partial","Inadequate",IF($I33="N/A","Inadequate",IF(OR($I33="",$I33=0),"Blank","Error"))))) -> Blank | K33: No Override | L33: =IF($K33="No Override",$J33,$K33) -> Blank | N33: =IF($J33=$L33,"","***") | O33: =IF(OR($I33="",$I33=0),"",$I33) | P33: =IF(OR($H33="",$H33=0),"",$H33) -> Comment is required | Q33: =$L33 -> Blank | R33: =$K33 -> No Override | S33: =$C33 -> 3 | T33: =IF($L33=$Q33,"","***")
A34: 4 | C34: =IF($B34="",$A34,$B34) -> 4 | D34: Configuration Management | E34: CM-1.1 | F34: Configuration Management Policy and Procedures | G34: Are there documented procedures to outline who/when and how the system/application is configured? If yes, please attach | H34: ='5. Configuration'!$I3 -> Comment is required | I34: ='5. Configuration'!$H3 -> 0 | J34: =IF($I34="Yes","Adequate",IF($I34="No","Inadequate",IF($I34="Partial","Inadequate",IF($I34="N/A","Inadequate",IF(OR($I34="",$I34=0),"Blank","Error"))))) -> Blank | K34: No Override | L34: =IF($K34="No Override",$J34,$K34) -> Blank | N34: =IF($J34=$L34,"","***") | O34: =IF(OR($I34="",$I34=0),"",$I34) | P34: =IF(OR($H34="",$H34=0),"",$H34) -> Comment is required | Q34: =$L34 -> Blank | R34: =$K34 -> No Override | S34: =$C34 -> 4 | T34: =IF($L34=$Q34,"","***")
A35: 1 | C35: =IF($B35="",$A35,$B35) -> 1 | D35: Configuration Management | E35: CM-2.1 | F35: Baseline Configuration | G35: Do you have a current configuration baseline documented for the information system? (The baseline configuration is a documented, up-to-date specification to which the information system is built.) | H35: ='5. Configuration'!$I4 -> Comment is required | I35: ='5. Configuration'!$H4 -> 0 | J35: =IF($I35="Yes","Adequate",IF($I35="No","Inadequate",IF($I35="Partial","Inadequate",IF($I35="N/A","Inadequate",IF(OR($I35="",$I35=0),"Blank","Error"))))) -> Blank | K35: No Override | L35: =IF($K35="No Override",$J35,$K35) -> Blank | N35: =IF($J35=$L35,"","***") | O35: =IF(OR($I35="",$I35=0),"",$I35) | P35: =IF(OR($H35="",$H35=0),"",$H35) -> Comment is required | Q35: =$L35 -> Blank | R35: =$K35 -> No Override | S35: =$C35 -> 1 | T35: =IF($L35=$Q35,"","***")
